Workbook

Sheet Léeme
A1: Métodos de valuación en el tiempo
A2: Emisores: NNN, O, WPC · datos al 28-09-2026 · generado el 13-10-2026
A3: Azul sobre amarillo: insumo, editable. Negro: fórmula o valor calculado por el estudio. Herramienta de análisis, no asesoría de inversión.
A5: Umbrales de la señal (percentil contra la historia propia)
A6: Barato desde el percentil | B6: 0.7
A7: Caro abajo del percentil | B7: 0.3
A9: Supuestos de los modelos de valor (hojas «… valor»)
A10: Prima de riesgo sobre el Treasury | B10: 0.03
A11: Crecimiento del dividendo: mínimo | B11: 0
A12: Crecimiento del dividendo: máximo | B12: 0.04
A13: Crecimiento del flujo, 5 años: mínimo | B13: 0
A14: Crecimiento del flujo, 5 años: máximo | B14: 0.08
A15: Crecimiento perpetuo después | B15: 0.02
A16: r − g mínimo | B16: 0.02
A17: Crecimiento entregado: mínimo | B17: -0.05
A18: Crecimiento entregado: máximo | B18: 0.1
A19: Margen de la señal absoluta de valor | B19: 0.15
A20: Margen de la señal absoluta de crecimiento | B20: 0.01
A22: Los métodos
A23: Múltiplo P/FFO | B23: Precio ÷ flujo por acción conocido (FFO de Nareit; AFFO en WPC). Barato = múltiplo bajo contra su propia historia.
A24: Prima sobre el Treasury | B24: Yield de flujo menos el Treasury a 10 años. Es la Puerta 2 del semáforo.
A25: Prima sobre la tasa real | B25: Yield de flujo menos la tasa real: Treasury a 10 años menos la inflación de 12 meses. El flujo de un REIT crece con la inflación; compararlo contra una tasa nominal castiga los años de inflación alta.
A26: Prima sobre bonos Baa | B26: Yield de flujo menos el rendimiento de los bonos corporativos Baa (Moody's): contra la alternativa de crédito, no contra la libre de riesgo.
A27: Yield de dividendo | B27: Dividendo regular vigente anualizado ÷ precio, contra su propia historia.
A28: Dividendo sobre el Treasury | B28: Yield de dividendo menos el Treasury a 10 años: la lente «contra el bono» del estudio.
A29: Múltiplo contra sus últimos 5 años | B29: Yield de flujo entre su mediana de los cinco años previos. No compara contra toda la historia sino contra el régimen reciente de tasas.
A30: Consenso de los siete | B30: El promedio de los percentiles de los siete métodos (con al menos cuatro disponibles). Es la regla que se recomienda: no se escoge el método que mejor salió, porque con 21 intentos el mejor siempre sale bien por azar.
A31: DDM (Gordon sobre el dividendo) | B31: Dividendo vigente × (1 + g) ÷ (r − g); g = crecimiento del dividendo de los 5 años previos, entre 0% y 4%; r = Treasury a 10 años + 3%. La señal es valor ÷ precio − 1.
A32: DCF del flujo en dos etapas | B32: AFFO por acción (FFO donde no hay) creciendo 5 años a su ritmo de los 5 previos (0% a 8%) y después 2% perpetuo, descontado a r. La señal es valor ÷ precio − 1.
A33: Crecimiento entregado contra implícito | B33: El crecimiento del flujo por acción de los 5 años previos menos el crecimiento perpetuo que justifica el precio con r. Positivo: el mercado descuenta menos de lo que el emisor ha hecho.
A34: NAV aproximado | B34: NOI anualizado del último trimestre ÷ el cap rate de las compras del propio emisor, menos deuda neta y preferentes, por acción. La señal es NAV ÷ precio − 1.
A36: Cómo se calculó
A37: • | B37: Point-in-time (P1): el flujo por acción es el de los últimos 12 meses conocido a cada fecha, con la fecha real de publicación de cada cifra; el Treasury y los bonos Baa, el dato del día hábil anterior; el CPI de un mes, 45 días después de su fecha, que es cuando se publica.
A38: • | B38: Percentil expandible (P5): cada fin de mes contra todos los fines de mes anteriores del mismo emisor, con al menos 36. Nunca contra otro emisor (P4): un yield de 7% puede ser caro en uno y barato en otro.
A39: • | B39: Retornos siguientes: retorno total en dólares con el dividendo neto del 20% de impuesto, anualizado. La alternativa de esperar es el T-bill a 3 meses de esos mismos años, neto del 20%.
A40: • | B40: La evaluación usa fines de trimestre para no contar tres veces casi el mismo mes. Aun así las ventanas de 5 años se enciman: las independientes son una por cada 20 trimestres.
A41: • | B41: Backtest por emisor: la regla de «solo compras, reinversión en 12 meses» del estudio de reglas, con el percentil del método en lugar de la prima del semáforo y sin las puertas de calidad ni de deterioro: barato compra todo y la reserva, medio la mitad, caro nada; nunca vende.
A42: • | B42: Asignación entre emisores: desde el primer mes en que los tres tienen percentil del método; la decisión de fin de mes se ejecuta al cierre de la sesión siguiente; 0.25% de comisión, 20% al dividendo y 10% a la ganancia al vender todo al final. El benchmark reparte en tercios y cada emisor reinvierte sus propios dividendos (P6 llevado a tres papeles).
A43: • | B43: Controles: el espejo (todo al más caro) y cada mitad del periodo por separado, con su propia TIR, se fijaron antes de ver el resultado. El azar se endureció después: la primera versión sorteaba el emisor cada mes, reparte sola el dinero entre los tres y cualquier método le ganaba; la que queda conserva las rachas del método (200 sorteos, semilla fija, reproducible).
A44: • | B44: Pruebas múltiples: siete métodos en tres emisores son 21 intentos. Por eso se recomienda el consenso y no el mejor, y por eso se exige que el resultado aparezca en los tres emisores y en las dos mitades. El consenso se definió después de ver los siete: no escoge por resultado, pero tampoco es una prueba a ciegas.
A45: • | B45: Sesgo de supervivencia: O, NNN y WPC existen hoy y se escogieron hoy. La reversión a la media que aprovecha la asignación es la de emisores que sobrevivieron; en uno que se está muriendo, «barato» es una trampa. La regla solo debe repartir entre emisores que pasan la Puerta 1.
A46: • | B46: Diseño fijado antes de correr, en su propio commit: supuestos, umbrales de la señal absoluta e hipótesis. La prueba 54 los congela.
A47: • | B47: Tasa de descuento: Treasury a 10 años + 3% (la prima de net lease de la aplicación). La señal absoluta se reporta también con 2% y 4%.
A48: • | B48: DDM: dividendo vigente anualizado; crecimiento del dividendo de los 5 años previos, entre 0% y 4% y con r − g de al menos 2%. DCF: AFFO por acción (FFO donde no hay) 5 años a su crecimiento de los 5 previos (0% a 8%) y 2% perpetuo después.
... A54: • | B54: Señal absoluta: barato si el valor supera al precio en 15% o más, caro si queda 15% o más abajo; en crecimiento, ±1 punto. Contra su historia: percentil expandible ≥ 70 barato, < 30 caro.

Sheet Hoy
A1: Método | B1: Percentil NNN | C1: Percentil O | D1: Percentil WPC | E1: Señal NNN | F1: Señal O | G1: Señal WPC
A2: Múltiplo P/FFO | B2: 0.63647643 | C2: 0.76760563 | D2: 0.36750789 | E2: =IF(B2="","",IF(B2>='Léeme'!$B$6,"barato",IF(B2<'Léeme'!$B$7,"caro","medio"))) | F2: =IF(C2="","",IF(C2>='Léeme'!$B$6,"barato",IF(C2<'Léeme'!$B$7,"caro","medio"))) | G2: =IF(D2="","",IF(D2>='Léeme'!$B$6,"barato",IF(D2<'Léeme'!$B$7,"caro","medio")))
A3: Prima sobre el Treasury | B3: 0.39826303 | C3: 0.40985915 | D3: 0.011041009 | E3: =IF(B3="","",IF(B3>='Léeme'!$B$6,"barato",IF(B3<'Léeme'!$B$7,"caro","medio"))) | F3: =IF(C3="","",IF(C3>='Léeme'!$B$6,"barato",IF(C3<'Léeme'!$B$7,"caro","medio"))) | G3: =IF(D3="","",IF(D3>='Léeme'!$B$6,"barato",IF(D3<'Léeme'!$B$7,"caro","medio")))
A4: Prima sobre la tasa real | B4: 0.58188586 | C4: 0.6915493 | D4: 0.14984227 | E4: =IF(B4="","",IF(B4>='Léeme'!$B$6,"barato",IF(B4<'Léeme'!$B$7,"caro","medio"))) | F4: =IF(C4="","",IF(C4>='Léeme'!$B$6,"barato",IF(C4<'Léeme'!$B$7,"caro","medio"))) | G4: =IF(D4="","",IF(D4>='Léeme'!$B$6,"barato",IF(D4<'Léeme'!$B$7,"caro","medio")))
A5: Prima sobre bonos Baa | B5: 0.6439206 | C5: 0.81267606 | D5: 0.093059937 | E5: =IF(B5="","",IF(B5>='Léeme'!$B$6,"barato",IF(B5<'Léeme'!$B$7,"caro","medio"))) | F5: =IF(C5="","",IF(C5>='Léeme'!$B$6,"barato",IF(C5<'Léeme'!$B$7,"caro","medio"))) | G5: =IF(D5="","",IF(D5>='Léeme'!$B$6,"barato",IF(D5<'Léeme'!$B$7,"caro","medio")))
A6: Yield de dividendo | B6: 0.46642686 | C6: 0.57942708 | D6: 0.35714286 | E6: =IF(B6="","",IF(B6>='Léeme'!$B$6,"barato",IF(B6<'Léeme'!$B$7,"caro","medio"))) | F6: =IF(C6="","",IF(C6>='Léeme'!$B$6,"barato",IF(C6<'Léeme'!$B$7,"caro","medio"))) | G6: =IF(D6="","",IF(D6>='Léeme'!$B$6,"barato",IF(D6<'Léeme'!$B$7,"caro","medio")))
A7: Dividendo sobre el Treasury | B7: 0.010791367 | C7: 0.014322917 | D7: 0.0043731778 | E7: =IF(B7="","",IF(B7>='Léeme'!$B$6,"barato",IF(B7<'Léeme'!$B$7,"caro","medio"))) | F7: =IF(C7="","",IF(C7>='Léeme'!$B$6,"barato",IF(C7<'Léeme'!$B$7,"caro","medio"))) | G7: =IF(D7="","",IF(D7>='Léeme'!$B$6,"barato",IF(D7<'Léeme'!$B$7,"caro","medio")))
A8: Múltiplo contra sus últimos 5 años | B8: 0.70435967 | C8: 0.98275862 | D8: 0.73843416 | E8: =IF(B8="","",IF(B8>='Léeme'!$B$6,"barato",IF(B8<'Léeme'!$B$7,"caro","medio"))) | F8: =IF(C8="","",IF(C8>='Léeme'!$B$6,"barato",IF(C8<'Léeme'!$B$7,"caro","medio"))) | G8: =IF(D8="","",IF(D8>='Léeme'!$B$6,"barato",IF(D8<'Léeme'!$B$7,"caro","medio")))
A9: Consenso de los siete | B9: 0.49173197 | C9: 0.60831411 | D9: 0.24591447 | E9: =IF(B9="","",IF(B9>='Léeme'!$B$6,"barato",IF(B9<'Léeme'!$B$7,"caro","medio"))) | F9: =IF(C9="","",IF(C9>='Léeme'!$B$6,"barato",IF(C9<'Léeme'!$B$7,"caro","medio"))) | G9: =IF(D9="","",IF(D9>='Léeme'!$B$6,"barato",IF(D9<'Léeme'!$B$7,"caro","medio")))

Sheet Asignación
A1: A cuál de los tres va la aportación del mes: al de percentil más alto contra su propia historia
A3: Método | B3: Desde | C3: TIR | D3: TIR partes iguales | E3: Ventaja | F3: Ventaja al más caro | G3: Ventaja 1ª mitad | H3: Ventaja 2ª mitad | I3: Azar que la iguala | J3: Cambios de emisor | K3: Hoy va a
A4: Múltiplo P/FFO | B4: 37742 | C4: 0.08512453 | D4: 0.078219663 | E4: 69 | F4: -59 | G4: 177 | H4: 88 | I4: 0 | J4: 46 | K4: O
A5: Prima sobre el Treasury | B5: 37742 | C5: 0.0834971 | D5: 0.078219663 | E5: 53 | F5: -34 | G5: 145 | H5: 62 | I5: 0.005 | J5: 51 | K5: O
A6: Prima sobre la tasa real | B6: 37742 | C6: 0.082734053 | D6: 0.078219663 | E6: 45 | F6: -52 | G6: 129 | H6: 39 | I6: 0.005 | J6: 41 | K6: O
A7: Prima sobre bonos Baa | B7: 37742 | C7: 0.084722222 | D7: 0.078219663 | E7: 65 | F7: -44 | G7: 190 | H7: 63 | I7: 0 | J7: 40 | K7: O
A8: Yield de dividendo | B8: 36951 | C8: 0.088748715 | D8: 0.083393574 | E8: 54 | F8: -58 | G8: 178 | H8: 48 | I8: 0.005 | J8: 59 | K8: O
A9: Dividendo sobre el Treasury | B9: 36951 | C9: 0.087675775 | D9: 0.083393574 | E9: 43 | F9: -45 | G9: 96 | H9: 59 | I9: 0.035 | J9: 39 | K9: WPC
A10: Múltiplo contra sus últimos 5 años | B10: 38838 | C10: 0.079293604 | D10: 0.073827403 | E10: 55 | F10: -42 | G10: 117 | H10: 101 | I10: 0.005 | J10: 57 | K10: O
A11: Consenso de los siete | B11: 37742 | C11: 0.085466481 | D11: 0.078219663 | E11: 72 | F11: -53 | G11: 167 | H11: 88 | I11: 0 | J11: 54 | K11: O
A13: Cada fin de trimestre, con el consenso de los siete
A14: Trimestre | B14: NNN | C14: O | D14: WPC | E14: La aportación va a
A15: 1996-T1 | B15: 0.72323794 | E15: =IF(COUNT(B15:D15)<3,"—",INDEX($B$14:$D$14,MATCH(MAX(B15:D15),B15:D15,0)))
A16: 1996-T2 | B16: 0.39166667 | E16: =IF(COUNT(B16:D16)<3,"—",INDEX($B$14:$D$14,MATCH(MAX(B16:D16),B16:D16,0)))
A17: 1996-T3 | B17: 0.5244798 | E17: =IF(COUNT(B17:D17)<3,"—",INDEX($B$14:$D$14,MATCH(MAX(B17:D17),B17:D17,0)))
A18: 1996-T4 | B18: 0.17693237 | E18: =IF(COUNT(B18:D18)<3,"—",INDEX($B$14:$D$14,MATCH(MAX(B18:D18),B18:D18,0)))
A19: 1997-T1 | B19: 0.42139078 | E19: =IF(COUNT(B19:D19)<3,"—",INDEX($B$14:$D$14,MATCH(MAX(B19:D19),B19:D19,0)))
A20: 1997-T2 | B20: 0.33459596 | E20: =IF(COUNT(B20:D20)<3,"—",INDEX($B$14:$D$14,MATCH(MAX(B20:D20),B20:D20,0)))
A21: 1997-T3 | B21: 0.30048309 | E21: =IF(COUNT(B21:D21)<3,"—",INDEX($B$14:$D$14,MATCH(MAX(B21:D21),B21:D21,0)))
A22: 1997-T4 | B22: 0.12188697 | E22: =IF(COUNT(B22:D22)<3,"—",INDEX($B$14:$D$14,MATCH(MAX(B22:D22),B22:D22,0)))
A23: 1998-T1 | B23: 0.24626594 | E23: =IF(COUNT(B23:D23)<3,"—",INDEX($B$14:$D$14,MATCH(MAX(B23:D23),B23:D23,0)))
A24: 1998-T2 | B24: 0.6149172 | E24: =IF(COUNT(B24:D24)<3,"—",INDEX($B$14:$D$14,MATCH(MAX(B24:D24),B24:D24,0)))
A25: 1998-T3 | B25: 0.89453965 | E25: =IF(COUNT(B25:D25)<3,"—",INDEX($B$14:$D$14,MATCH(MAX(B25:D25),B25:D25,0)))
A26: 1998-T4 | B26: 0.95277778 | E26: =IF(COUNT(B26:D26)<3,"—",INDEX($B$14:$D$14,MATCH(MAX(B26:D26),B26:D26,0)))
... A30: 1999-T4 | B30: 0.99347479 | E30: =IF(COUNT(B30:D30)<3,"—",INDEX($B$14:$D$14,MATCH(MAX(B30:D30),B30:D30,0)))
A31: 2000-T1 | B31: 0.98168913 | C31: 0.98846574 | E31: =IF(COUNT(B31:D31)<3,"—",INDEX($B$14:$D$14,MATCH(MAX(B31:D31),B31:D31,0)))
A32: 2000-T2 | B32: 0.96753981 | C32: 0.73737923 | E32: =IF(COUNT(B32:D32)<3,"—",INDEX($B$14:$D$14,MATCH(MAX(B32:D32),B32:D32,0)))
A33: 2000-T3 | B33: 0.98438228 | C33: 0.81503015 | E33: =IF(COUNT(B33:D33)<3,"—",INDEX($B$14:$D$14,MATCH(MAX(B33:D33),B33:D33,0)))
A34: 2000-T4 | B34: 0.97602647 | C34: 0.71043478 | E34: =IF(COUNT(B34:D34)<3,"—",INDEX($B$14:$D$14,MATCH(MAX(B34:D34),B34:D34,0)))
A35: 2001-T1 | B35: 0.78910503 | C35: 0.55926217 | E35: =IF(COUNT(B35:D35)<3,"—",INDEX($B$14:$D$14,MATCH(MAX(B35:D35),B35:D35,0)))
A36: 2001-T2 | B36: 0.56400768 | C36: 0.31604147 | E36: =IF(COUNT(B36:D36)<3,"—",INDEX($B$14:$D$14,MATCH(MAX(B36:D36),B36:D36,0)))
A37: 2001-T3 | B37: 0.67171407 | C37: 0.40743146 | E37: =IF(COUNT(B37:D37)<3,"—",INDEX($B$14:$D$14,MATCH(MAX(B37:D37),B37:D37,0)))
A38: 2001-T4 | B38: 0.65182743 | C38: 0.28639847 | E38: =IF(COUNT(B38:D38)<3,"—",INDEX($B$14:$D$14,MATCH(MAX(B38:D38),B38:D38,0)))
A39: 2002-T1 | B39: 0.50309328 | C39: 0.062416515 | E39: =IF(COUNT(B39:D39)<3,"—",INDEX($B$14:$D$14,MATCH(MAX(B39:D39),B39:D39,0)))
A40: 2002-T2 | B40: 0.33271423 | C40: 0.058775762 | E40: =IF(COUNT(B40:D40)<3,"—",INDEX($B$14:$D$14,MATCH(MAX(B40:D40),B40:D40,0)))
A41: 2002-T3 | B41: 0.43938251 | C41: 0.33771248 | E41: =IF(COUNT(B41:D41)<3,"—",INDEX($B$14:$D$14,MATCH(MAX(B41:D41),B41:D41,0)))
A42: 2002-T4 | B42: 0.53157498 | C42: 0.29386724 | E42: =IF(COUNT(B42:D42)<3,"—",INDEX($B$14:$D$14,MATCH(MAX(B42:D42),B42:D42,0)))
A43: 2003-T1 | B43: 0.57245925 | C43: 0.32728204 | E43: =IF(COUNT(B43:D43)<3,"—",INDEX($B$14:$D$14,MATCH(MAX(B43:D43),B43:D43,0)))
A44: 2003-T2 | B44: 0.37036021 | C44: 0.2454753 | D44: 0.27001096 | E44: =IF(COUNT(B44:D44)<3,"—",INDEX($B$14:$D$14,MATCH(MAX(B44:D44),B44:D44,0)))
A45: 2003-T3 | B45: 0.36979913 | C45: 0.17069567 | D45: 0.096893581 | E45: =IF(COUNT(B45:D45)<3,"—",INDEX($B$14:$D$14,MATCH(MAX(B45:D45),B45:D45,0)))
A46: 2003-T4 | B46: 0.30865937 | C46: 0.15363049 | D46: 0.19805195 | E46: =IF(COUNT(B46:D46)<3,"—",INDEX($B$14:$D$14,MATCH(MAX(B46:D46),B46:D46,0)))
A47: 2004-T1 | B47: 0.23852473 | C47: 0.1311496 | D47: 0.21762363 | E47: =IF(COUNT(B47:D47)<3,"—",INDEX($B$14:$D$14,MATCH(MAX(B47:D47),B47:D47,0)))
A48: 2004-T2 | B48: 0.38081232 | C48: 0.16740204 | D48: 0.21736842 | E48: =IF(COUNT(B48:D48)<3,"—",INDEX($B$14:$D$14,MATCH(MAX(B48:D48),B48:D48,0)))
A49: 2004-T3 | B49: 0.36339231 | C49: 0.1613458 | D49: 0.33890614 | E49: =IF(COUNT(B49:D49)<3,"—",INDEX($B$14:$D$14,MATCH(MAX(B49:D49),B49:D49,0)))
A50: 2004-T4 | B50: 0.23404116 | C50: 0.078912106 | D50: 0.06155633 | E50: =IF(COUNT(B50:D50)<3,"—",INDEX($B$14:$D$14,MATCH(MAX(B50:D50),B50:D50,0)))
A51: 2005-T1 | B51: 0.33520569 | C51: 0.20931618 | D51: 0.67637089 | E51: =IF(COUNT(B51:D51)<3,"—",INDEX($B$14:$D$14,MATCH(MAX(B51:D51),B51:D51,0)))
A52: 2005-T2 | B52: 0.23779626 | C52: 0.13540732 | D52: 0.73717009 | E52: =IF(COUNT(B52:D52)<3,"—",INDEX($B$14:$D$14,MATCH(MAX(B52:D52),B52:D52,0)))
A53: 2005-T3 | B53: 0.25336592 | C53: 0.22850835 | D53: 0.77692308 | E53: =IF(COUNT(B53:D53)<3,"—",INDEX($B$14:$D$14,MATCH(MAX(B53:D53),B53:D53,0)))
A54: 2005-T4 | B54: 0.20794813 | C54: 0.44541066 | D54: 0.79312683 | E54: =IF(COUNT(B54:D54)<3,"—",INDEX($B$14:$D$14,MATCH(MAX(B54:D54),B54:D54,0)))
A55: 2006-T1 | B55: 0.07874622 | C55: 0.25282373 | D55: 0.32815449 | E55: =IF(COUNT(B55:D55)<3,"—",INDEX($B$14:$D$14,MATCH(MAX(B55:D55),B55:D55,0)))
... A137: 2026-T3 | B137: 0.49173197 | C137: 0.60831411 | D137: 0.24591447 | E137: =IF(COUNT(B137:D137)<3,"—",INDEX($B$14:$D$14,MATCH(MAX(B137:D137),B137:D137,0)))

Sheet Evaluación
A1: ¿Predicen? Percentil contra el retorno de los años siguientes, un renglón por trimestre
A3: NNN REIT, Inc. (NNN)
A4: Método | B4: Correlación 1 año | C4: Correlación 5 años | D4: 5 años si barato | E4: 5 años si medio | F4: 5 años si caro | G4: Brecha barato − caro | H4: Caro contra el efectivo | I4: Veces que caro le ganó al efectivo | J4: TIR con el método (solo ese papel) | K4: TIR sin reglas | L4: Ventaja
A5: Múltiplo P/FFO | B5: 0.291 | C5: 0.457 | D5: 0.19329794 | E5: 0.13565686 | F5: 0.08054282 | G5: 0.11275512 | H5: 0.068255118 | I5: 0.84615385 | J5: 0.086491103 | K5: 0.088193309 | L5: -17
A6: Prima sobre el Treasury | B6: 0.293 | C6: 0.529 | D6: 0.17385414 | E6: 0.095283298 | F6: 0.080522553 | G6: 0.093331582 | H6: 0.064925063 | I6: 0.73684211 | J6: 0.087054545 | K6: 0.088193309 | L6: -11
A7: Prima sobre la tasa real | B7: 0.141 | C7: 0.553 | D7: 0.16335406 | E7: 0.097781598 | F7: 0.08054282 | G7: 0.082811244 | H7: 0.052892207 | I7: 0.8 | J7: 0.086941905 | K7: 0.088193309 | L7: -13
A8: Prima sobre bonos Baa | B8: 0.222 | C8: 0.369 | D8: 0.16335406 | E8: 0.085254279 | F8: 0.1002799 | G8: 0.063074166 | H8: 0.09165513 | I8: 0.85714286 | J8: 0.087090746 | K8: 0.088193309 | L8: -11
A9: Yield de dividendo | B9: 0.332 | C9: 0.471 | D9: 0.20539413 | E9: 0.10331107 | F9: 0.088431034 | G9: 0.1169631 | H9: 0.069652062 | I9: 0.86842105 | J9: 0.087386167 | K9: 0.088193309 | L9: -8
A10: Dividendo sobre el Treasury | B10: 0.392 | C10: 0.593 | D10: 0.16069914 | E10: 0.10485413 | F10: 0.055720961 | G10: 0.10497818 | H10: 0.037848204 | I10: 0.73684211 | J10: 0.088142577 | K10: 0.088193309 | L10: -1
A11: Múltiplo contra sus últimos 5 años | B11: 0.126 | C11: 0.19 | D11: 0.16335406 | E11: 0.088094521 | F11: 0.11095707 | G11: 0.05239699 | H11: 0.10322296 | I11: 0.9375 | J11: 0.086056558 | K11: 0.088193309 | L11: -21
A12: Consenso de los siete | B12: 0.299 | C12: 0.534 | D12: 0.20070335 | E12: 0.1123695 | F12: 0.073373941 | G12: 0.12732941 | H12: 0.05665649 | I12: 0.75 | J12: 0.087359293 | K12: 0.088193309 | L12: -8
A15: Realty Income Corporation (O)
A16: Método | B16: Correlación 1 año | C16: Correlación 5 años | D16: 5 años si barato | E16: 5 años si medio | F16: 5 años si caro | G16: Brecha barato − caro | H16: Caro contra el efectivo | I16: Veces que caro le ganó al efectivo | J16: TIR con el método (solo ese papel) | K16: TIR sin reglas | L16: Ventaja
A17: Múltiplo P/FFO | B17: 0.379 | C17: 0.456 | D17: 0.22335445 | E17: 0.16924143 | F17: 0.1024585 | G17: 0.12089595 | H17: 0.092663669 | I17: 0.91304348 | J17: 0.094894533 | K17: 0.098350613 | L17: -35
A18: Prima sobre el Treasury | B18: 0.386 | C18: 0.277 | D18: 0.1765465 | E18: 0.11776756 | F18: 0.10919198 | G18: 0.067354524 | H18: 0.093971742 | I18: 0.86666667 | J18: 0.096684669 | K18: 0.098350613 | L18: -17
A19: Prima sobre la tasa real | B19: 0.057 | C19: 0.296 | D19: 0.1765465 | E19: 0.10362004 | F19: 0.1024585 | G19: 0.074087998 | H19: 0.092663669 | I19: 0.90322581 | J19: 0.095193882 | K19: 0.098350613 | L19: -32
A20: Prima sobre bonos Baa | B20: 0.331 | C20: 0.004 | D20: 0.079839022 | E20: 0.11463509 | F20: 0.11909432 | G20: -0.039255303 | H20: 0.11127447 | I20: 0.95348837 | J20: 0.095736981 | K20: 0.098350613 | L20: -26
A21: Yield de dividendo | B21: 0.26 | C21: 0.608 | D21: 0.22335445 | E21: 0.17156391 | F21: 0.10753134 | G21: 0.11582312 | H21: 0.093971742 | I21: 0.91891892 | J21: 0.095092804 | K21: 0.098350613 | L21: -33
A22: Dividendo sobre el Treasury | B22: 0.344 | C22: 0.45 | D22: 0.18076528 | E22: 0.11313833 | F22: 0.11652919 | G22: 0.06423609 | H22: 0.092663669 | I22: 0.86956522 | J22: 0.097658684 | K22: 0.098350613 | L22: -7
A23: Múltiplo contra sus últimos 5 años | B23: 0.221 | C23: 0.295 | D23: 0.13182595 | E23: 0.1024585 | F23: 0.090192221 | G23: 0.041633731 | H23: 0.068002232 | I23: 0.9 | J23: 0.098158103 | K23: 0.098350613 | L23: -2
A24: Consenso de los siete | B24: 0.372 | C24: 0.363 | D24: 0.1992985 | E24: 0.12887686 | F24: 0.09395317 | G24: 0.10534533 | H24: 0.080651241 | I24: 0.84615385 | J24: 0.096253274 | K24: 0.098350613 | L24: -21
A27: W. P. Carey Inc. (WPC)
A28: Método | B28: Correlación 1 año | C28: Correlación 5 años | D28: 5 años si barato | E28: 5 años si medio | F28: 5 años si caro | G28: Brecha barato − caro | H28: Caro contra el efectivo | I28: Veces que caro le ganó al efectivo | J28: TIR con el método (solo ese papel) | K28: TIR sin reglas | L28: Ventaja
A29: Múltiplo P/FFO | B29: 0.265 | C29: 0.566 | D29: 0.24273252 | E29: 0.15465159 | F29: 0.063224995 | G29: 0.17950752 | H29: 0.05525272 | I29: 0.80851064 | J29: 0.090092894 | K29: 0.093423565 | L29: -33
A30: Prima sobre el Treasury | B30: 0.371 | C30: 0.505 | D30: 0.16289105 | E30: 0.09062331 | F30: 0.048635575 | G30: 0.11425547 | H30: 0.044337829 | I30: 0.64 | J30: 0.092871538 | K30: 0.093423565 | L30: -6
A31: Prima sobre la tasa real | B31: 0.134 | C31: 0.459 | D31: 0.13997026 | E31: 0.099738104 | F31: 0.063224995 | G31: 0.076745262 | H31: 0.05525272 | I31: 0.73913043 | J31: 0.092239918 | K31: 0.093423565 | L31: -12
A32: Prima sobre bonos Baa | B32: 0.355 | C32: 0.481 | D32: 0.12762155 | E32: 0.074800862 | F32: 0.049505848 | G32: 0.078115707 | H32: 0.046014087 | I32: 0.66666667 | J32: 0.094189423 | K32: 0.093423565 | L32: 8
A33: Yield de dividendo | B33: 0.25 | C33: 0.326 | D33: 0.27513493 | E33: 0.10445089 | F33: 0.083385306 | G33: 0.19174963 | H33: 0.067138624 | I33: 0.78571429 | J33: 0.090632689 | K33: 0.093423565 | L33: -28
A34: Dividendo sobre el Treasury | B34: 0.312 | C34: 0.15 | D34: 0.09062331 | E34: 0.099123437 | F34: 0.11837699 | G34: -0.027753682 | H34: 0.096731235 | I34: 0.73684211 | J34: 0.092070981 | K34: 0.093423565 | L34: -14
A35: Múltiplo contra sus últimos 5 años | B35: 0.051 | C35: 0.304 | D35: 0.11132289 | E35: 0.11304145 | F35: 0.07704271 | G35: 0.034280182 | H35: 0.068548684 | I35: 0.80952381 | J35: 0.091881831 | K35: 0.093423565 | L35: -15
A36: Consenso de los siete | B36: 0.375 | C36: 0.525 | D36: 0.24011409 | E36: 0.095746783 | F36: 0.04249346 | G36: 0.19762063 | H36: 0.029337581 | I36: 0.57142857 | J36: 0.092251909 | K36: 0.093423565 | L36: -12

Sheet NNN
A1: Trimestre | B1: Fecha | C1: Precio | D1: Flujo por acción, 12 meses | E1: Dividendo anualizado | F1: Treasury 10 años | G1: Inflación 12 meses | H1: Bonos Baa | I1: Múltiplo precio/flujo | J1: Yield de flujo | K1: Yield de dividendo | L1: Tasa real | M1: Prima sobre el Treasury | N1: Prima sobre la tasa real | O1: Prima sobre bonos Baa | P1: Dividendo sobre el Treasury | Q1: Percentil: Múltiplo P/FFO | R1: Percentil: Prima sobre el Treasury | S1: Percentil: Prima sobre la tasa real | T1: Percentil: Prima sobre bonos Baa | U1: Percentil: Yield de dividendo | V1: Percentil: Dividendo sobre el Treasury | W1: Percentil: Múltiplo contra sus últimos 5 años | X1: Percentil: Consenso de los siete | Y1: Señal del consenso | Z1: Retorno anual, 1 año después | AA1: Retorno anual, 5 años después
A2: 1992-T1 | B2: 33694 | C2: 9.875 | E2: 1.08 | F2: 0.0754 | G2: 0.028189911 | H2: 0.0922 | I2: =IFERROR(C2/D2,"") | J2: =IFERROR(D2/C2,"") | K2: =IFERROR(E2/C2,"") | L2: =IFERROR(F2-G2,"") | M2: =IFERROR(J2-F2,"") | N2: =IFERROR(J2-L2,"") | O2: =IFERROR(J2-H2,"") | P2: =IFERROR(K2-F2,"") | Y2: =IF(X2="","",IF(X2>='Léeme'!$B$6,"barato",IF(X2<'Léeme'!$B$7,"caro","medio"))) | Z2: 0.5178514 | AA2: 0.16304417
A3: 1992-T2 | B3: 33785 | C3: 10 | E3: 1.08 | F3: 0.0714 | G3: 0.030235988 | H3: 0.09 | I3: =IFERROR(C3/D3,"") | J3: =IFERROR(D3/C3,"") | K3: =IFERROR(E3/C3,"") | L3: =IFERROR(F3-G3,"") | M3: =IFERROR(J3-F3,"") | N3: =IFERROR(J3-L3,"") | O3: =IFERROR(J3-H3,"") | P3: =IFERROR(K3-F3,"") | Y3: =IF(X3="","",IF(X3>='Léeme'!$B$6,"barato",IF(X3<'Léeme'!$B$7,"caro","medio"))) | Z3: 0.45112217 | AA3: 0.16773688
A4: 1992-T3 | B4: 33877 | C4: 11.625 | E4: 1.08 | F4: 0.0637 | G4: 0.030746706 | H4: 0.0865 | I4: =IFERROR(C4/D4,"") | J4: =IFERROR(D4/C4,"") | K4: =IFERROR(E4/C4,"") | L4: =IFERROR(F4-G4,"") | M4: =IFERROR(J4-F4,"") | N4: =IFERROR(J4-L4,"") | O4: =IFERROR(J4-H4,"") | P4: =IFERROR(K4-F4,"") | Y4: =IF(X4="","",IF(X4>='Léeme'!$B$6,"barato",IF(X4<'Léeme'!$B$7,"caro","medio"))) | Z4: 0.28902578 | AA4: 0.14100136
A5: 1992-T4 | B5: 33969 | C5: 12.125 | E5: 1.08 | F5: 0.067 | G5: 0.031204644 | H5: 0.0874 | I5: =IFERROR(C5/D5,"") | J5: =IFERROR(D5/C5,"") | K5: =IFERROR(E5/C5,"") | L5: =IFERROR(F5-G5,"") | M5: =IFERROR(J5-F5,"") | N5: =IFERROR(J5-L5,"") | O5: =IFERROR(J5-H5,"") | P5: =IFERROR(K5-F5,"") | Y5: =IF(X5="","",IF(X5>='Léeme'!$B$6,"barato",IF(X5<'Léeme'!$B$7,"caro","medio"))) | Z5: 0.21136269 | AA5: 0.15694074
A6: 1993-T1 | B6: 34059 | C6: 13.875 | D6: 1.15 | E6: 1.08 | F6: 0.0603 | G6: 0.032467532 | H6: 0.082 | I6: =IFERROR(C6/D6,"") | J6: =IFERROR(D6/C6,"") | K6: =IFERROR(E6/C6,"") | L6: =IFERROR(F6-G6,"") | M6: =IFERROR(J6-F6,"") | N6: =IFERROR(J6-L6,"") | O6: =IFERROR(J6-H6,"") | P6: =IFERROR(K6-F6,"") | Y6: =IF(X6="","",IF(X6>='Léeme'!$B$6,"barato",IF(X6<'Léeme'!$B$7,"caro","medio"))) | Z6: 0.066950114 | AA6: 0.12212797
A7: 1993-T2 | B7: 34150 | C7: 13.5 | D7: 1.15 | E7: 1.08 | F7: 0.058 | G7: 0.032211883 | H7: 0.0795 | I7: =IFERROR(C7/D7,"") | J7: =IFERROR(D7/C7,"") | K7: =IFERROR(E7/C7,"") | L7: =IFERROR(F7-G7,"") | M7: =IFERROR(J7-F7,"") | N7: =IFERROR(J7-L7,"") | O7: =IFERROR(J7-H7,"") | P7: =IFERROR(K7-F7,"") | Y7: =IF(X7="","",IF(X7>='Léeme'!$B$6,"barato",IF(X7<'Léeme'!$B$7,"caro","medio"))) | Z7: 0.076982056 | AA7: 0.10907072
A8: 1993-T3 | B8: 34242 | C8: 14 | D8: 1.15 | E8: 1.12 | F8: 0.054 | G8: 0.028409091 | H8: 0.0736 | I8: =IFERROR(C8/D8,"") | J8: =IFERROR(D8/C8,"") | K8: =IFERROR(E8/C8,"") | L8: =IFERROR(F8-G8,"") | M8: =IFERROR(J8-F8,"") | N8: =IFERROR(J8-L8,"") | O8: =IFERROR(J8-H8,"") | P8: =IFERROR(K8-F8,"") | Y8: =IF(X8="","",IF(X8>='Léeme'!$B$6,"barato",IF(X8<'Léeme'!$B$7,"caro","medio"))) | Z8: -0.065884408 | AA8: 0.078706659
A9: 1993-T4 | B9: 34334 | C9: 13.75 | D9: 1.15 | E9: 1.12 | F9: 0.0583 | G9: 0.027445461 | H9: 0.0775 | I9: =IFERROR(C9/D9,"") | J9: =IFERROR(D9/C9,"") | K9: =IFERROR(E9/C9,"") | L9: =IFERROR(F9-G9,"") | M9: =IFERROR(J9-F9,"") | N9: =IFERROR(J9-L9,"") | O9: =IFERROR(J9-H9,"") | P9: =IFERROR(K9-F9,"") | Y9: =IF(X9="","",IF(X9>='Léeme'!$B$6,"barato",IF(X9<'Léeme'!$B$7,"caro","medio"))) | Z9: -0.045724961 | AA9: 0.061587366
A10: 1994-T1 | B10: 34424 | C10: 13.875 | D10: 1.05 | E10: 1.12 | F10: 0.0677 | G10: 0.025157233 | H10: 0.0832 | I10: =IFERROR(C10/D10,"") | J10: =IFERROR(D10/C10,"") | K10: =IFERROR(E10/C10,"") | L10: =IFERROR(F10-G10,"") | M10: =IFERROR(J10-F10,"") | N10: =IFERROR(J10-L10,"") | O10: =IFERROR(J10-H10,"") | P10: =IFERROR(K10-F10,"") | Y10: =IF(X10="","",IF(X10>='Léeme'!$B$6,"barato",IF(X10<'Léeme'!$B$7,"caro","medio"))) | Z10: -0.06130771 | AA10: 0.024797098
A11: 1994-T2 | B11: 34515 | C11: 13.625 | D11: 1.05 | E11: 1.12 | F11: 0.0734 | G11: 0.022884882 | H11: 0.0878 | I11: =IFERROR(C11/D11,"") | J11: =IFERROR(D11/C11,"") | K11: =IFERROR(E11/C11,"") | L11: =IFERROR(F11-G11,"") | M11: =IFERROR(J11-F11,"") | N11: =IFERROR(J11-L11,"") | O11: =IFERROR(J11-H11,"") | P11: =IFERROR(K11-F11,"") | Y11: =IF(X11="","",IF(X11>='Léeme'!$B$6,"barato",IF(X11<'Léeme'!$B$7,"caro","medio"))) | Z11: 0.03779907 | AA11: 0.058412264
A12: 1994-T3 | B12: 34607 | C12: 12.25 | D12: 1.05 | E12: 1.16 | F12: 0.0762 | G12: 0.029005525 | H12: 0.0916 | I12: =IFERROR(C12/D12,"") | J12: =IFERROR(D12/C12,"") | K12: =IFERROR(E12/C12,"") | L12: =IFERROR(F12-G12,"") | M12: =IFERROR(J12-F12,"") | N12: =IFERROR(J12-L12,"") | O12: =IFERROR(J12-H12,"") | P12: =IFERROR(K12-F12,"") | Y12: =IF(X12="","",IF(X12>='Léeme'!$B$6,"barato",IF(X12<'Léeme'!$B$7,"caro","medio"))) | Z12: 0.16664439 | AA12: 0.041344725
A13: 1994-T4 | B13: 34698 | C13: 12.25 | D13: 1.05 | E13: 1.16 | F13: 0.0784 | G13: 0.026027397 | H13: 0.091 | I13: =IFERROR(C13/D13,"") | J13: =IFERROR(D13/C13,"") | K13: =IFERROR(E13/C13,"") | L13: =IFERROR(F13-G13,"") | M13: =IFERROR(J13-F13,"") | N13: =IFERROR(J13-L13,"") | O13: =IFERROR(J13-H13,"") | P13: =IFERROR(K13-F13,"") | U13: 0.77777778 | V13: 0.26388889 | Y13: =IF(X13="","",IF(X13>='Léeme'!$B$6,"barato",IF(X13<'Léeme'!$B$7,"caro","medio"))) | Z13: 0.12075844 | AA13: 0.030659075
A14: 1995-T1 | B14: 34789 | C14: 12.125 | D14: 1.16 | E14: 1.16 | F14: 0.072 | G14: 0.028629857 | H14: 0.0866 | I14: =IFERROR(C14/D14,"") | J14: =IFERROR(D14/C14,"") | K14: =IFERROR(E14/C14,"") | L14: =IFERROR(F14-G14,"") | M14: =IFERROR(J14-F14,"") | N14: =IFERROR(J14-L14,"") | O14: =IFERROR(J14-H14,"") | P14: =IFERROR(K14-F14,"") | U14: 0.78205128 | V14: 0.57692308 | Y14: =IF(X14="","",IF(X14>='Léeme'!$B$6,"barato",IF(X14<'Léeme'!$B$7,"caro","medio"))) | Z14: 0.17520029 | AA14: 0.041351422
A15: 1995-T2 | B15: 34880 | C15: 13.125 | D15: 1.16 | E15: 1.16 | F15: 0.0621 | G15: 0.031186441 | H15: 0.0799 | I15: =IFERROR(C15/D15,"") | J15: =IFERROR(D15/C15,"") | K15: =IFERROR(E15/C15,"") | L15: =IFERROR(F15-G15,"") | M15: =IFERROR(J15-F15,"") | N15: =IFERROR(J15-L15,"") | O15: =IFERROR(J15-H15,"") | P15: =IFERROR(K15-F15,"") | U15: 0.44047619 | V15: 0.70238095 | Y15: =IF(X15="","",IF(X15>='Léeme'!$B$6,"barato",IF(X15<'Léeme'!$B$7,"caro","medio"))) | Z15: 0.1352454 | AA15: 0.027244433
A16: 1995-T3 | B16: 34971 | C16: 13.25 | D16: 1.16 | E16: 1.16 | F16: 0.0617 | G16: 0.026174497 | H16: 0.0795 | I16: =IFERROR(C16/D16,"") | J16: =IFERROR(D16/C16,"") | K16: =IFERROR(E16/C16,"") | L16: =IFERROR(F16-G16,"") | M16: =IFERROR(J16-F16,"") | N16: =IFERROR(J16-L16,"") | O16: =IFERROR(J16-H16,"") | P16: =IFERROR(K16-F16,"") | U16: 0.41111111 | V16: 0.61111111 | Y16: =IF(X16="","",IF(X16>='Léeme'!$B$6,"barato",IF(X16<'Léeme'!$B$7,"caro","medio"))) | Z16: 0.10344785 | AA16: 0.023564574
A17: 1995-T4 | B17: 35062 | C17: 12.75 | D17: 1.16 | E17: 1.16 | F17: 0.0558 | G17: 0.026034713 | H17: 0.0741 | I17: =IFERROR(C17/D17,"") | J17: =IFERROR(D17/C17,"") | K17: =IFERROR(E17/C17,"") | L17: =IFERROR(F17-G17,"") | M17: =IFERROR(J17-F17,"") | N17: =IFERROR(J17-L17,"") | O17: =IFERROR(J17-H17,"") | P17: =IFERROR(K17-F17,"") | U17: 0.57291667 | V17: 0.86458333 | Y17: =IF(X17="","",IF(X17>='Léeme'!$B$6,"barato",IF(X17<'Léeme'!$B$7,"caro","medio"))) | Z17: 0.31474716 | AA17: 0.029101653
A18: 1996-T1 | B18: 35153 | C18: 13.25 | D18: 1.24 | E18: 1.16 | F18: 0.0634 | G18: 0.027170311 | H18: 0.0817 | I18: =IFERROR(C18/D18,"") | J18: =IFERROR(D18/C18,"") | K18: =IFERROR(E18/C18,"") | L18: =IFERROR(F18-G18,"") | M18: =IFERROR(J18-F18,"") | N18: =IFERROR(J18-L18,"") | O18: =IFERROR(J18-H18,"") | P18: =IFERROR(K18-F18,"") | Q18: 0.90540541 | R18: 0.87837838 | S18: 0.7972973 | T18: 0.90540541 | U18: 0.37254902 | V18: 0.48039216 | X18: 0.72323794 | Y18: =IF(X18="","",IF(X18>='Léeme'!$B$6,"barato",IF(X18<'Léeme'!$B$7,"caro","medio"))) | Z18: 0.2012613 | AA18: 0.046060128
A19: 1996-T2 | B19: 35244 | C19: 13.875 | D19: 1.24 | E19: 1.16 | F19: 0.0673 | G19: 0.028270874 | H19: 0.0834 | I19: =IFERROR(C19/D19,"") | J19: =IFERROR(D19/C19,"") | K19: =IFERROR(E19/C19,"") | L19: =IFERROR(F19-G19,"") | M19: =IFERROR(J19-F19,"") | N19: =IFERROR(J19-L19,"") | O19: =IFERROR(J19-H19,"") | P19: =IFERROR(K19-F19,"") | Q19: 0.7125 | R19: 0.3625 | S19: 0.3375 | T19: 0.4375 | U19: 0.30555556 | V19: 0.19444444 | X19: 0.39166667 | Y19: =IF(X19="","",IF(X19>='Léeme'!$B$6,"barato",IF(X19<'Léeme'!$B$7,"caro","medio"))) | Z19: 0.17925981 | AA19: 0.072730985
A20: 1996-T3 | B20: 35338 | C20: 13.625 | D20: 1.24 | E20: 1.2 | F20: 0.0672 | G20: 0.028122956 | H20: 0.0821 | I20: =IFERROR(C20/D20,"") | J20: =IFERROR(D20/C20,"") | K20: =IFERROR(E20/C20,"") | L20: =IFERROR(F20-G20,"") | M20: =IFERROR(J20-F20,"") | N20: =IFERROR(J20-L20,"") | O20: =IFERROR(J20-H20,"") | P20: =IFERROR(K20-F20,"") | Q20: 0.8372093 | R20: 0.47674419 | S20: 0.40697674 | T20: 0.6627907 | U20: 0.42105263 | V20: 0.34210526 | X20: 0.5244798 | Y20: =IF(X20="","",IF(X20>='Léeme'!$B$6,"barato",IF(X20<'Léeme'!$B$7,"caro","medio"))) | Z20: 0.24760839 | AA20: 0.071915604
A21: 1996-T4 | B21: 35430 | C21: 15.875 | D21: 1.24 | E21: 1.2 | F21: 0.0643 | G21: 0.032530904 | H21: 0.0786 | I21: =IFERROR(C21/D21,"") | J21: =IFERROR(D21/C21,"") | K21: =IFERROR(E21/C21,"") | L21: =IFERROR(F21-G21,"") | M21: =IFERROR(J21-F21,"") | N21: =IFERROR(J21-L21,"") | O21: =IFERROR(J21-H21,"") | P21: =IFERROR(K21-F21,"") | Q21: 0.14130435 | R21: 0.27173913 | S21: 0.29347826 | T21: 0.27173913 | U21: 0.0083333333 | V21: 0.075 | X21: 0.17693237 | Y21: =IF(X21="","",IF(X21>='Léeme'!$B$6,"barato",IF(X21<'Léeme'!$B$7,"caro","medio"))) | Z21: 0.19773252 | AA21: 0.036030973
A22: 1997-T1 | B22: 35520 | C22: 14.75 | D22: 1.34 | E22: 1.2 | F22: 0.0692 | G22: 0.030322581 | H22: 0.0832 | I22: =IFERROR(C22/D22,"") | J22: =IFERROR(D22/C22,"") | K22: =IFERROR(E22/C22,"") | L22: =IFERROR(F22-G22,"") | M22: =IFERROR(J22-F22,"") | N22: =IFERROR(J22-L22,"") | O22: =IFERROR(J22-H22,"") | P22: =IFERROR(K22-F22,"") | Q22: 0.76530612 | R22: 0.37755102 | S22: 0.43877551 | T22: 0.58163265 | U22: 0.24603175 | V22: 0.11904762 | X22: 0.42139078 | Y22: =IF(X22="","",IF(X22>='Léeme'!$B$6,"barato",IF(X22<'Léeme'!$B$7,"caro","medio"))) | Z22: 0.26899568 | AA22: 0.067238807
A23: 1997-T2 | B23: 35611 | C23: 15.3125 | D23: 1.34 | E23: 1.2 | F23: 0.0651 | G23: 0.022378517 | H23: 0.0797 | I23: =IFERROR(C23/D23,"") | J23: =IFERROR(D23/C23,"") | K23: =IFERROR(E23/C23,"") | L23: =IFERROR(F23-G23,"") | M23: =IFERROR(J23-F23,"") | N23: =IFERROR(J23-L23,"") | O23: =IFERROR(J23-H23,"") | P23: =IFERROR(K23-F23,"") | Q23: 0.52884615 | R23: 0.39423077 | S23: 0.24038462 | T23: 0.58653846 | U23: 0.098484848 | V23: 0.15909091 | X23: 0.33459596 | Y23: =IF(X23="","",IF(X23>='Léeme'!$B$6,"barato",IF(X23<'Léeme'!$B$7,"caro","medio"))) | Z23: 0.12143783 | AA23: 0.088767547
A24: 1997-T3 | B24: 35703 | C24: 15.9375 | D24: 1.34 | E24: 1.2 | F24: 0.0612 | G24: 0.022900763 | H24: 0.0764 | I24: =IFERROR(C24/D24,"") | J24: =IFERROR(D24/C24,"") | K24: =IFERROR(E24/C24,"") | L24: =IFERROR(F24-G24,"") | M24: =IFERROR(J24-F24,"") | N24: =IFERROR(J24-L24,"") | O24: =IFERROR(J24-H24,"") | P24: =IFERROR(K24-F24,"") | Q24: 0.3 | R24: 0.44545455 | S24: 0.28181818 | T24: 0.57272727 | U24: 0.0072463768 | V24: 0.19565217 | X24: 0.30048309 | Y24: =IF(X24="","",IF(X24>='Léeme'!$B$6,"barato",IF(X24<'Léeme'!$B$7,"caro","medio"))) | Z24: -0.026473938 | AA24: 0.08174101
A25: 1997-T4 | B25: 35795 | C25: 17.875 | D25: 1.34 | E25: 1.2 | F25: 0.0575 | G25: 0.018903592 | H25: 0.0732 | I25: =IFERROR(C25/D25,"") | J25: =IFERROR(D25/C25,"") | K25: =IFERROR(E25/C25,"") | L25: =IFERROR(F25-G25,"") | M25: =IFERROR(J25-F25,"") | N25: =IFERROR(J25-L25,"") | O25: =IFERROR(J25-H25,"") | P25: =IFERROR(K25-F25,"") | Q25: 0.0086206897 | R25: 0.25 | S25: 0.14655172 | T25: 0.28448276 | U25: 0.0069444444 | V25: 0.034722222 | X25: 0.12188697 | Y25: =IF(X25="","",IF(X25>='Léeme'!$B$6,"barato",IF(X25<'Léeme'!$B$7,"caro","medio"))) | Z25: -0.21205241 | AA25: 0.046926151
A26: 1998-T1 | B26: 35885 | C26: 17.625 | D26: 1.4132 | E26: 1.2 | F26: 0.0567 | G26: 0.014402004 | H26: 0.0736 | I26: =IFERROR(C26/D26,"") | J26: =IFERROR(D26/C26,"") | K26: =IFERROR(E26/C26,"") | L26: =IFERROR(F26-G26,"") | M26: =IFERROR(J26-F26,"") | N26: =IFERROR(J26-L26,"") | O26: =IFERROR(J26-H26,"") | P26: =IFERROR(K26-F26,"") | Q26: 0.20491803 | R26: 0.48360656 | S26: 0.18852459 | T26: 0.46721311 | U26: 0.02 | V26: 0.11333333 | X26: 0.24626594 | Y26: =IF(X26="","",IF(X26>='Léeme'!$B$6,"barato",IF(X26<'Léeme'!$B$7,"caro","medio"))) | Z26: -0.3221687 | AA26: 0.047434545
A27: 1998-T2 | B27: 35976 | C27: 16.1875 | D27: 1.4132 | E27: 1.24 | F27: 0.0544 | G27: 0.016885553 | H27: 0.0713 | I27: =IFERROR(C27/D27,"") | J27: =IFERROR(D27/C27,"") | K27: =IFERROR(E27/C27,"") | L27: =IFERROR(F27-G27,"") | M27: =IFERROR(J27-F27,"") | N27: =IFERROR(J27-L27,"") | O27: =IFERROR(J27-H27,"") | P27: =IFERROR(K27-F27,"") | Q27: 0.5859375 | R27: 0.9609375 | S27: 0.4609375 | T27: 0.9765625 | U27: 0.16025641 | V27: 0.54487179 | X27: 0.6149172 | Y27: =IF(X27="","",IF(X27>='Léeme'!$B$6,"barato",IF(X27<'Léeme'!$B$7,"caro","medio"))) | Z27: -0.14751531 | AA27: 0.094149757
A28: 1998-T3 | B28: 36068 | C28: 14.625 | D28: 1.4132 | E28: 1.24 | F28: 0.0444 | G28: 0.016169154 | H28: 0.0709 | I28: =IFERROR(C28/D28,"") | J28: =IFERROR(D28/C28,"") | K28: =IFERROR(E28/C28,"") | L28: =IFERROR(F28-G28,"") | M28: =IFERROR(J28-F28,"") | N28: =IFERROR(J28-L28,"") | O28: =IFERROR(J28-H28,"") | P28: =IFERROR(K28-F28,"") | Q28: 0.97761194 | R28: 0.97761194 | S28: 0.97761194 | T28: 0.97761194 | U28: 0.5 | V28: 0.95679012 | X28: 0.89453965 | Y28: =IF(X28="","",IF(X28>='Léeme'!$B$6,"barato",IF(X28<'Léeme'!$B$7,"caro","medio"))) | Z28: -0.2168293 | AA28: 0.11355179
A29: 1998-T4 | B29: 36160 | C29: 13.25 | D29: 1.4132 | E29: 1.24 | F29: 0.0465 | G29: 0.014842301 | H29: 0.0726 | I29: =IFERROR(C29/D29,"") | J29: =IFERROR(D29/C29,"") | K29: =IFERROR(E29/C29,"") | L29: =IFERROR(F29-G29,"") | M29: =IFERROR(J29-F29,"") | N29: =IFERROR(J29-L29,"") | O29: =IFERROR(J29-H29,"") | P29: =IFERROR(K29-F29,"") | Q29: 0.97857143 | R29: 0.99285714 | S29: 0.99285714 | T29: 0.97857143 | U29: 0.7797619 | V29: 0.99404762 | X29: 0.95277778 | Y29: =IF(X29="","",IF(X29>='Léeme'!$B$6,"barato",IF(X29<'Léeme'!$B$7,"caro","medio"))) | Z29: -0.18709225 | AA29: 0.14536496
A30: 1999-T1 | B30: 36250 | C30: 11.1875 | D30: 1.4463 | E30: 1.24 | F30: 0.0525 | G30: 0.016666667 | H30: 0.0753 | I30: =IFERROR(C30/D30,"") | J30: =IFERROR(D30/C30,"") | K30: =IFERROR(E30/C30,"") | L30: =IFERROR(F30-G30,"") | M30: =IFERROR(J30-F30,"") | N30: =IFERROR(J30-L30,"") | O30: =IFERROR(J30-H30,"") | P30: =IFERROR(K30-F30,"") | Q30: 0.99315068 | R30: 0.99315068 | S30: 0.99315068 | T30: 0.99315068 | U30: 0.97126437 | V30: 0.99425287 | W30: 0.98648649 | X30: 0.9892295 | Y30: =IF(X30="","",IF(X30>='Léeme'!$B$6,"barato",IF(X30<'Léeme'!$B$7,"caro","medio"))) | Z30: 0.016998679 | AA30: 0.20871012
A31: 1999-T2 | B31: 36341 | C31: 12.875 | D31: 1.4463 | E31: 1.24 | F31: 0.0581 | G31: 0.020910209 | H31: 0.0805 | I31: =IFERROR(C31/D31,"") | J31: =IFERROR(D31/C31,"") | K31: =IFERROR(E31/C31,"") | L31: =IFERROR(F31-G31,"") | M31: =IFERROR(J31-F31,"") | N31: =IFERROR(J31-L31,"") | O31: =IFERROR(J31-H31,"") | P31: =IFERROR(K31-F31,"") | Q31: 0.95394737 | R31: 0.91447368 | S31: 0.92763158 | T31: 0.91447368 | U31: 0.87222222 | V31: 0.88333333 | W31: 0.9125 | X31: 0.91122598 | Y31: =IF(X31="","",IF(X31>='Léeme'!$B$6,"barato",IF(X31<'Léeme'!$B$7,"caro","medio"))) | Z31: -0.1062667 | AA31: 0.14233802
A32: 1999-T3 | B32: 36433 | C32: 10.625 | D32: 1.4463 | E32: 1.24 | F32: 0.059 | G32: 0.022643819 | H32: 0.0828 | I32: =IFERROR(C32/D32,"") | J32: =IFERROR(D32/C32,"") | K32: =IFERROR(E32/C32,"") | L32: =IFERROR(F32-G32,"") | M32: =IFERROR(J32-F32,"") | N32: =IFERROR(J32-L32,"") | O32: =IFERROR(J32-H32,"") | P32: =IFERROR(K32-F32,"") | Q32: 0.99367089 | R32: 0.99367089 | S32: 0.99367089 | T32: 0.98101266 | U32: 0.99462366 | V32: 0.98387097 | W32: 0.98837209 | X32: 0.98984172 | Y32: =IF(X32="","",IF(X32>='Léeme'!$B$6,"barato",IF(X32<'Léeme'!$B$7,"caro","medio"))) | Z32: 0.070390192 | AA32: 0.19932855
A33: 1999-T4 | B33: 36525 | C33: 9.9375 | D33: 1.4463 | E33: 1.24 | F33: 0.0645 | G33: 0.026203534 | H33: 0.0823 | I33: =IFERROR(C33/D33,"") | J33: =IFERROR(D33/C33,"") | K33: =IFERROR(E33/C33,"") | L33: =IFERROR(F33-G33,"") | M33: =IFERROR(J33-F33,"") | N33: =IFERROR(J33-L33,"") | O33: =IFERROR(J33-H33,"") | P33: =IFERROR(K33-F33,"") | Q33: 0.99390244 | R33: 0.99390244 | S33: 0.99390244 | T33: 0.99390244 | U33: 0.99479167 | V33: 0.99479167 | W33: 0.98913043 | X33: 0.99347479 | Y33: =IF(X33="","",IF(X33>='Léeme'!$B$6,"barato",IF(X33<'Léeme'!$B$7,"caro","medio"))) | Z33: 0.12630754 | AA33: 0.2434767
A34: 2000-T1 | B34: 36616 | C34: 10.4375 | D34: 1.5142 | E34: 1.24 | F34: 0.0603 | G34: 0.032179721 | H34: 0.0836 | I34: =IFERROR(C34/D34,"") | J34: =IFERROR(D34/C34,"") | K34: =IFERROR(E34/C34,"") | L34: =IFERROR(F34-G34,"") | M34: =IFERROR(J34-F34,"") | N34: =IFERROR(J34-L34,"") | O34: =IFERROR(J34-H34,"") | P34: =IFERROR(K34-F34,"") | Q34: 0.98235294 | R34: 0.99411765 | S34: 0.99411765 | T34: 0.98235294 | U34: 0.96464646 | V34: 0.98484848 | W34: 0.96938776 | X34: 0.98168913 | Y34: =IF(X34="","",IF(X34>='Léeme'!$B$6,"barato",IF(X34<'Léeme'!$B$7,"caro","medio"))) | Z34: 0.23875404 | AA34: 0.20207815
A35: 2000-T2 | B35: 36707 | C35: 10.515625 | D35: 1.5142 | E35: 1.24 | F35: 0.0603 | G35: 0.031325301 | H35: 0.0844 | I35: =IFERROR(C35/D35,"") | J35: =IFERROR(D35/C35,"") | K35: =IFERROR(E35/C35,"") | L35: =IFERROR(F35-G35,"") | M35: =IFERROR(J35-F35,"") | N35: =IFERROR(J35-L35,"") | O35: =IFERROR(J35-H35,"") | P35: =IFERROR(K35-F35,"") | Q35: 0.97159091 | R35: 0.98295455 | S35: 0.98295455 | T35: 0.97159091 | U35: 0.95588235 | V35: 0.95588235 | W35: 0.95192308 | X35: 0.96753981 | Y35: =IF(X35="","",IF(X35>='Léeme'!$B$6,"barato",IF(X35<'Léeme'!$B$7,"caro","medio"))) | Z35: 0.48159694 | AA35: 0.22329519
A36: 2000-T3 | B36: 36798 | C36: 10.375 | D36: 1.5142 | E36: 1.24 | F36: 0.058 | G36: 0.033512867 | H36: 0.0832 | I36: =IFERROR(C36/D36,"") | J36: =IFERROR(D36/C36,"") | K36: =IFERROR(E36/C36,"") | L36: =IFERROR(F36-G36,"") | M36: =IFERROR(J36-F36,"") | N36: =IFERROR(J36-L36,"") | O36: =IFERROR(J36-H36,"") | P36: =IFERROR(K36-F36,"") | Q36: 0.99450549 | R36: 0.99450549 | S36: 0.98351648 | T36: 0.98351648 | U36: 0.96666667 | V36: 0.9952381 | W36: 0.97272727 | X36: 0.98438228 | Y36: =IF(X36="","",IF(X36>='Léeme'!$B$6,"barato",IF(X36<'Léeme'!$B$7,"caro","medio"))) | Z36: 0.38988397 | AA36: 0.2182835
A37: 2000-T4 | B37: 36889 | C37: 10.1875 | D37: 1.5142 | E37: 1.26 | F37: 0.0512 | G37: 0.034441805 | H37: 0.0796 | I37: =IFERROR(C37/D37,"") | J37: =IFERROR(D37/C37,"") | K37: =IFERROR(E37/C37,"") | L37: =IFERROR(F37-G37,"") | M37: =IFERROR(J37-F37,"") | N37: =IFERROR(J37-L37,"") | O37: =IFERROR(J37-H37,"") | P37: =IFERROR(K37-F37,"") | Q37: 0.97340426 | R37: 0.99468085 | S37: 0.99468085 | T37: 0.98404255 | U37: 0.96759259 | V37: 0.99537037 | W37: 0.92241379 | X37: 0.97602647 | Y37: =IF(X37="","",IF(X37>='Léeme'!$B$6,"barato",IF(X37<'Léeme'!$B$7,"caro","medio"))) | Z37: 0.38880254 | AA37: 0.22741198
A38: 2001-T1 | B38: 36980 | C38: 11.8 | D38: 1.4453 | E38: 1.26 | F38: 0.0493 | G38: 0.035294118 | H38: 0.08 | I38: =IFERROR(C38/D38,"") | J38: =IFERROR(D38/C38,"") | K38: =IFERROR(E38/C38,"") | L38: =IFERROR(F38-G38,"") | M38: =IFERROR(J38-F38,"") | N38: =IFERROR(J38-L38,"") | O38: =IFERROR(J38-H38,"") | P38: =IFERROR(K38-F38,"") | Q38: 0.77835052 | R38: 0.81958763 | S38: 0.8814433 | T38: 0.79896907 | U38: 0.75225225 | V38: 0.87837838 | W38: 0.6147541 | X38: 0.78910503 | Y38: =IF(X38="","",IF(X38>='Léeme'!$B$6,"barato",IF(X38<'Léeme'!$B$7,"caro","medio"))) | Z38: 0.27767622 | AA38: 0.21731845
A39: 2001-T2 | B39: 37071 | C39: 14.25 | D39: 1.4453 | E39: 1.26 | F39: 0.0542 | G39: 0.035630841 | H39: 0.0801 | I39: =IFERROR(C39/D39,"") | J39: =IFERROR(D39/C39,"") | K39: =IFERROR(E39/C39,"") | L39: =IFERROR(F39-G39,"") | M39: =IFERROR(J39-F39,"") | N39: =IFERROR(J39-L39,"") | O39: =IFERROR(J39-H39,"") | P39: =IFERROR(K39-F39,"") | Q39: 0.685 | R39: 0.655 | S39: 0.755 | T39: 0.655 | U39: 0.46052632 | V39: 0.63596491 | W39: 0.1015625 | X39: 0.56400768 | Y39: =IF(X39="","",IF(X39>='Léeme'!$B$6,"barato",IF(X39<'Léeme'!$B$7,"caro","medio"))) | Z39: 0.20858176 | AA39: 0.13565686
A40: 2001-T3 | B40: 37162 | C40: 13.25 | D40: 1.4453 | E40: 1.26 | F40: 0.046 | G40: 0.027214823 | H40: 0.0805 | I40: =IFERROR(C40/D40,"") | J40: =IFERROR(D40/C40,"") | K40: =IFERROR(E40/C40,"") | L40: =IFERROR(F40-G40,"") | M40: =IFERROR(J40-F40,"") | N40: =IFERROR(J40-L40,"") | O40: =IFERROR(J40-H40,"") | P40: =IFERROR(K40-F40,"") | Q40: 0.71359223 | R40: 0.77184466 | S40: 0.7815534 | T40: 0.68446602 | U40: 0.67094017 | V40: 0.83333333 | W40: 0.24626866 | X40: 0.67171407 | Y40: =IF(X40="","",IF(X40>='Léeme'!$B$6,"barato",IF(X40<'Léeme'!$B$7,"caro","medio"))) | Z40: 0.31232612 | AA40: 0.17145708
A41: 2001-T4 | B41: 37256 | C41: 13 | D41: 1.4453 | E41: 1.26 | F41: 0.0507 | G41: 0.018943743 | H41: 0.0802 | I41: =IFERROR(C41/D41,"") | J41: =IFERROR(D41/C41,"") | K41: =IFERROR(E41/C41,"") | L41: =IFERROR(F41-G41,"") | M41: =IFERROR(J41-F41,"") | N41: =IFERROR(J41-L41,"") | O41: =IFERROR(J41-H41,"") | P41: =IFERROR(K41-F41,"") | Q41: 0.72641509 | R41: 0.72169811 | S41: 0.71226415 | T41: 0.68396226 | U41: 0.7 | V41: 0.75416667 | W41: 0.26428571 | X41: 0.65182743 | Y41: =IF(X41="","",IF(X41>='Léeme'!$B$6,"barato",IF(X41<'Léeme'!$B$7,"caro","medio"))) | Z41: 0.26204949 | AA41: 0.18726734
... A119: 2021-T2 | B119: 44377 | C119: 46.880001 | D119: 2.49 | E119: 2.08 | F119: 0.0145 | G119: 0.049182571 | H119: 0.0336 | I119: =IFERROR(C119/D119,"") | J119: =IFERROR(D119/C119,"") | K119: =IFERROR(E119/C119,"") | L119: =IFERROR(F119-G119,"") | M119: =IFERROR(J119-F119,"") | N119: =IFERROR(J119-L119,"") | O119: =IFERROR(J119-H119,"") | P119: =IFERROR(K119-F119,"") | Q119: 0.16323529 | R119: 0.66029412 | S119: 0.875 | T119: 0.77205882 | U119: 0.13700565 | V119: 0.61723164 | W119: 0.56414474 | X119: 0.54128147 | Y119: =IF(X119="","",IF(X119>='Léeme'!$B$6,"barato",IF(X119<'Léeme'!$B$7,"caro","medio"))) | Z119: -0.048410847 | AA119: 0.041532972
A120: 2021-T3 | B120: 44469 | C120: 43.189999 | D120: 2.49 | E120: 2.12 | F120: 0.0152 | G120: 0.051520153 | H120: 0.0336 | I120: =IFERROR(C120/D120,"") | J120: =IFERROR(D120/C120,"") | K120: =IFERROR(E120/C120,"") | L120: =IFERROR(F120-G120,"") | M120: =IFERROR(J120-F120,"") | N120: =IFERROR(J120-L120,"") | O120: =IFERROR(J120-H120,"") | P120: =IFERROR(K120-F120,"") | Q120: 0.29591837 | R120: 0.7244898 | S120: 0.91399417 | T120: 0.79737609 | U120: 0.2394958 | V120: 0.68207283 | W120: 0.7247557 | X120: 0.62544325 | Y120: =IF(X120="","",IF(X120>='Léeme'!$B$6,"barato",IF(X120<'Léeme'!$B$7,"caro","medio"))) | Z120: -0.041943529
A121: 2021-T4 | B121: 44561 | C121: 48.07 | D121: 2.49 | E121: 2.12 | F121: 0.0152 | G121: 0.069019704 | H121: 0.0337 | I121: =IFERROR(C121/D121,"") | J121: =IFERROR(D121/C121,"") | K121: =IFERROR(E121/C121,"") | L121: =IFERROR(F121-G121,"") | M121: =IFERROR(J121-F121,"") | N121: =IFERROR(J121-L121,"") | O121: =IFERROR(J121-H121,"") | P121: =IFERROR(K121-F121,"") | Q121: 0.14884393 | R121: 0.6199422 | S121: 0.94653179 | T121: 0.73265896 | U121: 0.1375 | V121: 0.58194444 | W121: 0.50483871 | X121: 0.52460858 | Y121: =IF(X121="","",IF(X121>='Léeme'!$B$6,"barato",IF(X121<'Léeme'!$B$7,"caro","medio"))) | Z121: -0.010497028
A122: 2022-T1 | B122: 44651 | C122: 44.939999 | D122: 2.68 | E122: 2.12 | F122: 0.0232 | G122: 0.079372788 | H122: 0.0428 | I122: =IFERROR(C122/D122,"") | J122: =IFERROR(D122/C122,"") | K122: =IFERROR(E122/C122,"") | L122: =IFERROR(F122-G122,"") | M122: =IFERROR(J122-F122,"") | N122: =IFERROR(J122-L122,"") | O122: =IFERROR(J122-H122,"") | P122: =IFERROR(K122-F122,"") | Q122: 0.33381089 | R122: 0.60888252 | S122: 0.96991404 | T122: 0.70057307 | U122: 0.20247934 | V122: 0.43112948 | W122: 0.73961661 | X122: 0.56948656 | Y122: =IF(X122="","",IF(X122>='Léeme'!$B$6,"barato",IF(X122<'Léeme'!$B$7,"caro","medio"))) | Z122: 0.020791122
A123: 2022-T2 | B123: 44742 | C123: 43 | D123: 2.68 | E123: 2.12 | F123: 0.0298 | G123: 0.085381712 | H123: 0.0534 | I123: =IFERROR(C123/D123,"") | J123: =IFERROR(D123/C123,"") | K123: =IFERROR(E123/C123,"") | L123: =IFERROR(F123-G123,"") | M123: =IFERROR(J123-F123,"") | N123: =IFERROR(J123-L123,"") | O123: =IFERROR(J123-H123,"") | P123: =IFERROR(K123-F123,"") | Q123: 0.35369318 | R123: 0.515625 | S123: 0.97301136 | T123: 0.48153409 | U123: 0.25546448 | V123: 0.2363388 | W123: 0.78955696 | X123: 0.51503198 | Y123: =IF(X123="","",IF(X123>='Léeme'!$B$6,"barato",IF(X123<'Léeme'!$B$7,"caro","medio"))) | Z123: 0.035010321
A124: 2022-T3 | B124: 44834 | C124: 39.860001 | D124: 2.68 | E124: 2.2 | F124: 0.0383 | G124: 0.082225792 | H124: 0.0603 | I124: =IFERROR(C124/D124,"") | J124: =IFERROR(D124/C124,"") | K124: =IFERROR(E124/C124,"") | L124: =IFERROR(F124-G124,"") | M124: =IFERROR(J124-F124,"") | N124: =IFERROR(J124-L124,"") | O124: =IFERROR(J124-H124,"") | P124: =IFERROR(K124-F124,"") | Q124: 0.39859155 | R124: 0.39014085 | S124: 0.94225352 | T124: 0.40140845 | U124: 0.31300813 | V124: 0.16666667 | W124: 0.81347962 | X124: 0.48936411 | Y124: =IF(X124="","",IF(X124>='Léeme'!$B$6,"barato",IF(X124<'Léeme'!$B$7,"caro","medio"))) | Z124: -0.076749497
A125: 2022-T4 | B125: 44925 | C125: 45.759998 | D125: 2.68 | E125: 2.2 | F125: 0.0388 | G125: 0.071228565 | H125: 0.0584 | I125: =IFERROR(C125/D125,"") | J125: =IFERROR(D125/C125,"") | K125: =IFERROR(E125/C125,"") | L125: =IFERROR(F125-G125,"") | M125: =IFERROR(J125-F125,"") | N125: =IFERROR(J125-L125,"") | O125: =IFERROR(J125-H125,"") | P125: =IFERROR(K125-F125,"") | Q125: 0.3198324 | R125: 0.060055866 | S125: 0.85335196 | T125: 0.11871508 | U125: 0.24327957 | V125: 0.014784946 | W125: 0.65993789 | X125: 0.32427967 | Y125: =IF(X125="","",IF(X125>='Léeme'!$B$6,"barato",IF(X125<'Léeme'!$B$7,"caro","medio"))) | Z125: -0.01700428
A126: 2023-T1 | B126: 45016 | C126: 44.150002 | D126: 3.1 | E126: 2.2 | F126: 0.0348 | G126: 0.059578207 | H126: 0.0566 | I126: =IFERROR(C126/D126,"") | J126: =IFERROR(D126/C126,"") | K126: =IFERROR(E126/C126,"") | L126: =IFERROR(F126-G126,"") | M126: =IFERROR(J126-F126,"") | N126: =IFERROR(J126-L126,"") | O126: =IFERROR(J126-H126,"") | P126: =IFERROR(K126-F126,"") | Q126: 0.44736842 | R126: 0.59695291 | S126: 0.88504155 | T126: 0.64127424 | U126: 0.27333333 | V126: 0.14266667 | W126: 0.83538462 | X126: 0.5460031 | Y126: =IF(X126="","",IF(X126>='Léeme'!$B$6,"barato",IF(X126<'Léeme'!$B$7,"caro","medio"))) | Z126: 0.012091401
A127: 2023-T2 | B127: 45107 | C127: 42.790001 | D127: 3.1 | E127: 2.2 | F127: 0.0381 | G127: 0.041318512 | H127: 0.0577 | I127: =IFERROR(C127/D127,"") | J127: =IFERROR(D127/C127,"") | K127: =IFERROR(E127/C127,"") | L127: =IFERROR(F127-G127,"") | M127: =IFERROR(J127-F127,"") | N127: =IFERROR(J127-L127,"") | O127: =IFERROR(J127-H127,"") | P127: =IFERROR(K127-F127,"") | Q127: 0.48214286 | R127: 0.56181319 | S127: 0.74862637 | T127: 0.66620879 | U127: 0.30026455 | V127: 0.10978836 | W127: 0.85213415 | X127: 0.53156832 | Y127: =IF(X127="","",IF(X127>='Léeme'!$B$6,"barato",IF(X127<'Léeme'!$B$7,"caro","medio"))) | Z127: 0.04172507
A128: 2023-T3 | B128: 45198 | C128: 35.34 | D128: 3.1 | E128: 2.26 | F128: 0.0459 | G128: 0.037225048 | H128: 0.0639 | I128: =IFERROR(C128/D128,"") | J128: =IFERROR(D128/C128,"") | K128: =IFERROR(E128/C128,"") | L128: =IFERROR(F128-G128,"") | M128: =IFERROR(J128-F128,"") | N128: =IFERROR(J128-L128,"") | O128: =IFERROR(J128-H128,"") | P128: =IFERROR(K128-F128,"") | Q128: 0.72615804 | R128: 0.72070845 | S128: 0.77792916 | T128: 0.80517711 | U128: 0.47637795 | V128: 0.21653543 | W128: 0.93504532 | X128: 0.66541878 | Y128: =IF(X128="","",IF(X128>='Léeme'!$B$6,"barato",IF(X128<'Léeme'!$B$7,"caro","medio"))) | Z128: 0.42534922
A129: 2023-T4 | B129: 45289 | C129: 43.099998 | D129: 3.1 | E129: 2.26 | F129: 0.0388 | G129: 0.031333463 | H129: 0.0546 | I129: =IFERROR(C129/D129,"") | J129: =IFERROR(D129/C129,"") | K129: =IFERROR(E129/C129,"") | L129: =IFERROR(F129-G129,"") | M129: =IFERROR(J129-F129,"") | N129: =IFERROR(J129-L129,"") | O129: =IFERROR(J129-H129,"") | P129: =IFERROR(K129-F129,"") | Q129: 0.47162162 | R129: 0.52837838 | S129: 0.62837838 | T129: 0.71486486 | U129: 0.30859375 | V129: 0.12369792 | W129: 0.81287425 | X129: 0.51262988 | Y129: =IF(X129="","",IF(X129>='Léeme'!$B$6,"barato",IF(X129<'Léeme'!$B$7,"caro","medio"))) | Z129: -0.018747812
A130: 2024-T1 | B130: 45379 | C130: 42.740002 | D130: 3.24 | E130: 2.26 | F130: 0.042 | G130: 0.031570741 | H130: 0.0574 | I130: =IFERROR(C130/D130,"") | J130: =IFERROR(D130/C130,"") | K130: =IFERROR(E130/C130,"") | L130: =IFERROR(F130-G130,"") | M130: =IFERROR(J130-F130,"") | N130: =IFERROR(J130-L130,"") | O130: =IFERROR(J130-H130,"") | P130: =IFERROR(K130-F130,"") | Q130: 0.52144772 | R130: 0.54021448 | S130: 0.63941019 | T130: 0.73592493 | U130: 0.30878553 | V130: 0.0374677 | W130: 0.81750742 | X130: 0.514394 | Y130: =IF(X130="","",IF(X130>='Léeme'!$B$6,"barato",IF(X130<'Léeme'!$B$7,"caro","medio"))) | Z130: 0.028760231
A131: 2024-T2 | B131: 45471 | C131: 42.599998 | D131: 3.24 | E131: 2.26 | F131: 0.0436 | G131: 0.032442786 | H131: 0.0584 | I131: =IFERROR(C131/D131,"") | J131: =IFERROR(D131/C131,"") | K131: =IFERROR(E131/C131,"") | L131: =IFERROR(F131-G131,"") | M131: =IFERROR(J131-F131,"") | N131: =IFERROR(J131-L131,"") | O131: =IFERROR(J131-H131,"") | P131: =IFERROR(K131-F131,"") | Q131: 0.52260638 | R131: 0.49867021 | S131: 0.62898936 | T131: 0.71941489 | U131: 0.31410256 | V131: 0.024358974 | W131: 0.77794118 | X131: 0.49801194 | Y131: =IF(X131="","",IF(X131>='Léeme'!$B$6,"barato",IF(X131<'Léeme'!$B$7,"caro","medio"))) | Z131: 0.051685152
... A135: 2025-T2 | B135: 45838 | C135: 43.18 | D135: 3.32 | E135: 2.32 | F135: 0.0424 | G135: 0.023772651 | H135: 0.0608 | I135: =IFERROR(C135/D135,"") | J135: =IFERROR(D135/C135,"") | K135: =IFERROR(E135/C135,"") | L135: =IFERROR(F135-G135,"") | M135: =IFERROR(J135-F135,"") | N135: =IFERROR(J135-L135,"") | O135: =IFERROR(J135-H135,"") | P135: =IFERROR(K135-F135,"") | Q135: 0.54768041 | R135: 0.56314433 | S135: 0.51675258 | T135: 0.67654639 | U135: 0.32711443 | V135: 0.083333333 | W135: 0.671875 | X135: 0.48377807 | Y135: =IF(X135="","",IF(X135>='Léeme'!$B$6,"barato",IF(X135<'Léeme'!$B$7,"caro","medio"))) | Z135: 0.12798738
A136: 2025-T3 | B136: 45930 | C136: 42.57 | D136: 3.32 | E136: 2.4 | F136: 0.0416 | G136: 0.029385917 | H136: 0.0579 | I136: =IFERROR(C136/D136,"") | J136: =IFERROR(D136/C136,"") | K136: =IFERROR(E136/C136,"") | L136: =IFERROR(F136-G136,"") | M136: =IFERROR(J136-F136,"") | N136: =IFERROR(J136-L136,"") | O136: =IFERROR(J136-H136,"") | P136: =IFERROR(K136-F136,"") | Q136: 0.56905371 | R136: 0.62276215 | S136: 0.65089514 | T136: 0.77621483 | U136: 0.37407407 | V136: 0.18641975 | W136: 0.6943662 | X136: 0.55339798 | Y136: =IF(X136="","",IF(X136>='Léeme'!$B$6,"barato",IF(X136<'Léeme'!$B$7,"caro","medio")))
A137: 2025-T4 | B137: 46022 | C137: 39.630001 | D137: 3.32 | E137: 2.4 | F137: 0.0418 | G137: 0.026964439 | H137: 0.0589 | I137: =IFERROR(C137/D137,"") | J137: =IFERROR(D137/C137,"") | K137: =IFERROR(E137/C137,"") | L137: =IFERROR(F137-G137,"") | M137: =IFERROR(J137-F137,"") | N137: =IFERROR(J137-L137,"") | O137: =IFERROR(J137-H137,"") | P137: =IFERROR(K137-F137,"") | Q137: 0.66116751 | R137: 0.74238579 | S137: 0.69923858 | T137: 0.82360406 | U137: 0.46691176 | V137: 0.29044118 | W137: 0.77234637 | X137: 0.63658504 | Y137: =IF(X137="","",IF(X137>='Léeme'!$B$6,"barato",IF(X137<'Léeme'!$B$7,"caro","medio")))
A138: 2026-T1 | B138: 46112 | C138: 42.029999 | D138: 3.4 | E138: 2.4 | F138: 0.043 | G138: 0.024340041 | H138: 0.0614 | I138: =IFERROR(C138/D138,"") | J138: =IFERROR(D138/C138,"") | K138: =IFERROR(E138/C138,"") | L138: =IFERROR(F138-G138,"") | M138: =IFERROR(J138-F138,"") | N138: =IFERROR(J138-L138,"") | O138: =IFERROR(J138-H138,"") | P138: =IFERROR(K138-F138,"") | Q138: 0.61838791 | R138: 0.66624685 | S138: 0.57052897 | T138: 0.75692695 | U138: 0.39294404 | V138: 0.16666667 | W138: 0.71883657 | X138: 0.55579114 | Y138: =IF(X138="","",IF(X138>='Léeme'!$B$6,"barato",IF(X138<'Léeme'!$B$7,"caro","medio")))
A139: 2026-T2 | B139: 46203 | C139: 46.529999 | D139: 3.4 | E139: 2.4 | F139: 0.0444 | G139: 0.041666147 | H139: 0.0593 | I139: =IFERROR(C139/D139,"") | J139: =IFERROR(D139/C139,"") | K139: =IFERROR(E139/C139,"") | L139: =IFERROR(F139-G139,"") | M139: =IFERROR(J139-F139,"") | N139: =IFERROR(J139-L139,"") | O139: =IFERROR(J139-H139,"") | P139: =IFERROR(K139-F139,"") | Q139: 0.46375 | R139: 0.34375 | S139: 0.72375 | T139: 0.58625 | U139: 0.28381643 | V139: 0.0012077295 | W139: 0.49587912 | X139: 0.41405761 | Y139: =IF(X139="","",IF(X139>='Léeme'!$B$6,"barato",IF(X139<'Léeme'!$B$7,"caro","medio")))
A140: 2026-T3 | B140: 46293 | C140: 41.41 | D140: 3.4 | E140: 2.48 | F140: 0.0524 | G140: 0.033530163 | H140: 0.0663 | I140: =IFERROR(C140/D140,"") | J140: =IFERROR(D140/C140,"") | K140: =IFERROR(E140/C140,"") | L140: =IFERROR(F140-G140,"") | M140: =IFERROR(J140-F140,"") | N140: =IFERROR(J140-L140,"") | O140: =IFERROR(J140-H140,"") | P140: =IFERROR(K140-F140,"") | Q140: 0.63647643 | R140: 0.39826303 | S140: 0.58188586 | T140: 0.6439206 | U140: 0.46642686 | V140: 0.010791367 | W140: 0.70435967 | X140: 0.49173197 | Y140: =IF(X140="","",IF(X140>='Léeme'!$B$6,"barato",IF(X140<'Léeme'!$B$7,"caro","medio")))

Sheet O
A1: Trimestre | B1: Fecha | C1: Precio | D1: Flujo por acción, 12 meses | E1: Dividendo anualizado | F1: Treasury 10 años | G1: Inflación 12 meses | H1: Bonos Baa | I1: Múltiplo precio/flujo | J1: Yield de flujo | K1: Yield de dividendo | L1: Tasa real | M1: Prima sobre el Treasury | N1: Prima sobre la tasa real | O1: Prima sobre bonos Baa | P1: Dividendo sobre el Treasury | Q1: Percentil: Múltiplo P/FFO | R1: Percentil: Prima sobre el Treasury | S1: Percentil: Prima sobre la tasa real | T1: Percentil: Prima sobre bonos Baa | U1: Percentil: Yield de dividendo | V1: Percentil: Dividendo sobre el Treasury | W1: Percentil: Múltiplo contra sus últimos 5 años | X1: Percentil: Consenso de los siete | Y1: Señal del consenso | Z1: Retorno anual, 1 año después | AA1: Retorno anual, 5 años después
A2: 1994-T4 | B2: 34698 | C2: 8.5625 | E2: 0.9 | F2: 0.0784 | G2: 0.026027397 | H2: 0.091 | I2: =IFERROR(C2/D2,"") | J2: =IFERROR(D2/C2,"") | K2: =IFERROR(E2/C2,"") | L2: =IFERROR(F2-G2,"") | M2: =IFERROR(J2-F2,"") | N2: =IFERROR(J2-L2,"") | O2: =IFERROR(J2-H2,"") | P2: =IFERROR(K2-F2,"") | Y2: =IF(X2="","",IF(X2>='Léeme'!$B$6,"barato",IF(X2<'Léeme'!$B$7,"caro","medio"))) | Z2: 0.43585758 | AA2: 0.11429622
A3: 1995-T1 | B3: 34789 | C3: 9.0625 | E3: 0.9 | F3: 0.072 | G3: 0.028629857 | H3: 0.0866 | I3: =IFERROR(C3/D3,"") | J3: =IFERROR(D3/C3,"") | K3: =IFERROR(E3/C3,"") | L3: =IFERROR(F3-G3,"") | M3: =IFERROR(J3-F3,"") | N3: =IFERROR(J3-L3,"") | O3: =IFERROR(J3-H3,"") | P3: =IFERROR(K3-F3,"") | Y3: =IF(X3="","",IF(X3>='Léeme'!$B$6,"barato",IF(X3<'Léeme'!$B$7,"caro","medio"))) | Z3: 0.24080914 | AA3: 0.084799037
A4: 1995-T2 | B4: 34880 | C4: 10.5625 | E4: 0.9 | F4: 0.0621 | G4: 0.031186441 | H4: 0.0799 | I4: =IFERROR(C4/D4,"") | J4: =IFERROR(D4/C4,"") | K4: =IFERROR(E4/C4,"") | L4: =IFERROR(F4-G4,"") | M4: =IFERROR(J4-F4,"") | N4: =IFERROR(J4-L4,"") | O4: =IFERROR(J4-H4,"") | P4: =IFERROR(K4-F4,"") | Y4: =IF(X4="","",IF(X4>='Léeme'!$B$6,"barato",IF(X4<'Léeme'!$B$7,"caro","medio"))) | Z4: 0.064448 | AA4: 0.095746681
A5: 1995-T3 | B5: 34971 | C5: 10.5625 | E5: 0.93 | F5: 0.0617 | G5: 0.026174497 | H5: 0.0795 | I5: =IFERROR(C5/D5,"") | J5: =IFERROR(D5/C5,"") | K5: =IFERROR(E5/C5,"") | L5: =IFERROR(F5-G5,"") | M5: =IFERROR(J5-F5,"") | N5: =IFERROR(J5-L5,"") | O5: =IFERROR(J5-H5,"") | P5: =IFERROR(K5-F5,"") | Y5: =IF(X5="","",IF(X5>='Léeme'!$B$6,"barato",IF(X5<'Léeme'!$B$7,"caro","medio"))) | Z5: 0.16618186 | AA5: 0.09354619
A6: 1995-T4 | B6: 35062 | C6: 11.25 | E6: 0.93 | F6: 0.0558 | G6: 0.026034713 | H6: 0.0741 | I6: =IFERROR(C6/D6,"") | J6: =IFERROR(D6/C6,"") | K6: =IFERROR(E6/C6,"") | L6: =IFERROR(F6-G6,"") | M6: =IFERROR(J6-F6,"") | N6: =IFERROR(J6-L6,"") | O6: =IFERROR(J6-H6,"") | P6: =IFERROR(K6-F6,"") | Y6: =IF(X6="","",IF(X6>='Léeme'!$B$6,"barato",IF(X6<'Léeme'!$B$7,"caro","medio"))) | Z6: 0.12983795 | AA6: 0.090712777
A7: 1996-T1 | B7: 35153 | C7: 10.375001 | E7: 0.93 | F7: 0.0634 | G7: 0.027170311 | H7: 0.0817 | I7: =IFERROR(C7/D7,"") | J7: =IFERROR(D7/C7,"") | K7: =IFERROR(E7/C7,"") | L7: =IFERROR(F7-G7,"") | M7: =IFERROR(J7-F7,"") | N7: =IFERROR(J7-L7,"") | O7: =IFERROR(J7-H7,"") | P7: =IFERROR(K7-F7,"") | Y7: =IF(X7="","",IF(X7>='Léeme'!$B$6,"barato",IF(X7<'Léeme'!$B$7,"caro","medio"))) | Z7: 0.21656993 | AA7: 0.12080155
A8: 1996-T2 | B8: 35244 | C8: 10.375001 | E8: 0.93 | F8: 0.0673 | G8: 0.028270874 | H8: 0.0834 | I8: =IFERROR(C8/D8,"") | J8: =IFERROR(D8/C8,"") | K8: =IFERROR(E8/C8,"") | L8: =IFERROR(F8-G8,"") | M8: =IFERROR(J8-F8,"") | N8: =IFERROR(J8-L8,"") | O8: =IFERROR(J8-H8,"") | P8: =IFERROR(K8-F8,"") | Y8: =IF(X8="","",IF(X8>='Léeme'!$B$6,"barato",IF(X8<'Léeme'!$B$7,"caro","medio"))) | Z8: 0.34750043 | AA8: 0.13985667
A9: 1996-T3 | B9: 35338 | C9: 11.375001 | E9: 0.93 | F9: 0.0672 | G9: 0.028122956 | H9: 0.0821 | I9: =IFERROR(C9/D9,"") | J9: =IFERROR(D9/C9,"") | K9: =IFERROR(E9/C9,"") | L9: =IFERROR(F9-G9,"") | M9: =IFERROR(J9-F9,"") | N9: =IFERROR(J9-L9,"") | O9: =IFERROR(J9-H9,"") | P9: =IFERROR(K9-F9,"") | Y9: =IF(X9="","",IF(X9>='Léeme'!$B$6,"barato",IF(X9<'Léeme'!$B$7,"caro","medio"))) | Z9: 0.25794276 | AA9: 0.12270724
A10: 1996-T4 | B10: 35430 | C10: 11.9375 | E10: 0.945 | F10: 0.0643 | G10: 0.032530904 | H10: 0.0786 | I10: =IFERROR(C10/D10,"") | J10: =IFERROR(D10/C10,"") | K10: =IFERROR(E10/C10,"") | L10: =IFERROR(F10-G10,"") | M10: =IFERROR(J10-F10,"") | N10: =IFERROR(J10-L10,"") | O10: =IFERROR(J10-H10,"") | P10: =IFERROR(K10-F10,"") | Y10: =IF(X10="","",IF(X10>='Léeme'!$B$6,"barato",IF(X10<'Léeme'!$B$7,"caro","medio"))) | Z10: 0.1305234 | AA10: 0.11488464
A11: 1997-T1 | B11: 35520 | C11: 11.5 | D11: 1.0385 | E11: 0.948 | F11: 0.0692 | G11: 0.030322581 | H11: 0.0832 | I11: =IFERROR(C11/D11,"") | J11: =IFERROR(D11/C11,"") | K11: =IFERROR(E11/C11,"") | L11: =IFERROR(F11-G11,"") | M11: =IFERROR(J11-F11,"") | N11: =IFERROR(J11-L11,"") | O11: =IFERROR(J11-H11,"") | P11: =IFERROR(K11-F11,"") | Y11: =IF(X11="","",IF(X11>='Léeme'!$B$6,"barato",IF(X11<'Léeme'!$B$7,"caro","medio"))) | Z11: 0.25329292 | AA11: 0.15065954
A12: 1997-T2 | B12: 35611 | C12: 13.125 | D12: 1.0385 | E12: 0.948 | F12: 0.0651 | G12: 0.022378517 | H12: 0.0797 | I12: =IFERROR(C12/D12,"") | J12: =IFERROR(D12/C12,"") | K12: =IFERROR(E12/C12,"") | L12: =IFERROR(F12-G12,"") | M12: =IFERROR(J12-F12,"") | N12: =IFERROR(J12-L12,"") | O12: =IFERROR(J12-H12,"") | P12: =IFERROR(K12-F12,"") | Y12: =IF(X12="","",IF(X12>='Léeme'!$B$6,"barato",IF(X12<'Léeme'!$B$7,"caro","medio"))) | Z12: 0.065155107 | AA12: 0.1443037
A13: 1997-T3 | B13: 35703 | C13: 13.46875 | D13: 1.0385 | E13: 0.948 | F13: 0.0612 | G13: 0.022900763 | H13: 0.0764 | I13: =IFERROR(C13/D13,"") | J13: =IFERROR(D13/C13,"") | K13: =IFERROR(E13/C13,"") | L13: =IFERROR(F13-G13,"") | M13: =IFERROR(J13-F13,"") | N13: =IFERROR(J13-L13,"") | O13: =IFERROR(J13-H13,"") | P13: =IFERROR(K13-F13,"") | U13: 0.041666667 | V13: 0.125 | Y13: =IF(X13="","",IF(X13>='Léeme'!$B$6,"barato",IF(X13<'Léeme'!$B$7,"caro","medio"))) | Z13: -0.019264569 | AA13: 0.1206507
A14: 1997-T4 | B14: 35795 | C14: 12.71875 | D14: 1.0385 | E14: 0.96 | F14: 0.0575 | G14: 0.018903592 | H14: 0.0732 | I14: =IFERROR(C14/D14,"") | J14: =IFERROR(D14/C14,"") | K14: =IFERROR(E14/C14,"") | L14: =IFERROR(F14-G14,"") | M14: =IFERROR(J14-F14,"") | N14: =IFERROR(J14-L14,"") | O14: =IFERROR(J14-H14,"") | P14: =IFERROR(K14-F14,"") | U14: 0.21794872 | V14: 0.3974359 | Y14: =IF(X14="","",IF(X14>='Léeme'!$B$6,"barato",IF(X14<'Léeme'!$B$7,"caro","medio"))) | Z14: 0.040067579 | AA14: 0.13884469
A15: 1998-T1 | B15: 35885 | C15: 13.59375 | D15: 1.11 | E15: 0.972 | F15: 0.0567 | G15: 0.014402004 | H15: 0.0736 | I15: =IFERROR(C15/D15,"") | J15: =IFERROR(D15/C15,"") | K15: =IFERROR(E15/C15,"") | L15: =IFERROR(F15-G15,"") | M15: =IFERROR(J15-F15,"") | N15: =IFERROR(J15-L15,"") | O15: =IFERROR(J15-H15,"") | P15: =IFERROR(K15-F15,"") | U15: 0.05952381 | V15: 0.32142857 | Y15: =IF(X15="","",IF(X15>='Léeme'!$B$6,"barato",IF(X15<'Léeme'!$B$7,"caro","medio"))) | Z15: -0.17529875 | AA15: 0.12834215
A16: 1998-T2 | B16: 35976 | C16: 13.1875 | D16: 1.11 | E16: 0.99 | F16: 0.0544 | G16: 0.016885553 | H16: 0.0713 | I16: =IFERROR(C16/D16,"") | J16: =IFERROR(D16/C16,"") | K16: =IFERROR(E16/C16,"") | L16: =IFERROR(F16-G16,"") | M16: =IFERROR(J16-F16,"") | N16: =IFERROR(J16-L16,"") | O16: =IFERROR(J16-H16,"") | P16: =IFERROR(K16-F16,"") | U16: 0.3 | V16: 0.56666667 | Y16: =IF(X16="","",IF(X16>='Léeme'!$B$6,"barato",IF(X16<'Léeme'!$B$7,"caro","medio"))) | Z16: -0.036230189 | AA16: 0.14907251
A17: 1998-T3 | B17: 36068 | C17: 12.4375 | D17: 1.11 | E17: 1.008 | F17: 0.0444 | G17: 0.016169154 | H17: 0.0709 | I17: =IFERROR(C17/D17,"") | J17: =IFERROR(D17/C17,"") | K17: =IFERROR(E17/C17,"") | L17: =IFERROR(F17-G17,"") | M17: =IFERROR(J17-F17,"") | N17: =IFERROR(J17-L17,"") | O17: =IFERROR(J17-H17,"") | P17: =IFERROR(K17-F17,"") | U17: 0.44791667 | V17: 0.96875 | Y17: =IF(X17="","",IF(X17>='Léeme'!$B$6,"barato",IF(X17<'Léeme'!$B$7,"caro","medio"))) | Z17: -0.0028507739 | AA17: 0.17104531
A18: 1998-T4 | B18: 36160 | C18: 12.4375 | D18: 1.11 | E18: 1.02 | F18: 0.0465 | G18: 0.014842301 | H18: 0.0726 | I18: =IFERROR(C18/D18,"") | J18: =IFERROR(D18/C18,"") | K18: =IFERROR(E18/C18,"") | L18: =IFERROR(F18-G18,"") | M18: =IFERROR(J18-F18,"") | N18: =IFERROR(J18-L18,"") | O18: =IFERROR(J18-H18,"") | P18: =IFERROR(K18-F18,"") | U18: 0.5 | V18: 0.95098039 | Y18: =IF(X18="","",IF(X18>='Léeme'!$B$6,"barato",IF(X18<'Léeme'!$B$7,"caro","medio"))) | Z18: -0.10750793 | AA18: 0.17208251
A19: 1999-T1 | B19: 36250 | C19: 10.500001 | D19: 1.18 | E19: 1.032 | F19: 0.0525 | G19: 0.016666667 | H19: 0.0753 | I19: =IFERROR(C19/D19,"") | J19: =IFERROR(D19/C19,"") | K19: =IFERROR(E19/C19,"") | L19: =IFERROR(F19-G19,"") | M19: =IFERROR(J19-F19,"") | N19: =IFERROR(J19-L19,"") | O19: =IFERROR(J19-H19,"") | P19: =IFERROR(K19-F19,"") | U19: 0.89814815 | V19: 0.99074074 | Y19: =IF(X19="","",IF(X19>='Léeme'!$B$6,"barato",IF(X19<'Léeme'!$B$7,"caro","medio"))) | Z19: -0.010993476 | AA19: 0.23766206
A20: 1999-T2 | B20: 36341 | C20: 11.875 | D20: 1.18 | E20: 1.05 | F20: 0.0581 | G20: 0.020910209 | H20: 0.0805 | I20: =IFERROR(C20/D20,"") | J20: =IFERROR(D20/C20,"") | K20: =IFERROR(E20/C20,"") | L20: =IFERROR(F20-G20,"") | M20: =IFERROR(J20-F20,"") | N20: =IFERROR(J20-L20,"") | O20: =IFERROR(J20-H20,"") | P20: =IFERROR(K20-F20,"") | U20: 0.71052632 | V20: 0.78070175 | Y20: =IF(X20="","",IF(X20>='Léeme'!$B$6,"barato",IF(X20<'Léeme'!$B$7,"caro","medio"))) | Z20: 0.07278152 | AA20: 0.19011371
A21: 1999-T3 | B21: 36433 | C21: 11.5625 | D21: 1.18 | E21: 1.068 | F21: 0.059 | G21: 0.022643819 | H21: 0.0828 | I21: =IFERROR(C21/D21,"") | J21: =IFERROR(D21/C21,"") | K21: =IFERROR(E21/C21,"") | L21: =IFERROR(F21-G21,"") | M21: =IFERROR(J21-F21,"") | N21: =IFERROR(J21-L21,"") | O21: =IFERROR(J21-H21,"") | P21: =IFERROR(K21-F21,"") | U21: 0.80833333 | V21: 0.80833333 | Y21: =IF(X21="","",IF(X21>='Léeme'!$B$6,"barato",IF(X21<'Léeme'!$B$7,"caro","medio"))) | Z21: 0.090050136 | AA21: 0.21328161
A22: 1999-T4 | B22: 36525 | C22: 10.3125 | D22: 1.18 | E22: 1.08 | F22: 0.0645 | G22: 0.026203534 | H22: 0.0823 | I22: =IFERROR(C22/D22,"") | J22: =IFERROR(D22/C22,"") | K22: =IFERROR(E22/C22,"") | L22: =IFERROR(F22-G22,"") | M22: =IFERROR(J22-F22,"") | N22: =IFERROR(J22-L22,"") | O22: =IFERROR(J22-H22,"") | P22: =IFERROR(K22-F22,"") | U22: 0.94444444 | V22: 0.96031746 | Y22: =IF(X22="","",IF(X22>='Léeme'!$B$6,"barato",IF(X22<'Léeme'!$B$7,"caro","medio"))) | Z22: 0.30193819 | AA22: 0.26820905
A23: 2000-T1 | B23: 36616 | C23: 9.624999 | D23: 1.2285 | E23: 1.086 | F23: 0.0603 | G23: 0.032179721 | H23: 0.0836 | I23: =IFERROR(C23/D23,"") | J23: =IFERROR(D23/C23,"") | K23: =IFERROR(E23/C23,"") | L23: =IFERROR(F23-G23,"") | M23: =IFERROR(J23-F23,"") | N23: =IFERROR(J23-L23,"") | O23: =IFERROR(J23-H23,"") | P23: =IFERROR(K23-F23,"") | Q23: 0.98648649 | R23: 0.98648649 | S23: 0.98648649 | T23: 0.98648649 | U23: 0.99242424 | V23: 0.99242424 | X23: 0.98846574 | Y23: =IF(X23="","",IF(X23>='Léeme'!$B$6,"barato",IF(X23<'Léeme'!$B$7,"caro","medio"))) | Z23: 0.48095683 | AA23: 0.25798271
A24: 2000-T2 | B24: 36707 | C24: 11.789062 | D24: 1.2285 | E24: 1.098 | F24: 0.0603 | G24: 0.031325301 | H24: 0.0844 | I24: =IFERROR(C24/D24,"") | J24: =IFERROR(D24/C24,"") | K24: =IFERROR(E24/C24,"") | L24: =IFERROR(F24-G24,"") | M24: =IFERROR(J24-F24,"") | N24: =IFERROR(J24-L24,"") | O24: =IFERROR(J24-H24,"") | P24: =IFERROR(K24-F24,"") | Q24: 0.7875 | R24: 0.6875 | S24: 0.8625 | T24: 0.6375 | U24: 0.73188406 | V24: 0.7173913 | X24: 0.73737923 | Y24: =IF(X24="","",IF(X24>='Léeme'!$B$6,"barato",IF(X24<'Léeme'!$B$7,"caro","medio"))) | Z24: 0.34488267 | AA24: 0.2279858
A25: 2000-T3 | B25: 36798 | C25: 11.65625 | D25: 1.2285 | E25: 1.104 | F25: 0.058 | G25: 0.033512867 | H25: 0.0832 | I25: =IFERROR(C25/D25,"") | J25: =IFERROR(D25/C25,"") | K25: =IFERROR(E25/C25,"") | L25: =IFERROR(F25-G25,"") | M25: =IFERROR(J25-F25,"") | N25: =IFERROR(J25-L25,"") | O25: =IFERROR(J25-H25,"") | P25: =IFERROR(K25-F25,"") | Q25: 0.80232558 | R25: 0.8255814 | S25: 0.91860465 | T25: 0.73255814 | U25: 0.74305556 | V25: 0.86805556 | X25: 0.81503015 | Y25: =IF(X25="","",IF(X25>='Léeme'!$B$6,"barato",IF(X25<'Léeme'!$B$7,"caro","medio"))) | Z25: 0.33018866 | AA25: 0.21568055
A26: 2000-T4 | B26: 36889 | C26: 12.4375 | D26: 1.2285 | E26: 1.11 | F26: 0.0512 | G26: 0.034441805 | H26: 0.0796 | I26: =IFERROR(C26/D26,"") | J26: =IFERROR(D26/C26,"") | K26: =IFERROR(E26/C26,"") | L26: =IFERROR(F26-G26,"") | M26: =IFERROR(J26-F26,"") | N26: =IFERROR(J26-L26,"") | O26: =IFERROR(J26-H26,"") | P26: =IFERROR(K26-F26,"") | Q26: 0.55434783 | R26: 0.79347826 | S26: 0.88043478 | T26: 0.55434783 | U26: 0.59333333 | V26: 0.88666667 | X26: 0.71043478 | Y26: =IF(X26="","",IF(X26>='Léeme'!$B$6,"barato",IF(X26<'Léeme'!$B$7,"caro","medio"))) | Z26: 0.27485672 | AA26: 0.17861412
A27: 2001-T1 | B27: 36980 | C27: 13.249999 | D27: 1.2285 | E27: 1.116 | F27: 0.0493 | G27: 0.035294118 | H27: 0.08 | I27: =IFERROR(C27/D27,"") | J27: =IFERROR(D27/C27,"") | K27: =IFERROR(E27/C27,"") | L27: =IFERROR(F27-G27,"") | M27: =IFERROR(J27-F27,"") | N27: =IFERROR(J27-L27,"") | O27: =IFERROR(J27-H27,"") | P27: =IFERROR(K27-F27,"") | Q27: 0.43877551 | R27: 0.58163265 | S27: 0.82653061 | T27: 0.31632653 | U27: 0.41666667 | V27: 0.77564103 | X27: 0.55926217 | Y27: =IF(X27="","",IF(X27>='Léeme'!$B$6,"barato",IF(X27<'Léeme'!$B$7,"caro","medio"))) | Z27: 0.332427 | AA27: 0.18522449
A28: 2001-T2 | B28: 37071 | C28: 14.779999 | D28: 1.2585 | E28: 1.128 | F28: 0.0542 | G28: 0.035630841 | H28: 0.0801 | I28: =IFERROR(C28/D28,"") | J28: =IFERROR(D28/C28,"") | K28: =IFERROR(E28/C28,"") | L28: =IFERROR(F28-G28,"") | M28: =IFERROR(J28-F28,"") | N28: =IFERROR(J28-L28,"") | O28: =IFERROR(J28-H28,"") | P28: =IFERROR(K28-F28,"") | Q28: 0.29807692 | R28: 0.31730769 | S28: 0.60576923 | T28: 0.14423077 | U28: 0.2037037 | V28: 0.32716049 | X28: 0.31604147 | Y28: =IF(X28="","",IF(X28>='Léeme'!$B$6,"barato",IF(X28<'Léeme'!$B$7,"caro","medio"))) | Z28: 0.32472171 | AA28: 0.14314918
A29: 2001-T3 | B29: 37162 | C29: 14.500001 | D29: 1.2585 | E29: 1.134 | F29: 0.046 | G29: 0.027214823 | H29: 0.0805 | I29: =IFERROR(C29/D29,"") | J29: =IFERROR(D29/C29,"") | K29: =IFERROR(E29/C29,"") | L29: =IFERROR(F29-G29,"") | M29: =IFERROR(J29-F29,"") | N29: =IFERROR(J29-L29,"") | O29: =IFERROR(J29-H29,"") | P29: =IFERROR(K29-F29,"") | Q29: 0.3 | R29: 0.46363636 | S29: 0.60909091 | T29: 0.19090909 | U29: 0.23214286 | V29: 0.64880952 | X29: 0.40743146 | Y29: =IF(X29="","",IF(X29>='Léeme'!$B$6,"barato",IF(X29<'Léeme'!$B$7,"caro","medio"))) | Z29: 0.24828848 | AA29: 0.16924143
A30: 2001-T4 | B30: 37256 | C30: 14.7 | D30: 1.2585 | E30: 1.14 | F30: 0.0507 | G30: 0.018943743 | H30: 0.0802 | I30: =IFERROR(C30/D30,"") | J30: =IFERROR(D30/C30,"") | K30: =IFERROR(E30/C30,"") | L30: =IFERROR(F30-G30,"") | M30: =IFERROR(J30-F30,"") | N30: =IFERROR(J30-L30,"") | O30: =IFERROR(J30-H30,"") | P30: =IFERROR(K30-F30,"") | Q30: 0.28448276 | R30: 0.31896552 | S30: 0.30172414 | T30: 0.14655172 | U30: 0.21264368 | V30: 0.45402299 | X30: 0.28639847 | Y30: =IF(X30="","",IF(X30>='Léeme'!$B$6,"barato",IF(X30<'Léeme'!$B$7,"caro","medio"))) | Z30: 0.25733902 | AA30: 0.19181306
A31: 2002-T1 | B31: 37343 | C31: 16.600001 | D31: 1.2585 | E31: 1.146 | F31: 0.0542 | G31: 0.011363636 | H31: 0.0816 | I31: =IFERROR(C31/D31,"") | J31: =IFERROR(D31/C31,"") | K31: =IFERROR(E31/C31,"") | L31: =IFERROR(F31-G31,"") | M31: =IFERROR(J31-F31,"") | N31: =IFERROR(J31-L31,"") | O31: =IFERROR(J31-H31,"") | P31: =IFERROR(K31-F31,"") | Q31: 0.024590164 | R31: 0.1557377 | S31: 0.0081967213 | T31: 0.0081967213 | U31: 0.016666667 | V31: 0.16111111 | X31: 0.062416515 | Y31: =IF(X31="","",IF(X31>='Léeme'!$B$6,"barato",IF(X31<'Léeme'!$B$7,"caro","medio"))) | Z31: 0.1366948 | AA31: 0.16246322
A32: 2002-T2 | B32: 37435 | C32: 18.459999 | D32: 1.3285 | E32: 1.158 | F32: 0.0486 | G32: 0.012408347 | H32: 0.0798 | I32: =IFERROR(C32/D32,"") | J32: =IFERROR(D32/C32,"") | K32: =IFERROR(E32/C32,"") | L32: =IFERROR(F32-G32,"") | M32: =IFERROR(J32-F32,"") | N32: =IFERROR(J32-L32,"") | O32: =IFERROR(J32-H32,"") | P32: =IFERROR(K32-F32,"") | Q32: 0.0078125 | R32: 0.1796875 | S32: 0.0390625 | T32: 0.0078125 | U32: 0.0053763441 | V32: 0.11290323 | X32: 0.058775762 | Y32: =IF(X32="","",IF(X32>='Léeme'!$B$6,"barato",IF(X32<'Léeme'!$B$7,"caro","medio"))) | Z32: 0.10667046 | AA32: 0.11750117
A33: 2002-T3 | B33: 37529 | C33: 17.075001 | D33: 1.3285 | E33: 1.158 | F33: 0.0363 | G33: 0.017474634 | H33: 0.074 | I33: =IFERROR(C33/D33,"") | J33: =IFERROR(D33/C33,"") | K33: =IFERROR(E33/C33,"") | L33: =IFERROR(F33-G33,"") | M33: =IFERROR(J33-F33,"") | N33: =IFERROR(J33-L33,"") | O33: =IFERROR(J33-H33,"") | P33: =IFERROR(K33-F33,"") | Q33: 0.082089552 | R33: 0.58955224 | S33: 0.45522388 | T33: 0.20149254 | U33: 0.026041667 | V33: 0.671875 | X33: 0.33771248 | Y33: =IF(X33="","",IF(X33>='Léeme'!$B$6,"barato",IF(X33<'Léeme'!$B$7,"caro","medio"))) | Z33: 0.22199388 | AA33: 0.15709507
A34: 2002-T4 | B34: 37621 | C34: 17.499999 | D34: 1.3285 | E34: 1.17 | F34: 0.0383 | G34: 0.022535211 | H34: 0.073 | I34: =IFERROR(C34/D34,"") | J34: =IFERROR(D34/C34,"") | K34: =IFERROR(E34/C34,"") | L34: =IFERROR(F34-G34,"") | M34: =IFERROR(J34-F34,"") | N34: =IFERROR(J34-L34,"") | O34: =IFERROR(J34-H34,"") | P34: =IFERROR(K34-F34,"") | Q34: 0.05 | R34: 0.43571429 | S34: 0.47857143 | T34: 0.19285714 | U34: 0.035353535 | V34: 0.57070707 | X34: 0.29386724 | Y34: =IF(X34="","",IF(X34>='Léeme'!$B$6,"barato",IF(X34<'Léeme'!$B$7,"caro","medio"))) | Z34: 0.20096399 | AA34: 0.14322983
A35: 2003-T1 | B35: 37711 | C35: 17.874999 | D35: 1.38 | E35: 1.176 | F35: 0.0383 | G35: 0.031460674 | H35: 0.0693 | I35: =IFERROR(C35/D35,"") | J35: =IFERROR(D35/C35,"") | K35: =IFERROR(E35/C35,"") | L35: =IFERROR(F35-G35,"") | M35: =IFERROR(J35-F35,"") | N35: =IFERROR(J35-L35,"") | O35: =IFERROR(J35-H35,"") | P35: =IFERROR(K35-F35,"") | Q35: 0.089041096 | R35: 0.44520548 | S35: 0.70547945 | T35: 0.39041096 | U35: 0.014705882 | V35: 0.5245098 | W35: 0.12162162 | X35: 0.32728204 | Y35: =IF(X35="","",IF(X35>='Léeme'!$B$6,"barato",IF(X35<'Léeme'!$B$7,"caro","medio"))) | Z35: 0.30949243 | AA35: 0.1263843
A36: 2003-T2 | B36: 37802 | C36: 19.039999 | D36: 1.38 | E36: 1.182 | F36: 0.0354 | G36: 0.018941504 | H36: 0.0638 | I36: =IFERROR(C36/D36,"") | J36: =IFERROR(D36/C36,"") | K36: =IFERROR(E36/C36,"") | L36: =IFERROR(F36-G36,"") | M36: =IFERROR(J36-F36,"") | N36: =IFERROR(J36-L36,"") | O36: =IFERROR(J36-H36,"") | P36: =IFERROR(K36-F36,"") | Q36: 0.019736842 | R36: 0.375 | S36: 0.38815789 | T36: 0.44078947 | U36: 0.0047619048 | V36: 0.45238095 | W36: 0.0375 | X36: 0.2454753 | Y36: =IF(X36="","",IF(X36>='Léeme'!$B$6,"barato",IF(X36<'Léeme'!$B$7,"caro","medio"))) | Z36: 0.14862547 | AA36: 0.086431272
A37: 2003-T3 | B37: 37894 | C37: 19.825001 | D37: 1.38 | E37: 1.188 | F37: 0.0396 | G37: 0.022160665 | H37: 0.0665 | I37: =IFERROR(C37/D37,"") | J37: =IFERROR(D37/C37,"") | K37: =IFERROR(E37/C37,"") | L37: =IFERROR(F37-G37,"") | M37: =IFERROR(J37-F37,"") | N37: =IFERROR(J37-L37,"") | O37: =IFERROR(J37-H37,"") | P37: =IFERROR(K37-F37,"") | Q37: 0.012658228 | R37: 0.28481013 | S37: 0.33544304 | T37: 0.22151899 | U37: 0.023148148 | V37: 0.28240741 | W37: 0.034883721 | X37: 0.17069567 | Y37: =IF(X37="","",IF(X37>='Léeme'!$B$6,"barato",IF(X37<'Léeme'!$B$7,"caro","medio"))) | Z37: 0.19041865 | AA37: 0.10362004
A38: 2003-T4 | B38: 37986 | C38: 20 | D38: 1.38 | E38: 1.2 | F38: 0.0427 | G38: 0.019283747 | H38: 0.0662 | I38: =IFERROR(C38/D38,"") | J38: =IFERROR(D38/C38,"") | K38: =IFERROR(E38/C38,"") | L38: =IFERROR(F38-G38,"") | M38: =IFERROR(J38-F38,"") | N38: =IFERROR(J38-L38,"") | O38: =IFERROR(J38-H38,"") | P38: =IFERROR(K38-F38,"") | Q38: 0.018292683 | R38: 0.22560976 | S38: 0.26219512 | T38: 0.20121951 | U38: 0.040540541 | V38: 0.22972973 | W38: 0.097826087 | X38: 0.15363049 | Y38: =IF(X38="","",IF(X38>='Léeme'!$B$6,"barato",IF(X38<'Léeme'!$B$7,"caro","medio"))) | Z38: 0.3236333 | AA38: 0.080513851
A39: 2004-T1 | B39: 38077 | C39: 22.325 | D39: 1.46 | E39: 1.2 | F39: 0.0386 | G39: 0.016884532 | H39: 0.0619 | I39: =IFERROR(C39/D39,"") | J39: =IFERROR(D39/C39,"") | K39: =IFERROR(E39/C39,"") | L39: =IFERROR(F39-G39,"") | M39: =IFERROR(J39-F39,"") | N39: =IFERROR(J39-L39,"") | O39: =IFERROR(J39-H39,"") | P39: =IFERROR(K39-F39,"") | Q39: 0.0058823529 | R39: 0.26470588 | S39: 0.20588235 | T39: 0.26470588 | U39: 0.0043859649 | V39: 0.1622807 | W39: 0.010204082 | X39: 0.1311496 | Y39: =IF(X39="","",IF(X39>='Léeme'!$B$6,"barato",IF(X39<'Léeme'!$B$7,"caro","medio"))) | Z39: 0.07290712 | AA39: 0.015663931
A40: 2004-T2 | B40: 38168 | C40: 20.865 | D40: 1.46 | E40: 1.218 | F40: 0.0462 | G40: 0.028977583 | H40: 0.0676 | I40: =IFERROR(C40/D40,"") | J40: =IFERROR(D40/C40,"") | K40: =IFERROR(E40/C40,"") | L40: =IFERROR(F40-G40,"") | M40: =IFERROR(J40-F40,"") | N40: =IFERROR(J40-L40,"") | O40: =IFERROR(J40-H40,"") | P40: =IFERROR(K40-F40,"") | Q40: 0.096590909 | R40: 0.14204545 | S40: 0.40340909 | T40: 0.17613636 | U40: 0.02991453 | V40: 0.064102564 | W40: 0.25961538 | X40: 0.16740204 | Y40: =IF(X40="","",IF(X40>='Léeme'!$B$6,"barato",IF(X40<'Léeme'!$B$7,"caro","medio"))) | Z40: 0.25468793 | AA40: 0.062106587
A41: 2004-T3 | B41: 38260 | C41: 22.515 | D41: 1.46 | E41: 1.308 | F41: 0.0414 | G41: 0.025474255 | H41: 0.0622 | I41: =IFERROR(C41/D41,"") | J41: =IFERROR(D41/C41,"") | K41: =IFERROR(E41/C41,"") | L41: =IFERROR(F41-G41,"") | M41: =IFERROR(J41-F41,"") | N41: =IFERROR(J41-L41,"") | O41: =IFERROR(J41-H41,"") | P41: =IFERROR(K41-F41,"") | Q41: 0.0054945055 | R41: 0.13736264 | S41: 0.33516484 | T41: 0.19230769 | U41: 0.020833333 | V41: 0.22916667 | W41: 0.20909091 | X41: 0.1613458 | Y41: =IF(X41="","",IF(X41>='Léeme'!$B$6,"barato",IF(X41<'Léeme'!$B$7,"caro","medio"))) | Z41: 0.10968743 | AA41: 0.079827328
A42: 2004-T4 | B42: 38352 | C42: 25.29 | D42: 1.46 | E42: 1.32 | F42: 0.0424 | G42: 0.036216216 | H42: 0.0616 | I42: =IFERROR(C42/D42,"") | J42: =IFERROR(D42/C42,"") | K42: =IFERROR(E42/C42,"") | L42: =IFERROR(F42-G42,"") | M42: =IFERROR(J42-F42,"") | N42: =IFERROR(J42-L42,"") | O42: =IFERROR(J42-H42,"") | P42: =IFERROR(K42-F42,"") | Q42: 0.0053191489 | R42: 0.04787234 | S42: 0.38829787 | T42: 0.037234043 | U42: 0.0040650407 | V42: 0.06097561 | W42: 0.0086206897 | X42: 0.078912106 | Y42: =IF(X42="","",IF(X42>='Léeme'!$B$6,"barato",IF(X42<'Léeme'!$B$7,"caro","medio"))) | Z42: -0.10485478 | AA42: 0.057835034
A43: 2005-T1 | B43: 38442 | C43: 22.880001 | D43: 1.5 | E43: 1.332 | F43: 0.045 | G43: 0.030530262 | H43: 0.0617 | I43: =IFERROR(C43/D43,"") | J43: =IFERROR(D43/C43,"") | K43: =IFERROR(E43/C43,"") | L43: =IFERROR(F43-G43,"") | M43: =IFERROR(J43-F43,"") | N43: =IFERROR(J43-L43,"") | O43: =IFERROR(J43-H43,"") | P43: =IFERROR(K43-F43,"") | Q43: 0.077319588 | R43: 0.10824742 | S43: 0.37628866 | T43: 0.33505155 | U43: 0.075396825 | V43: 0.091269841 | W43: 0.40163934 | X43: 0.20931618 | Y43: =IF(X43="","",IF(X43>='Léeme'!$B$6,"barato",IF(X43<'Léeme'!$B$7,"caro","medio"))) | Z43: 0.10859966 | AA43: 0.11652919
A44: 2005-T2 | B44: 38533 | C44: 25.039999 | D44: 1.5 | E44: 1.332 | F44: 0.0394 | G44: 0.02869288 | H44: 0.0586 | I44: =IFERROR(C44/D44,"") | J44: =IFERROR(D44/C44,"") | K44: =IFERROR(E44/C44,"") | L44: =IFERROR(F44-G44,"") | M44: =IFERROR(J44-F44,"") | N44: =IFERROR(J44-L44,"") | O44: =IFERROR(J44-H44,"") | P44: =IFERROR(K44-F44,"") | Q44: 0.025 | R44: 0.115 | S44: 0.345 | T44: 0.175 | U44: 0.019379845 | V44: 0.13565891 | W44: 0.1328125 | X44: 0.13540732 | Y44: =IF(X44="","",IF(X44>='Léeme'!$B$6,"barato",IF(X44<'Léeme'!$B$7,"caro","medio"))) | Z44: -0.081990732 | AA44: 0.09395317
A45: 2005-T3 | B45: 38625 | C45: 23.910001 | D45: 1.5 | E45: 1.392 | F45: 0.0434 | G45: 0.036469345 | H45: 0.0612 | I45: =IFERROR(C45/D45,"") | J45: =IFERROR(D45/C45,"") | K45: =IFERROR(E45/C45,"") | L45: =IFERROR(F45-G45,"") | M45: =IFERROR(J45-F45,"") | N45: =IFERROR(J45-L45,"") | O45: =IFERROR(J45-H45,"") | P45: =IFERROR(K45-F45,"") | Q45: 0.082524272 | R45: 0.082524272 | S45: 0.52912621 | T45: 0.19902913 | U45: 0.11742424 | V45: 0.20833333 | W45: 0.38059701 | X45: 0.22850835 | Y45: =IF(X45="","",IF(X45>='Léeme'!$B$6,"barato",IF(X45<'Léeme'!$B$7,"caro","medio"))) | Z45: 0.085666031 | AA45: 0.12757802
A46: 2005-T4 | B46: 38716 | C46: 21.619999 | D46: 1.5 | E46: 1.392 | F46: 0.0439 | G46: 0.033385498 | H46: 0.0619 | I46: =IFERROR(C46/D46,"") | J46: =IFERROR(D46/C46,"") | K46: =IFERROR(E46/C46,"") | L46: =IFERROR(F46-G46,"") | M46: =IFERROR(J46-F46,"") | N46: =IFERROR(J46-L46,"") | O46: =IFERROR(J46-H46,"") | P46: =IFERROR(K46-F46,"") | Q46: 0.20283019 | R46: 0.34433962 | S46: 0.57075472 | T46: 0.53301887 | U46: 0.24814815 | V46: 0.42592593 | W46: 0.79285714 | X46: 0.44541066 | Y46: =IF(X46="","",IF(X46>='Léeme'!$B$6,"barato",IF(X46<'Léeme'!$B$7,"caro","medio"))) | Z46: 0.34399341 | AA46: 0.15459276
... A108: 2021-T2 | B108: 44377 | C108: 66.739997 | D108: 3.12 | E108: 2.832 | F108: 0.0145 | G108: 0.049182571 | H108: 0.0336 | I108: =IFERROR(C108/D108,"") | J108: =IFERROR(D108/C108,"") | K108: =IFERROR(E108/C108,"") | L108: =IFERROR(F108-G108,"") | M108: =IFERROR(J108-F108,"") | N108: =IFERROR(J108-L108,"") | O108: =IFERROR(J108-H108,"") | P108: =IFERROR(K108-F108,"") | Q108: 0.11472603 | R108: 0.64554795 | S108: 0.95034247 | T108: 0.83390411 | U108: 0.098130841 | V108: 0.69314642 | W108: 0.58789062 | X108: 0.56052692 | Y108: =IF(X108="","",IF(X108>='Léeme'!$B$6,"barato",IF(X108<'Léeme'!$B$7,"caro","medio"))) | Z108: 0.091817442 | AA108: 0.032978029
A109: 2021-T3 | B109: 44469 | C109: 64.860002 | D109: 3.12 | E109: 2.832 | F109: 0.0152 | G109: 0.051520153 | H109: 0.0336 | I109: =IFERROR(C109/D109,"") | J109: =IFERROR(D109/C109,"") | K109: =IFERROR(E109/C109,"") | L109: =IFERROR(F109-G109,"") | M109: =IFERROR(J109-F109,"") | N109: =IFERROR(J109-L109,"") | O109: =IFERROR(J109-H109,"") | P109: =IFERROR(K109-F109,"") | Q109: 0.16101695 | R109: 0.6559322 | S109: 0.96101695 | T109: 0.83898305 | U109: 0.12808642 | V109: 0.71759259 | W109: 0.63899614 | X109: 0.58594633 | Y109: =IF(X109="","",IF(X109>='Léeme'!$B$6,"barato",IF(X109<'Léeme'!$B$7,"caro","medio"))) | Z109: -0.04135941
A110: 2021-T4 | B110: 44561 | C110: 71.589996 | D110: 3.12 | E110: 2.964 | F110: 0.0152 | G110: 0.069019704 | H110: 0.0337 | I110: =IFERROR(C110/D110,"") | J110: =IFERROR(D110/C110,"") | K110: =IFERROR(E110/C110,"") | L110: =IFERROR(F110-G110,"") | M110: =IFERROR(J110-F110,"") | N110: =IFERROR(J110-L110,"") | O110: =IFERROR(J110-H110,"") | P110: =IFERROR(K110-F110,"") | Q110: 0.065436242 | R110: 0.49832215 | S110: 0.99161074 | T110: 0.7533557 | U110: 0.093272171 | V110: 0.59174312 | W110: 0.44465649 | X110: 0.49119952 | Y110: =IF(X110="","",IF(X110>='Léeme'!$B$6,"barato",IF(X110<'Léeme'!$B$7,"caro","medio"))) | Z110: -0.081729753
A111: 2022-T1 | B111: 44651 | C111: 69.300003 | D111: 3.12 | E111: 2.964 | F111: 0.0232 | G111: 0.079372788 | H111: 0.0428 | I111: =IFERROR(C111/D111,"") | J111: =IFERROR(D111/C111,"") | K111: =IFERROR(E111/C111,"") | L111: =IFERROR(F111-G111,"") | M111: =IFERROR(J111-F111,"") | N111: =IFERROR(J111-L111,"") | O111: =IFERROR(J111-H111,"") | P111: =IFERROR(K111-F111,"") | Q111: 0.094684385 | R111: 0.22757475 | S111: 0.99169435 | T111: 0.40033223 | U111: 0.12575758 | V111: 0.33181818 | W111: 0.52264151 | X111: 0.384929 | Y111: =IF(X111="","",IF(X111>='Léeme'!$B$6,"barato",IF(X111<'Léeme'!$B$7,"caro","medio"))) | Z111: -0.05240725
A112: 2022-T2 | B112: 44742 | C112: 68.260002 | D112: 3.12 | E112: 2.976 | F112: 0.0298 | G112: 0.085381712 | H112: 0.0534 | I112: =IFERROR(C112/D112,"") | J112: =IFERROR(D112/C112,"") | K112: =IFERROR(E112/C112,"") | L112: =IFERROR(F112-G112,"") | M112: =IFERROR(J112-F112,"") | N112: =IFERROR(J112-L112,"") | O112: =IFERROR(J112-H112,"") | P112: =IFERROR(K112-F112,"") | Q112: 0.12335526 | R112: 0.057565789 | S112: 0.98848684 | T112: 0.037828947 | U112: 0.14564565 | V112: 0.12762763 | W112: 0.61380597 | X112: 0.29918801 | Y112: =IF(X112="","",IF(X112>='Léeme'!$B$6,"barato",IF(X112<'Léeme'!$B$7,"caro","medio"))) | Z112: -0.090286046
A113: 2022-T3 | B113: 44834 | C113: 58.200001 | D113: 3.12 | E113: 2.976 | F113: 0.0383 | G113: 0.082225792 | H113: 0.0603 | I113: =IFERROR(C113/D113,"") | J113: =IFERROR(D113/C113,"") | K113: =IFERROR(E113/C113,"") | L113: =IFERROR(F113-G113,"") | M113: =IFERROR(J113-F113,"") | N113: =IFERROR(J113-L113,"") | O113: =IFERROR(J113-H113,"") | P113: =IFERROR(K113-F113,"") | Q113: 0.3762215 | R113: 0.050488599 | S113: 0.96579805 | T113: 0.060260586 | U113: 0.3735119 | V113: 0.09375 | W113: 0.92066421 | X113: 0.40581355 | Y113: =IF(X113="","",IF(X113>='Léeme'!$B$6,"barato",IF(X113<'Léeme'!$B$7,"caro","medio"))) | Z113: -0.10693088
A114: 2022-T4 | B114: 44925 | C114: 63.43 | D114: 3.12 | E114: 2.988 | F114: 0.0388 | G114: 0.071228565 | H114: 0.0584 | I114: =IFERROR(C114/D114,"") | J114: =IFERROR(D114/C114,"") | K114: =IFERROR(E114/C114,"") | L114: =IFERROR(F114-G114,"") | M114: =IFERROR(J114-F114,"") | N114: =IFERROR(J114-L114,"") | O114: =IFERROR(J114-H114,"") | P114: =IFERROR(K114-F114,"") | Q114: 0.21451613 | R114: 0.0080645161 | S114: 0.8983871 | T114: 0.014516129 | U114: 0.24926254 | V114: 0.028023599 | W114: 0.78284672 | X114: 0.31365953 | Y114: =IF(X114="","",IF(X114>='Léeme'!$B$6,"barato",IF(X114<'Léeme'!$B$7,"caro","medio"))) | Z114: -0.055740469
A115: 2023-T1 | B115: 45016 | C115: 63.32 | D115: 3.12 | E115: 3.06 | F115: 0.0348 | G115: 0.059578207 | H115: 0.0566 | I115: =IFERROR(C115/D115,"") | J115: =IFERROR(D115/C115,"") | K115: =IFERROR(E115/C115,"") | L115: =IFERROR(F115-G115,"") | M115: =IFERROR(J115-F115,"") | N115: =IFERROR(J115-L115,"") | O115: =IFERROR(J115-H115,"") | P115: =IFERROR(K115-F115,"") | Q115: 0.22523962 | R115: 0.046325879 | S115: 0.84824281 | T115: 0.062300319 | U115: 0.2997076 | V115: 0.13596491 | W115: 0.81046931 | X115: 0.34689292 | Y115: =IF(X115="","",IF(X115>='Léeme'!$B$6,"barato",IF(X115<'Léeme'!$B$7,"caro","medio"))) | Z115: -0.10685563
A116: 2023-T2 | B116: 45107 | C116: 59.790001 | D116: 3.12 | E116: 3.072 | F116: 0.0381 | G116: 0.041318512 | H116: 0.0577 | I116: =IFERROR(C116/D116,"") | J116: =IFERROR(D116/C116,"") | K116: =IFERROR(E116/C116,"") | L116: =IFERROR(F116-G116,"") | M116: =IFERROR(J116-F116,"") | N116: =IFERROR(J116-L116,"") | O116: =IFERROR(J116-H116,"") | P116: =IFERROR(K116-F116,"") | Q116: 0.34018987 | R116: 0.036392405 | S116: 0.61867089 | T116: 0.096518987 | U116: 0.39275362 | V116: 0.12608696 | W116: 0.89821429 | X116: 0.35840386 | Y116: =IF(X116="","",IF(X116>='Léeme'!$B$6,"barato",IF(X116<'Léeme'!$B$7,"caro","medio"))) | Z116: -0.078639113
A117: 2023-T3 | B117: 45198 | C117: 49.939999 | D117: 3.12 | E117: 3.072 | F117: 0.0459 | G117: 0.037225048 | H117: 0.0639 | I117: =IFERROR(C117/D117,"") | J117: =IFERROR(D117/C117,"") | K117: =IFERROR(E117/C117,"") | L117: =IFERROR(F117-G117,"") | M117: =IFERROR(J117-F117,"") | N117: =IFERROR(J117-L117,"") | O117: =IFERROR(J117-H117,"") | P117: =IFERROR(K117-F117,"") | Q117: 0.55642633 | R117: 0.10815047 | S117: 0.5815047 | T117: 0.2460815 | U117: 0.60488506 | V117: 0.24281609 | W117: 0.98056537 | X117: 0.47434708 | Y117: =IF(X117="","",IF(X117>='Léeme'!$B$6,"barato",IF(X117<'Léeme'!$B$7,"caro","medio"))) | Z117: 0.30992786
A118: 2023-T4 | B118: 45289 | C118: 57.419998 | D118: 3.12 | E118: 3.084 | F118: 0.0388 | G118: 0.031333463 | H118: 0.0546 | I118: =IFERROR(C118/D118,"") | J118: =IFERROR(D118/C118,"") | K118: =IFERROR(E118/C118,"") | L118: =IFERROR(F118-G118,"") | M118: =IFERROR(J118-F118,"") | N118: =IFERROR(J118-L118,"") | O118: =IFERROR(J118-H118,"") | P118: =IFERROR(K118-F118,"") | Q118: 0.42391304 | R118: 0.091614907 | S118: 0.39906832 | T118: 0.31832298 | U118: 0.44301994 | V118: 0.20940171 | W118: 0.92132867 | X118: 0.4009528 | Y118: =IF(X118="","",IF(X118>='Léeme'!$B$6,"barato",IF(X118<'Léeme'!$B$7,"caro","medio"))) | Z118: -0.044587107
A119: 2024-T1 | B119: 45379 | C119: 54.099998 | D119: 3.12 | E119: 3.084 | F119: 0.042 | G119: 0.031570741 | H119: 0.0574 | I119: =IFERROR(C119/D119,"") | J119: =IFERROR(D119/C119,"") | K119: =IFERROR(E119/C119,"") | L119: =IFERROR(F119-G119,"") | M119: =IFERROR(J119-F119,"") | N119: =IFERROR(J119-L119,"") | O119: =IFERROR(J119-H119,"") | P119: =IFERROR(K119-F119,"") | Q119: 0.49076923 | R119: 0.093846154 | S119: 0.40153846 | T119: 0.33076923 | U119: 0.51553672 | V119: 0.21327684 | W119: 0.92906574 | X119: 0.42497177 | Y119: =IF(X119="","",IF(X119>='Léeme'!$B$6,"barato",IF(X119<'Léeme'!$B$7,"caro","medio"))) | Z119: 0.090205911
A120: 2024-T2 | B120: 45471 | C120: 52.82 | D120: 3.12 | E120: 3.156 | F120: 0.0436 | G120: 0.032442786 | H120: 0.0584 | I120: =IFERROR(C120/D120,"") | J120: =IFERROR(D120/C120,"") | K120: =IFERROR(E120/C120,"") | L120: =IFERROR(F120-G120,"") | M120: =IFERROR(J120-F120,"") | N120: =IFERROR(J120-L120,"") | O120: =IFERROR(J120-H120,"") | P120: =IFERROR(K120-F120,"") | Q120: 0.51981707 | R120: 0.096036585 | S120: 0.4222561 | T120: 0.34603659 | U120: 0.56442577 | V120: 0.267507 | W120: 0.92979452 | X120: 0.44941052 | Y120: =IF(X120="","",IF(X120>='Léeme'!$B$6,"barato",IF(X120<'Léeme'!$B$7,"caro","medio"))) | Z120: 0.12889889
... A124: 2025-T2 | B124: 45838 | C124: 57.610001 | D124: 3.12 | E124: 3.228 | F124: 0.0424 | G124: 0.023772651 | H124: 0.0608 | I124: =IFERROR(C124/D124,"") | J124: =IFERROR(D124/C124,"") | K124: =IFERROR(E124/C124,"") | L124: =IFERROR(F124-G124,"") | M124: =IFERROR(J124-F124,"") | N124: =IFERROR(J124-L124,"") | O124: =IFERROR(J124-H124,"") | P124: =IFERROR(K124-F124,"") | Q124: 0.41911765 | R124: 0.042647059 | S124: 0.11323529 | T124: 0.080882353 | U124: 0.5 | V124: 0.17208672 | W124: 0.72532895 | X124: 0.29332829 | Y124: =IF(X124="","",IF(X124>='Léeme'!$B$6,"barato",IF(X124<'Léeme'!$B$7,"caro","medio"))) | Z124: 0.12699296
A125: 2025-T3 | B125: 45930 | C125: 60.790001 | D125: 3.12 | E125: 3.228 | F125: 0.0416 | G125: 0.029385917 | H125: 0.0579 | I125: =IFERROR(C125/D125,"") | J125: =IFERROR(D125/C125,"") | K125: =IFERROR(E125/C125,"") | L125: =IFERROR(F125-G125,"") | M125: =IFERROR(J125-F125,"") | N125: =IFERROR(J125-L125,"") | O125: =IFERROR(J125-H125,"") | P125: =IFERROR(K125-F125,"") | Q125: 0.28717201 | R125: 0.010204082 | S125: 0.19970845 | T125: 0.086005831 | U125: 0.40725806 | V125: 0.084677419 | W125: 0.60423453 | X125: 0.23989434 | Y125: =IF(X125="","",IF(X125>='Léeme'!$B$6,"barato",IF(X125<'Léeme'!$B$7,"caro","medio")))
A126: 2025-T4 | B126: 46022 | C126: 56.369999 | D126: 3.12 | E126: 3.24 | F126: 0.0418 | G126: 0.026964439 | H126: 0.0589 | I126: =IFERROR(C126/D126,"") | J126: =IFERROR(D126/C126,"") | K126: =IFERROR(E126/C126,"") | L126: =IFERROR(F126-G126,"") | M126: =IFERROR(J126-F126,"") | N126: =IFERROR(J126-L126,"") | O126: =IFERROR(J126-H126,"") | P126: =IFERROR(K126-F126,"") | Q126: 0.45809249 | R126: 0.076589595 | S126: 0.23265896 | T126: 0.20375723 | U126: 0.53466667 | V126: 0.284 | W126: 0.76290323 | X126: 0.36466688 | Y126: =IF(X126="","",IF(X126>='Léeme'!$B$6,"barato",IF(X126<'Léeme'!$B$7,"caro","medio")))
A127: 2026-T1 | B127: 46112 | C127: 61.18 | D127: 4.25 | E127: 3.252 | F127: 0.043 | G127: 0.024340041 | H127: 0.0614 | I127: =IFERROR(C127/D127,"") | J127: =IFERROR(D127/C127,"") | K127: =IFERROR(E127/C127,"") | L127: =IFERROR(F127-G127,"") | M127: =IFERROR(J127-F127,"") | N127: =IFERROR(J127-L127,"") | O127: =IFERROR(J127-H127,"") | P127: =IFERROR(K127-F127,"") | Q127: 0.67191977 | R127: 0.47994269 | S127: 0.54011461 | T127: 0.74641834 | U127: 0.40873016 | V127: 0.054232804 | W127: 0.97603834 | X127: 0.55391382 | Y127: =IF(X127="","",IF(X127>='Léeme'!$B$6,"barato",IF(X127<'Léeme'!$B$7,"caro","medio")))
A128: 2026-T2 | B128: 46203 | C128: 61.959999 | D128: 4.25 | E128: 3.252 | F128: 0.0444 | G128: 0.041666147 | H128: 0.0593 | I128: =IFERROR(C128/D128,"") | J128: =IFERROR(D128/C128,"") | K128: =IFERROR(E128/C128,"") | L128: =IFERROR(F128-G128,"") | M128: =IFERROR(J128-F128,"") | N128: =IFERROR(J128-L128,"") | O128: =IFERROR(J128-H128,"") | P128: =IFERROR(K128-F128,"") | Q128: 0.65767045 | R128: 0.39914773 | S128: 0.79119318 | T128: 0.77982955 | U128: 0.39501312 | V128: 0.027559055 | W128: 0.96677215 | X128: 0.57388361 | Y128: =IF(X128="","",IF(X128>='Léeme'!$B$6,"barato",IF(X128<'Léeme'!$B$7,"caro","medio")))
A129: 2026-T3 | B129: 46293 | C129: 55.330002 | D129: 4.25 | E129: 3.252 | F129: 0.0524 | G129: 0.033530163 | H129: 0.0663 | I129: =IFERROR(C129/D129,"") | J129: =IFERROR(D129/C129,"") | K129: =IFERROR(E129/C129,"") | L129: =IFERROR(F129-G129,"") | M129: =IFERROR(J129-F129,"") | N129: =IFERROR(J129-L129,"") | O129: =IFERROR(J129-H129,"") | P129: =IFERROR(K129-F129,"") | Q129: 0.76760563 | R129: 0.40985915 | S129: 0.6915493 | T129: 0.81267606 | U129: 0.57942708 | V129: 0.014322917 | W129: 0.98275862 | X129: 0.60831411 | Y129: =IF(X129="","",IF(X129>='Léeme'!$B$6,"barato",IF(X129<'Léeme'!$B$7,"caro","medio")))

Sheet WPC
A1: Trimestre | B1: Fecha | C1: Precio | D1: Flujo por acción, 12 meses | E1: Dividendo anualizado | F1: Treasury 10 años | G1: Inflación 12 meses | H1: Bonos Baa | I1: Múltiplo precio/flujo | J1: Yield de flujo | K1: Yield de dividendo | L1: Tasa real | M1: Prima sobre el Treasury | N1: Prima sobre la tasa real | O1: Prima sobre bonos Baa | P1: Dividendo sobre el Treasury | Q1: Percentil: Múltiplo P/FFO | R1: Percentil: Prima sobre el Treasury | S1: Percentil: Prima sobre la tasa real | T1: Percentil: Prima sobre bonos Baa | U1: Percentil: Yield de dividendo | V1: Percentil: Dividendo sobre el Treasury | W1: Percentil: Múltiplo contra sus últimos 5 años | X1: Percentil: Consenso de los siete | Y1: Señal del consenso | Z1: Retorno anual, 1 año después | AA1: Retorno anual, 5 años después
A2: 1998-T1 | B2: 35885 | C2: 20.125 | E2: 1.648 | F2: 0.0567 | G2: 0.014402004 | H2: 0.0736 | I2: =IFERROR(C2/D2,"") | J2: =IFERROR(D2/C2,"") | K2: =IFERROR(E2/C2,"") | L2: =IFERROR(F2-G2,"") | M2: =IFERROR(J2-F2,"") | N2: =IFERROR(J2-L2,"") | O2: =IFERROR(J2-H2,"") | P2: =IFERROR(K2-F2,"") | Y2: =IF(X2="","",IF(X2>='Léeme'!$B$6,"barato",IF(X2<'Léeme'!$B$7,"caro","medio"))) | Z2: -0.059405357 | AA2: 0.11803106
A3: 1998-T2 | B3: 35976 | C3: 19.75 | E3: 1.648 | F3: 0.0544 | G3: 0.016885553 | H3: 0.0713 | I3: =IFERROR(C3/D3,"") | J3: =IFERROR(D3/C3,"") | K3: =IFERROR(E3/C3,"") | L3: =IFERROR(F3-G3,"") | M3: =IFERROR(J3-F3,"") | N3: =IFERROR(J3-L3,"") | O3: =IFERROR(J3-H3,"") | P3: =IFERROR(K3-F3,"") | Y3: =IF(X3="","",IF(X3>='Léeme'!$B$6,"barato",IF(X3<'Léeme'!$B$7,"caro","medio"))) | Z3: -0.062080419 | AA3: 0.16246145
A4: 1998-T3 | B4: 36068 | C4: 19.75 | E4: 1.648 | F4: 0.0444 | G4: 0.016169154 | H4: 0.0709 | I4: =IFERROR(C4/D4,"") | J4: =IFERROR(D4/C4,"") | K4: =IFERROR(E4/C4,"") | L4: =IFERROR(F4-G4,"") | M4: =IFERROR(J4-F4,"") | N4: =IFERROR(J4-L4,"") | O4: =IFERROR(J4-H4,"") | P4: =IFERROR(K4-F4,"") | Y4: =IF(X4="","",IF(X4>='Léeme'!$B$6,"barato",IF(X4<'Léeme'!$B$7,"caro","medio"))) | Z4: 0.091519221 | AA4: 0.17482243
A5: 1998-T4 | B5: 36160 | C5: 19.6875 | E5: 1.648 | F5: 0.0465 | G5: 0.014842301 | H5: 0.0726 | I5: =IFERROR(C5/D5,"") | J5: =IFERROR(D5/C5,"") | K5: =IFERROR(E5/C5,"") | L5: =IFERROR(F5-G5,"") | M5: =IFERROR(J5-F5,"") | N5: =IFERROR(J5-L5,"") | O5: =IFERROR(J5-H5,"") | P5: =IFERROR(K5-F5,"") | Y5: =IF(X5="","",IF(X5>='Léeme'!$B$6,"barato",IF(X5<'Léeme'!$B$7,"caro","medio"))) | Z5: -0.072695071 | AA5: 0.16498631
A6: 1999-T1 | B6: 36250 | C6: 17.6875 | E6: 1.672 | F6: 0.0525 | G6: 0.016666667 | H6: 0.0753 | I6: =IFERROR(C6/D6,"") | J6: =IFERROR(D6/C6,"") | K6: =IFERROR(E6/C6,"") | L6: =IFERROR(F6-G6,"") | M6: =IFERROR(J6-F6,"") | N6: =IFERROR(J6-L6,"") | O6: =IFERROR(J6-H6,"") | P6: =IFERROR(K6-F6,"") | Y6: =IF(X6="","",IF(X6>='Léeme'!$B$6,"barato",IF(X6<'Léeme'!$B$7,"caro","medio"))) | Z6: 0.017710427 | AA6: 0.19181593
A7: 1999-T2 | B7: 36341 | C7: 17.25 | E7: 1.672 | F7: 0.0581 | G7: 0.020910209 | H7: 0.0805 | I7: =IFERROR(C7/D7,"") | J7: =IFERROR(D7/C7,"") | K7: =IFERROR(E7/C7,"") | L7: =IFERROR(F7-G7,"") | M7: =IFERROR(J7-F7,"") | N7: =IFERROR(J7-L7,"") | O7: =IFERROR(J7-H7,"") | P7: =IFERROR(K7-F7,"") | Y7: =IF(X7="","",IF(X7>='Léeme'!$B$6,"barato",IF(X7<'Léeme'!$B$7,"caro","medio"))) | Z7: 0.02836054 | AA7: 0.18678321
A8: 1999-T3 | B8: 36433 | C8: 20 | E8: 1.672 | F8: 0.059 | G8: 0.022643819 | H8: 0.0828 | I8: =IFERROR(C8/D8,"") | J8: =IFERROR(D8/C8,"") | K8: =IFERROR(E8/C8,"") | L8: =IFERROR(F8-G8,"") | M8: =IFERROR(J8-F8,"") | N8: =IFERROR(J8-L8,"") | O8: =IFERROR(J8-H8,"") | P8: =IFERROR(K8-F8,"") | Y8: =IF(X8="","",IF(X8>='Léeme'!$B$6,"barato",IF(X8<'Léeme'!$B$7,"caro","medio"))) | Z8: -0.049801123 | AA8: 0.15081861
A9: 1999-T4 | B9: 36525 | C9: 16.875 | E9: 1.672 | F9: 0.0645 | G9: 0.026203534 | H9: 0.0823 | I9: =IFERROR(C9/D9,"") | J9: =IFERROR(D9/C9,"") | K9: =IFERROR(E9/C9,"") | L9: =IFERROR(F9-G9,"") | M9: =IFERROR(J9-F9,"") | N9: =IFERROR(J9-L9,"") | O9: =IFERROR(J9-H9,"") | P9: =IFERROR(K9-F9,"") | Y9: =IF(X9="","",IF(X9>='Léeme'!$B$6,"barato",IF(X9<'Léeme'!$B$7,"caro","medio"))) | Z9: 0.1593801 | AA9: 0.22758979
A10: 2000-T1 | B10: 36616 | C10: 16.625 | E10: 1.692 | F10: 0.0603 | G10: 0.032179721 | H10: 0.0836 | I10: =IFERROR(C10/D10,"") | J10: =IFERROR(D10/C10,"") | K10: =IFERROR(E10/C10,"") | L10: =IFERROR(F10-G10,"") | M10: =IFERROR(J10-F10,"") | N10: =IFERROR(J10-L10,"") | O10: =IFERROR(J10-H10,"") | P10: =IFERROR(K10-F10,"") | Y10: =IF(X10="","",IF(X10>='Léeme'!$B$6,"barato",IF(X10<'Léeme'!$B$7,"caro","medio"))) | Z10: 0.25597285 | AA10: 0.19394365
A11: 2000-T2 | B11: 36707 | C11: 16.375001 | D11: 1.98 | E11: 1.692 | F11: 0.0603 | G11: 0.031325301 | H11: 0.0844 | I11: =IFERROR(C11/D11,"") | J11: =IFERROR(D11/C11,"") | K11: =IFERROR(E11/C11,"") | L11: =IFERROR(F11-G11,"") | M11: =IFERROR(J11-F11,"") | N11: =IFERROR(J11-L11,"") | O11: =IFERROR(J11-H11,"") | P11: =IFERROR(K11-F11,"") | Y11: =IF(X11="","",IF(X11>='Léeme'!$B$6,"barato",IF(X11<'Léeme'!$B$7,"caro","medio"))) | Z11: 0.21484502 | AA11: 0.18699838
A12: 2000-T3 | B12: 36798 | C12: 17.5625 | D12: 1.98 | E12: 1.692 | F12: 0.058 | G12: 0.033512867 | H12: 0.0832 | I12: =IFERROR(C12/D12,"") | J12: =IFERROR(D12/C12,"") | K12: =IFERROR(E12/C12,"") | L12: =IFERROR(F12-G12,"") | M12: =IFERROR(J12-F12,"") | N12: =IFERROR(J12-L12,"") | O12: =IFERROR(J12-H12,"") | P12: =IFERROR(K12-F12,"") | Y12: =IF(X12="","",IF(X12>='Léeme'!$B$6,"barato",IF(X12<'Léeme'!$B$7,"caro","medio"))) | Z12: 0.30372106 | AA12: 0.14827947
A13: 2000-T4 | B13: 36889 | C13: 18.1 | D13: 1.98 | E13: 1.692 | F13: 0.0512 | G13: 0.034441805 | H13: 0.0796 | I13: =IFERROR(C13/D13,"") | J13: =IFERROR(D13/C13,"") | K13: =IFERROR(E13/C13,"") | L13: =IFERROR(F13-G13,"") | M13: =IFERROR(J13-F13,"") | N13: =IFERROR(J13-L13,"") | O13: =IFERROR(J13-H13,"") | P13: =IFERROR(K13-F13,"") | Y13: =IF(X13="","",IF(X13>='Léeme'!$B$6,"barato",IF(X13<'Léeme'!$B$7,"caro","medio"))) | Z13: 0.39155696 | AA13: 0.12768385
A14: 2001-T1 | B14: 36980 | C14: 19.349999 | D14: 2.28 | E14: 1.692 | F14: 0.0493 | G14: 0.035294118 | H14: 0.08 | I14: =IFERROR(C14/D14,"") | J14: =IFERROR(D14/C14,"") | K14: =IFERROR(E14/C14,"") | L14: =IFERROR(F14-G14,"") | M14: =IFERROR(J14-F14,"") | N14: =IFERROR(J14-L14,"") | O14: =IFERROR(J14-H14,"") | P14: =IFERROR(K14-F14,"") | U14: 0.36486486 | V14: 0.52702703 | Y14: =IF(X14="","",IF(X14>='Léeme'!$B$6,"barato",IF(X14<'Léeme'!$B$7,"caro","medio"))) | Z14: 0.27760036 | AA14: 0.12431636
A15: 2001-T2 | B15: 37071 | C15: 18.500001 | D15: 2.28 | E15: 1.7 | F15: 0.0542 | G15: 0.035630841 | H15: 0.0801 | I15: =IFERROR(C15/D15,"") | J15: =IFERROR(D15/C15,"") | K15: =IFERROR(E15/C15,"") | L15: =IFERROR(F15-G15,"") | M15: =IFERROR(J15-F15,"") | N15: =IFERROR(J15-L15,"") | O15: =IFERROR(J15-H15,"") | P15: =IFERROR(K15-F15,"") | U15: 0.4625 | V15: 0.4875 | Y15: =IF(X15="","",IF(X15>='Léeme'!$B$6,"barato",IF(X15<'Léeme'!$B$7,"caro","medio"))) | Z15: 0.29170132 | AA15: 0.1185577
A16: 2001-T3 | B16: 37162 | C16: 21.35 | D16: 2.28 | E16: 1.704 | F16: 0.046 | G16: 0.027214823 | H16: 0.0805 | I16: =IFERROR(C16/D16,"") | J16: =IFERROR(D16/C16,"") | K16: =IFERROR(E16/C16,"") | L16: =IFERROR(F16-G16,"") | M16: =IFERROR(J16-F16,"") | N16: =IFERROR(J16-L16,"") | O16: =IFERROR(J16-H16,"") | P16: =IFERROR(K16-F16,"") | U16: 0.10465116 | V16: 0.31395349 | Y16: =IF(X16="","",IF(X16>='Léeme'!$B$6,"barato",IF(X16<'Léeme'!$B$7,"caro","medio"))) | Z16: 0.24946398 | AA16: 0.10748468
A17: 2001-T4 | B17: 37256 | C17: 23.2 | D17: 2.28 | E17: 1.708 | F17: 0.0507 | G17: 0.018943743 | H17: 0.0802 | I17: =IFERROR(C17/D17,"") | J17: =IFERROR(D17/C17,"") | K17: =IFERROR(E17/C17,"") | L17: =IFERROR(F17-G17,"") | M17: =IFERROR(J17-F17,"") | N17: =IFERROR(J17-L17,"") | O17: =IFERROR(J17-H17,"") | P17: =IFERROR(K17-F17,"") | U17: 0.010869565 | V17: 0.054347826 | Y17: =IF(X17="","",IF(X17>='Léeme'!$B$6,"barato",IF(X17<'Léeme'!$B$7,"caro","medio"))) | Z17: 0.128453 | AA17: 0.10792877
A18: 2002-T1 | B18: 37343 | C18: 23.239999 | D18: 2.41 | E18: 1.712 | F18: 0.0542 | G18: 0.011363636 | H18: 0.0816 | I18: =IFERROR(C18/D18,"") | J18: =IFERROR(D18/C18,"") | K18: =IFERROR(E18/C18,"") | L18: =IFERROR(F18-G18,"") | M18: =IFERROR(J18-F18,"") | N18: =IFERROR(J18-L18,"") | O18: =IFERROR(J18-H18,"") | P18: =IFERROR(K18-F18,"") | U18: 0.051020408 | V18: 0.030612245 | Y18: =IF(X18="","",IF(X18>='Léeme'!$B$6,"barato",IF(X18<'Léeme'!$B$7,"caro","medio"))) | Z18: 0.13364057 | AA18: 0.13067819
A19: 2002-T2 | B19: 37435 | C19: 22.5 | D19: 2.41 | E19: 1.712 | F19: 0.0486 | G19: 0.012408347 | H19: 0.0798 | I19: =IFERROR(C19/D19,"") | J19: =IFERROR(D19/C19,"") | K19: =IFERROR(E19/C19,"") | L19: =IFERROR(F19-G19,"") | M19: =IFERROR(J19-F19,"") | N19: =IFERROR(J19-L19,"") | O19: =IFERROR(J19-H19,"") | P19: =IFERROR(K19-F19,"") | U19: 0.16346154 | V19: 0.24038462 | Y19: =IF(X19="","",IF(X19>='Léeme'!$B$6,"barato",IF(X19<'Léeme'!$B$7,"caro","medio"))) | Z19: 0.38796553 | AA19: 0.11837699
A20: 2002-T3 | B20: 37529 | C20: 24.799999 | D20: 2.41 | E20: 1.72 | F20: 0.0363 | G20: 0.017474634 | H20: 0.074 | I20: =IFERROR(C20/D20,"") | J20: =IFERROR(D20/C20,"") | K20: =IFERROR(E20/C20,"") | L20: =IFERROR(F20-G20,"") | M20: =IFERROR(J20-F20,"") | N20: =IFERROR(J20-L20,"") | O20: =IFERROR(J20-H20,"") | P20: =IFERROR(K20-F20,"") | U20: 0.0090909091 | V20: 0.40909091 | Y20: =IF(X20="","",IF(X20>='Léeme'!$B$6,"barato",IF(X20<'Léeme'!$B$7,"caro","medio"))) | Z20: 0.34603301 | AA20: 0.101843
A21: 2002-T4 | B21: 37621 | C21: 24.75 | D21: 2.41 | E21: 1.72 | F21: 0.0383 | G21: 0.022535211 | H21: 0.073 | I21: =IFERROR(C21/D21,"") | J21: =IFERROR(D21/C21,"") | K21: =IFERROR(E21/C21,"") | L21: =IFERROR(F21-G21,"") | M21: =IFERROR(J21-F21,"") | N21: =IFERROR(J21-L21,"") | O21: =IFERROR(J21-H21,"") | P21: =IFERROR(K21-F21,"") | U21: 0.025862069 | V21: 0.35344828 | Y21: =IF(X21="","",IF(X21>='Léeme'!$B$6,"barato",IF(X21<'Léeme'!$B$7,"caro","medio"))) | Z21: 0.29299027 | AA21: 0.11483424
A22: 2003-T1 | B22: 37711 | C22: 25 | D22: 2.81 | E22: 1.728 | F22: 0.0383 | G22: 0.031460674 | H22: 0.0693 | I22: =IFERROR(C22/D22,"") | J22: =IFERROR(D22/C22,"") | K22: =IFERROR(E22/C22,"") | L22: =IFERROR(F22-G22,"") | M22: =IFERROR(J22-F22,"") | N22: =IFERROR(J22-L22,"") | O22: =IFERROR(J22-H22,"") | P22: =IFERROR(K22-F22,"") | U22: 0.024590164 | V22: 0.35245902 | Y22: =IF(X22="","",IF(X22>='Léeme'!$B$6,"barato",IF(X22<'Léeme'!$B$7,"caro","medio"))) | Z22: 0.29472963 | AA22: 0.089727902
A23: 2003-T2 | B23: 37802 | C23: 29.94 | D23: 2.81 | E23: 1.732 | F23: 0.0354 | G23: 0.018941504 | H23: 0.0638 | I23: =IFERROR(C23/D23,"") | J23: =IFERROR(D23/C23,"") | K23: =IFERROR(E23/C23,"") | L23: =IFERROR(F23-G23,"") | M23: =IFERROR(J23-F23,"") | N23: =IFERROR(J23-L23,"") | O23: =IFERROR(J23-H23,"") | P23: =IFERROR(K23-F23,"") | Q23: 0.013157895 | R23: 0.53947368 | S23: 0.32894737 | T23: 0.64473684 | U23: 0.0078125 | V23: 0.0859375 | X23: 0.27001096 | Y23: =IF(X23="","",IF(X23>='Léeme'!$B$6,"barato",IF(X23<'Léeme'!$B$7,"caro","medio"))) | Z23: 0.040230955 | AA23: 0.04249346
A24: 2003-T3 | B24: 37894 | C24: 31.75 | D24: 2.81 | E24: 1.732 | F24: 0.0396 | G24: 0.022160665 | H24: 0.0665 | I24: =IFERROR(C24/D24,"") | J24: =IFERROR(D24/C24,"") | K24: =IFERROR(E24/C24,"") | L24: =IFERROR(F24-G24,"") | M24: =IFERROR(J24-F24,"") | N24: =IFERROR(J24-L24,"") | O24: =IFERROR(J24-H24,"") | P24: =IFERROR(K24-F24,"") | Q24: 0.012195122 | R24: 0.1097561 | S24: 0.25609756 | T24: 0.15853659 | U24: 0.0074626866 | V24: 0.037313433 | X24: 0.096893581 | Y24: =IF(X24="","",IF(X24>='Léeme'!$B$6,"barato",IF(X24<'Léeme'!$B$7,"caro","medio"))) | Z24: -0.015525168 | AA24: 0.011676726
A25: 2003-T4 | B25: 37986 | C25: 30.519999 | D25: 2.81 | E25: 1.74 | F25: 0.0427 | G25: 0.019283747 | H25: 0.0662 | I25: =IFERROR(C25/D25,"") | J25: =IFERROR(D25/C25,"") | K25: =IFERROR(E25/C25,"") | L25: =IFERROR(F25-G25,"") | M25: =IFERROR(J25-F25,"") | N25: =IFERROR(J25-L25,"") | O25: =IFERROR(J25-H25,"") | P25: =IFERROR(K25-F25,"") | Q25: 0.125 | R25: 0.17045455 | S25: 0.23863636 | T25: 0.51136364 | U25: 0.078571429 | V25: 0.064285714 | X25: 0.19805195 | Y25: =IF(X25="","",IF(X25>='Léeme'!$B$6,"barato",IF(X25<'Léeme'!$B$7,"caro","medio"))) | Z25: 0.20471631 | AA25: -0.00074324038
A26: 2004-T1 | B26: 38077 | C26: 30.949999 | D26: 2.78 | E26: 1.74 | F26: 0.0386 | G26: 0.016884532 | H26: 0.0619 | I26: =IFERROR(C26/D26,"") | J26: =IFERROR(D26/C26,"") | K26: =IFERROR(E26/C26,"") | L26: =IFERROR(F26-G26,"") | M26: =IFERROR(J26-F26,"") | N26: =IFERROR(J26-L26,"") | O26: =IFERROR(J26-H26,"") | P26: =IFERROR(K26-F26,"") | Q26: 0.074468085 | R26: 0.26595745 | S26: 0.20212766 | T26: 0.58510638 | U26: 0.061643836 | V26: 0.11643836 | X26: 0.21762363 | Y26: =IF(X26="","",IF(X26>='Léeme'!$B$6,"barato",IF(X26<'Léeme'!$B$7,"caro","medio"))) | Z26: 0.026827357 | AA26: -0.013077787
A27: 2004-T2 | B27: 38168 | C27: 29.78 | D27: 2.78 | E27: 1.752 | F27: 0.0462 | G27: 0.028977583 | H27: 0.0676 | I27: =IFERROR(C27/D27,"") | J27: =IFERROR(D27/C27,"") | K27: =IFERROR(E27/C27,"") | L27: =IFERROR(F27-G27,"") | M27: =IFERROR(J27-F27,"") | N27: =IFERROR(J27-L27,"") | O27: =IFERROR(J27-H27,"") | P27: =IFERROR(K27-F27,"") | Q27: 0.15 | R27: 0.11 | S27: 0.43 | T27: 0.43 | U27: 0.125 | V27: 0.059210526 | X27: 0.21736842 | Y27: =IF(X27="","",IF(X27>='Léeme'!$B$6,"barato",IF(X27<'Léeme'!$B$7,"caro","medio"))) | Z27: 0.029293107 | AA27: 0.019247062
A28: 2004-T3 | B28: 38260 | C28: 29.859999 | D28: 2.78 | E28: 1.76 | F28: 0.0414 | G28: 0.025474255 | H28: 0.0622 | I28: =IFERROR(C28/D28,"") | J28: =IFERROR(D28/C28,"") | K28: =IFERROR(E28/C28,"") | L28: =IFERROR(F28-G28,"") | M28: =IFERROR(J28-F28,"") | N28: =IFERROR(J28-L28,"") | O28: =IFERROR(J28-H28,"") | P28: =IFERROR(K28-F28,"") | Q28: 0.17924528 | R28: 0.33018868 | S28: 0.48113208 | T28: 0.72641509 | U28: 0.15822785 | V28: 0.15822785 | X28: 0.33890614 | Y28: =IF(X28="","",IF(X28>='Léeme'!$B$6,"barato",IF(X28<'Léeme'!$B$7,"caro","medio"))) | Z28: -0.05461853 | AA28: 0.044906197
A29: 2004-T4 | B29: 38352 | C29: 35.160002 | D29: 2.78 | E29: 1.768 | F29: 0.0424 | G29: 0.036216216 | H29: 0.0616 | I29: =IFERROR(C29/D29,"") | J29: =IFERROR(D29/C29,"") | K29: =IFERROR(E29/C29,"") | L29: =IFERROR(F29-G29,"") | M29: =IFERROR(J29-F29,"") | N29: =IFERROR(J29-L29,"") | O29: =IFERROR(J29-H29,"") | P29: =IFERROR(K29-F29,"") | Q29: 0.0089285714 | R29: 0.0089285714 | S29: 0.33035714 | T29: 0.0089285714 | U29: 0.006097561 | V29: 0.006097561 | X29: 0.06155633 | Y29: =IF(X29="","",IF(X29>='Léeme'!$B$6,"barato",IF(X29<'Léeme'!$B$7,"caro","medio"))) | Z29: -0.2404054 | AA29: 0.0094324886
A30: 2005-T1 | B30: 38442 | C30: 30.37 | D30: 3.47 | E30: 1.776 | F30: 0.045 | G30: 0.030530262 | H30: 0.0617 | I30: =IFERROR(C30/D30,"") | J30: =IFERROR(D30/C30,"") | K30: =IFERROR(E30/C30,"") | L30: =IFERROR(F30-G30,"") | M30: =IFERROR(J30-F30,"") | N30: =IFERROR(J30-L30,"") | O30: =IFERROR(J30-H30,"") | P30: =IFERROR(K30-F30,"") | Q30: 0.8559322 | R30: 0.95762712 | S30: 0.92372881 | T30: 0.99152542 | U30: 0.19411765 | V30: 0.13529412 | X30: 0.67637089 | Y30: =IF(X30="","",IF(X30>='Léeme'!$B$6,"barato",IF(X30<'Léeme'!$B$7,"caro","medio"))) | Z30: -0.070302596 | AA30: 0.052215898
A31: 2005-T2 | B31: 38533 | C31: 29.28 | D31: 3.47 | E31: 1.784 | F31: 0.0394 | G31: 0.02869288 | H31: 0.0586 | I31: =IFERROR(C31/D31,"") | J31: =IFERROR(D31/C31,"") | K31: =IFERROR(E31/C31,"") | L31: =IFERROR(F31-G31,"") | M31: =IFERROR(J31-F31,"") | N31: =IFERROR(J31-L31,"") | O31: =IFERROR(J31-H31,"") | P31: =IFERROR(K31-F31,"") | Q31: 0.92741935 | R31: 0.97580645 | S31: 0.97580645 | T31: 0.97580645 | U31: 0.26704545 | V31: 0.30113636 | X31: 0.73717009 | Y31: =IF(X31="","",IF(X31>='Léeme'!$B$6,"barato",IF(X31<'Léeme'!$B$7,"caro","medio"))) | Z31: -0.086071536 | AA31: 0.047564349
A32: 2005-T3 | B32: 38625 | C32: 26.920001 | D32: 3.47 | E32: 1.792004 | F32: 0.0434 | G32: 0.036469345 | H32: 0.0612 | I32: =IFERROR(C32/D32,"") | J32: =IFERROR(D32/C32,"") | K32: =IFERROR(E32/C32,"") | L32: =IFERROR(F32-G32,"") | M32: =IFERROR(J32-F32,"") | N32: =IFERROR(J32-L32,"") | O32: =IFERROR(J32-H32,"") | P32: =IFERROR(K32-F32,"") | Q32: 0.99230769 | R32: 0.99230769 | S32: 0.99230769 | T32: 0.99230769 | U32: 0.32417582 | V32: 0.36813187 | X32: 0.77692308 | Y32: =IF(X32="","",IF(X32>='Léeme'!$B$6,"barato",IF(X32<'Léeme'!$B$7,"caro","medio"))) | Z32: 0.079979048 | AA32: 0.075396299
A33: 2005-T4 | B33: 38716 | C33: 25.36 | D33: 3.47 | E33: 1.8 | F33: 0.0439 | G33: 0.033385498 | H33: 0.0619 | I33: =IFERROR(C33/D33,"") | J33: =IFERROR(D33/C33,"") | K33: =IFERROR(E33/C33,"") | L33: =IFERROR(F33-G33,"") | M33: =IFERROR(J33-F33,"") | N33: =IFERROR(J33-L33,"") | O33: =IFERROR(J33-H33,"") | P33: =IFERROR(K33-F33,"") | Q33: 0.97794118 | R33: 0.97794118 | S33: 0.96323529 | T33: 0.97794118 | U33: 0.39893617 | V33: 0.46276596 | X33: 0.79312683 | Y33: =IF(X33="","",IF(X33>='Léeme'!$B$6,"barato",IF(X33<'Léeme'!$B$7,"caro","medio"))) | Z33: 0.25029877 | AA33: 0.10445089
A34: 2006-T1 | B34: 38807 | C34: 26.78 | D34: 2.53 | E34: 1.808 | F34: 0.0486 | G34: 0.036382536 | H34: 0.0656 | I34: =IFERROR(C34/D34,"") | J34: =IFERROR(D34/C34,"") | K34: =IFERROR(E34/C34,"") | L34: =IFERROR(F34-G34,"") | M34: =IFERROR(J34-F34,"") | N34: =IFERROR(J34-L34,"") | O34: =IFERROR(J34-H34,"") | P34: =IFERROR(K34-F34,"") | Q34: 0.26056338 | R34: 0.11971831 | S34: 0.52816901 | T34: 0.51408451 | U34: 0.31443299 | V34: 0.23195876 | X34: 0.32815449 | Y34: =IF(X34="","",IF(X34>='Léeme'!$B$6,"barato",IF(X34<'Léeme'!$B$7,"caro","medio"))) | Z34: 0.31111219 | AA34: 0.12189466
A35: 2006-T2 | B35: 38898 | C35: 25.319999 | D35: 2.53 | E35: 1.816 | F35: 0.0515 | G35: 0.039772727 | H35: 0.0691 | I35: =IFERROR(C35/D35,"") | J35: =IFERROR(D35/C35,"") | K35: =IFERROR(E35/C35,"") | L35: =IFERROR(F35-G35,"") | M35: =IFERROR(J35-F35,"") | N35: =IFERROR(J35-L35,"") | O35: =IFERROR(J35-H35,"") | P35: =IFERROR(K35-F35,"") | Q35: 0.43918919 | R35: 0.20945946 | S35: 0.64189189 | T35: 0.62837838 | U35: 0.465 | V35: 0.285 | W35: 0.67105263 | X35: 0.47713879 | Y35: =IF(X35="","",IF(X35>='Léeme'!$B$6,"barato",IF(X35<'Léeme'!$B$7,"caro","medio"))) | Z35: 0.30387751 | AA35: 0.16272991
A36: 2006-T3 | B36: 38989 | C36: 27.51 | D36: 2.53 | E36: 1.824 | F36: 0.0464 | G36: 0.039265681 | H36: 0.0636 | I36: =IFERROR(C36/D36,"") | J36: =IFERROR(D36/C36,"") | K36: =IFERROR(E36/C36,"") | L36: =IFERROR(F36-G36,"") | M36: =IFERROR(J36-F36,"") | N36: =IFERROR(J36-L36,"") | O36: =IFERROR(J36-H36,"") | P36: =IFERROR(K36-F36,"") | Q36: 0.17532468 | R36: 0.12337662 | S36: 0.53896104 | T36: 0.51298701 | U36: 0.28640777 | V36: 0.28640777 | W36: 0.54878049 | X36: 0.35317791 | Y36: =IF(X36="","",IF(X36>='Léeme'!$B$6,"barato",IF(X36<'Léeme'!$B$7,"caro","medio"))) | Z36: 0.20037193 | AA36: 0.12389712
A37: 2006-T4 | B37: 39080 | C37: 30.069999 | D37: 2.53 | E37: 1.832 | F37: 0.0471 | G37: 0.019687027 | H37: 0.0635 | I37: =IFERROR(C37/D37,"") | J37: =IFERROR(D37/C37,"") | K37: =IFERROR(E37/C37,"") | L37: =IFERROR(F37-G37,"") | M37: =IFERROR(J37-F37,"") | N37: =IFERROR(J37-L37,"") | O37: =IFERROR(J37-H37,"") | P37: =IFERROR(K37-F37,"") | Q37: 0.05625 | R37: 0.01875 | S37: 0.01875 | T37: 0.06875 | U37: 0.23113208 | V37: 0.11792453 | W37: 0.19318182 | X37: 0.10067692 | Y37: =IF(X37="","",IF(X37>='Léeme'!$B$6,"barato",IF(X37<'Léeme'!$B$7,"caro","medio"))) | Z37: 0.15845121 | AA37: 0.12767389
A38: 2007-T1 | B38: 39171 | C38: 33.37 | D38: 3.29 | E38: 1.848 | F38: 0.0465 | G38: 0.024202608 | H38: 0.0638 | I38: =IFERROR(C38/D38,"") | J38: =IFERROR(D38/C38,"") | K38: =IFERROR(E38/C38,"") | L38: =IFERROR(F38-G38,"") | M38: =IFERROR(J38-F38,"") | N38: =IFERROR(J38-L38,"") | O38: =IFERROR(J38-H38,"") | P38: =IFERROR(K38-F38,"") | Q38: 0.42771084 | R38: 0.42771084 | S38: 0.37951807 | T38: 0.71686747 | U38: 0.068807339 | V38: 0.02293578 | W38: 0.69148936 | X38: 0.39071996 | Y38: =IF(X38="","",IF(X38>='Léeme'!$B$6,"barato",IF(X38<'Léeme'!$B$7,"caro","medio"))) | Z38: -0.052362045 | AA38: 0.13018857
A39: 2007-T2 | B39: 39262 | C39: 31.450001 | D39: 3.29 | E39: 1.868 | F39: 0.0503 | G39: 0.027098857 | H39: 0.0672 | I39: =IFERROR(C39/D39,"") | J39: =IFERROR(D39/C39,"") | K39: =IFERROR(E39/C39,"") | L39: =IFERROR(F39-G39,"") | M39: =IFERROR(J39-F39,"") | N39: =IFERROR(J39-L39,"") | O39: =IFERROR(J39-H39,"") | P39: =IFERROR(K39-F39,"") | Q39: 0.64534884 | R39: 0.50581395 | S39: 0.51744186 | T39: 0.78488372 | U39: 0.21875 | V39: 0.049107143 | W39: 0.75 | X39: 0.4959065 | Y39: =IF(X39="","",IF(X39>='Léeme'!$B$6,"barato",IF(X39<'Léeme'!$B$7,"caro","medio"))) | Z39: -0.034615989 | AA39: 0.14075171
A40: 2007-T3 | B40: 39353 | C40: 31.5 | D40: 3.29 | E40: 1.888 | F40: 0.0459 | G40: 0.018974485 | H40: 0.0659 | I40: =IFERROR(C40/D40,"") | J40: =IFERROR(D40/C40,"") | K40: =IFERROR(E40/C40,"") | L40: =IFERROR(F40-G40,"") | M40: =IFERROR(J40-F40,"") | N40: =IFERROR(J40-L40,"") | O40: =IFERROR(J40-H40,"") | P40: =IFERROR(K40-F40,"") | Q40: 0.62359551 | R40: 0.66853933 | S40: 0.44382022 | T40: 0.78089888 | U40: 0.26521739 | V40: 0.17826087 | W40: 0.70754717 | X40: 0.52398277 | Y40: =IF(X40="","",IF(X40>='Léeme'!$B$6,"barato",IF(X40<'Léeme'!$B$7,"caro","medio"))) | Z40: -0.10650948 | AA40: 0.15441721
A41: 2007-T4 | B41: 39447 | C41: 33.199999 | D41: 3.29 | E41: 1.908 | F41: 0.0404 | G41: 0.043732673 | H41: 0.0662 | I41: =IFERROR(C41/D41,"") | J41: =IFERROR(D41/C41,"") | K41: =IFERROR(E41/C41,"") | L41: =IFERROR(F41-G41,"") | M41: =IFERROR(J41-F41,"") | N41: =IFERROR(J41-L41,"") | O41: =IFERROR(J41-H41,"") | P41: =IFERROR(K41-F41,"") | Q41: 0.46195652 | R41: 0.67934783 | S41: 0.8423913 | T41: 0.67934783 | U41: 0.17372881 | V41: 0.28389831 | W41: 0.6875 | X41: 0.54402437 | Y41: =IF(X41="","",IF(X41>='Léeme'!$B$6,"barato",IF(X41<'Léeme'!$B$7,"caro","medio"))) | Z41: -0.25195238 | AA41: 0.15488597
A42: 2008-T1 | B42: 39538 | C42: 29.97 | D42: 3.34 | E42: 1.928 | F42: 0.0345 | G42: 0.041429593 | H42: 0.0694 | I42: =IFERROR(C42/D42,"") | J42: =IFERROR(D42/C42,"") | K42: =IFERROR(E42/C42,"") | L42: =IFERROR(F42-G42,"") | M42: =IFERROR(J42-F42,"") | N42: =IFERROR(J42-L42,"") | O42: =IFERROR(J42-H42,"") | P42: =IFERROR(K42-F42,"") | Q42: 0.74210526 | R42: 0.9 | S42: 0.93157895 | T42: 0.83684211 | U42: 0.35950413 | V42: 0.65702479 | W42: 0.8220339 | X42: 0.74986988 | Y42: =IF(X42="","",IF(X42>='Léeme'!$B$6,"barato",IF(X42<'Léeme'!$B$7,"caro","medio"))) | Z42: -0.21113379 | AA42: 0.24011409
A43: 2008-T2 | B43: 39629 | C43: 28.710001 | D43: 3.34 | E43: 1.948 | F43: 0.0399 | G43: 0.040884138 | H43: 0.0703 | I43: =IFERROR(C43/D43,"") | J43: =IFERROR(D43/C43,"") | K43: =IFERROR(E43/C43,"") | L43: =IFERROR(F43-G43,"") | M43: =IFERROR(J43-F43,"") | N43: =IFERROR(J43-L43,"") | O43: =IFERROR(J43-H43,"") | P43: =IFERROR(K43-F43,"") | Q43: 0.82142857 | R43: 0.89285714 | S43: 0.92346939 | T43: 0.87244898 | U43: 0.43951613 | V43: 0.60887097 | W43: 0.87903226 | X43: 0.77680335 | Y43: =IF(X43="","",IF(X43>='Léeme'!$B$6,"barato",IF(X43<'Léeme'!$B$7,"caro","medio"))) | Z43: -0.070690412 | AA43: 0.24535094
A44: 2008-T3 | B44: 39721 | C44: 26.1 | D44: 3.34 | E44: 1.968004 | F44: 0.0385 | G44: 0.053080172 | H44: 0.0762 | I44: =IFERROR(C44/D44,"") | J44: =IFERROR(D44/C44,"") | K44: =IFERROR(E44/C44,"") | L44: =IFERROR(F44-G44,"") | M44: =IFERROR(J44-F44,"") | N44: =IFERROR(J44-L44,"") | O44: =IFERROR(J44-H44,"") | P44: =IFERROR(K44-F44,"") | Q44: 0.93564356 | R44: 0.96534653 | S44: 0.9950495 | T44: 0.87623762 | U44: 0.6496063 | V44: 0.81496063 | W44: 0.93076923 | X44: 0.88108763 | Y44: =IF(X44="","",IF(X44>='Léeme'!$B$6,"barato",IF(X44<'Léeme'!$B$7,"caro","medio"))) | Z44: 0.15713051 | AA44: 0.26255436
A45: 2008-T4 | B45: 39813 | C45: 23.429999 | D45: 3.34 | E45: 1.976 | F45: 0.0225 | G45: 0.010999175 | H45: 0.0797 | I45: =IFERROR(C45/D45,"") | J45: =IFERROR(D45/C45,"") | K45: =IFERROR(E45/C45,"") | L45: =IFERROR(F45-G45,"") | M45: =IFERROR(J45-F45,"") | N45: =IFERROR(J45-L45,"") | O45: =IFERROR(J45-H45,"") | P45: =IFERROR(K45-F45,"") | Q45: 0.97596154 | R45: 0.98557692 | S45: 0.94711538 | T45: 0.91826923 | U45: 0.75 | V45: 0.98846154 | W45: 0.96323529 | X45: 0.93265999 | Y45: =IF(X45="","",IF(X45>='Léeme'!$B$6,"barato",IF(X45<'Léeme'!$B$7,"caro","medio"))) | Z45: 0.2673183 | AA45: 0.27513493
A46: 2009-T1 | B46: 39903 | C46: 22.19 | D46: 3.09 | E46: 1.984 | F46: 0.0271 | G46: 8.4631407e-05 | H46: 0.0848 | I46: =IFERROR(C46/D46,"") | J46: =IFERROR(D46/C46,"") | K46: =IFERROR(E46/C46,"") | L46: =IFERROR(F46-G46,"") | M46: =IFERROR(J46-F46,"") | N46: =IFERROR(J46-L46,"") | O46: =IFERROR(J46-H46,"") | P46: =IFERROR(K46-F46,"") | Q46: 0.94859813 | R46: 0.95794393 | S46: 0.81775701 | T46: 0.85514019 | U46: 0.80075188 | V46: 0.98120301 | W46: 0.8943662 | X46: 0.89368005 | Y46: =IF(X46="","",IF(X46>='Léeme'!$B$6,"barato",IF(X46<'Léeme'!$B$7,"caro","medio"))) | Z46: 0.41451354 | AA46: 0.28220962
... A95: 2021-T2 | B95: 44377 | C95: 74.620002 | D95: 4.71 | E95: 4.2 | F95: 0.0145 | G95: 0.049182571 | H95: 0.0336 | I95: =IFERROR(C95/D95,"") | J95: =IFERROR(D95/C95,"") | K95: =IFERROR(E95/C95,"") | L95: =IFERROR(F95-G95,"") | M95: =IFERROR(J95-F95,"") | N95: =IFERROR(J95-L95,"") | O95: =IFERROR(J95-H95,"") | P95: =IFERROR(K95-F95,"") | Q95: 0.092519685 | R95: 0.25393701 | S95: 0.8011811 | T95: 0.43897638 | U95: 0.25535714 | V95: 0.84107143 | W95: 0.23165138 | X95: 0.41638487 | Y95: =IF(X95="","",IF(X95>='Léeme'!$B$6,"barato",IF(X95<'Léeme'!$B$7,"caro","medio"))) | Z95: 0.15785865 | AA95: 0.042377624
A96: 2021-T3 | B96: 44469 | C96: 73.039996 | D96: 4.84 | E96: 4.208 | F96: 0.0152 | G96: 0.051520153 | H96: 0.0336 | I96: =IFERROR(C96/D96,"") | J96: =IFERROR(D96/C96,"") | K96: =IFERROR(E96/C96,"") | L96: =IFERROR(F96-G96,"") | M96: =IFERROR(J96-F96,"") | N96: =IFERROR(J96-L96,"") | O96: =IFERROR(J96-H96,"") | P96: =IFERROR(K96-F96,"") | Q96: 0.13424125 | R96: 0.33268482 | S96: 0.85019455 | T96: 0.57392996 | U96: 0.31272085 | V96: 0.8639576 | W96: 0.33257919 | X96: 0.48575832 | Y96: =IF(X96="","",IF(X96>='Léeme'!$B$6,"barato",IF(X96<'Léeme'!$B$7,"caro","medio"))) | Z96: -0.0025906987
A97: 2021-T4 | B97: 44561 | C97: 82.049999 | D97: 4.93 | E97: 4.22 | F97: 0.0152 | G97: 0.069019704 | H97: 0.0337 | I97: =IFERROR(C97/D97,"") | J97: =IFERROR(D97/C97,"") | K97: =IFERROR(E97/C97,"") | L97: =IFERROR(F97-G97,"") | M97: =IFERROR(J97-F97,"") | N97: =IFERROR(J97-L97,"") | O97: =IFERROR(J97-H97,"") | P97: =IFERROR(K97-F97,"") | Q97: 0.055769231 | R97: 0.16346154 | S97: 0.93269231 | T97: 0.30961538 | U97: 0.092657343 | V97: 0.63111888 | W97: 0.17633929 | X97: 0.33737914 | Y97: =IF(X97="","",IF(X97>='Léeme'!$B$6,"barato",IF(X97<'Léeme'!$B$7,"caro","medio"))) | Z97: -0.005348886
A98: 2022-T1 | B98: 44651 | C98: 80.839999 | D98: 5.03 | E98: 4.228 | F98: 0.0232 | G98: 0.079372788 | H98: 0.0428 | I98: =IFERROR(C98/D98,"") | J98: =IFERROR(D98/C98,"") | K98: =IFERROR(E98/C98,"") | L98: =IFERROR(F98-G98,"") | M98: =IFERROR(J98-F98,"") | N98: =IFERROR(J98-L98,"") | O98: =IFERROR(J98-H98,"") | P98: =IFERROR(K98-F98,"") | Q98: 0.081749049 | R98: 0.081749049 | S98: 0.94106464 | T98: 0.10456274 | U98: 0.11245675 | V98: 0.38581315 | W98: 0.28414097 | X98: 0.28450519 | Y98: =IF(X98="","",IF(X98>='Léeme'!$B$6,"barato",IF(X98<'Léeme'!$B$7,"caro","medio"))) | Z98: 0.0012779324
A99: 2022-T2 | B99: 44742 | C99: 82.860002 | D99: 5.16 | E99: 4.236 | F99: 0.0298 | G99: 0.085381712 | H99: 0.0534 | I99: =IFERROR(C99/D99,"") | J99: =IFERROR(D99/C99,"") | K99: =IFERROR(E99/C99,"") | L99: =IFERROR(F99-G99,"") | M99: =IFERROR(J99-F99,"") | N99: =IFERROR(J99-L99,"") | O99: =IFERROR(J99-H99,"") | P99: =IFERROR(K99-F99,"") | Q99: 0.088345865 | R99: 0.031954887 | S99: 0.93045113 | T99: 0.039473684 | U99: 0.094178082 | V99: 0.16609589 | W99: 0.3673913 | X99: 0.24541298 | Y99: =IF(X99="","",IF(X99>='Léeme'!$B$6,"barato",IF(X99<'Léeme'!$B$7,"caro","medio"))) | Z99: -0.14570638
A100: 2022-T3 | B100: 44834 | C100: 69.800001 | D100: 5.2 | E100: 4.244 | F100: 0.0383 | G100: 0.082225792 | H100: 0.0603 | I100: =IFERROR(C100/D100,"") | J100: =IFERROR(D100/C100,"") | K100: =IFERROR(E100/C100,"") | L100: =IFERROR(F100-G100,"") | M100: =IFERROR(J100-F100,"") | N100: =IFERROR(J100-L100,"") | O100: =IFERROR(J100-H100,"") | P100: =IFERROR(K100-F100,"") | Q100: 0.25836431 | R100: 0.057620818 | S100: 0.93494424 | T100: 0.065055762 | U100: 0.47627119 | V100: 0.20169492 | W100: 0.83476395 | X100: 0.40410217 | Y100: =IF(X100="","",IF(X100>='Léeme'!$B$6,"barato",IF(X100<'Léeme'!$B$7,"caro","medio"))) | Z100: -0.18554224
A101: 2022-T4 | B101: 44925 | C101: 78.149997 | D101: 5.32 | E101: 4.26 | F101: 0.0388 | G101: 0.071228565 | H101: 0.0584 | I101: =IFERROR(C101/D101,"") | J101: =IFERROR(D101/C101,"") | K101: =IFERROR(E101/C101,"") | L101: =IFERROR(F101-G101,"") | M101: =IFERROR(J101-F101,"") | N101: =IFERROR(J101-L101,"") | O101: =IFERROR(J101-H101,"") | P101: =IFERROR(K101-F101,"") | Q101: 0.19301471 | R101: 0.0091911765 | S101: 0.77022059 | T101: 0.060661765 | U101: 0.19966443 | V101: 0.098993289 | W101: 0.63347458 | X101: 0.28074579 | Y101: =IF(X101="","",IF(X101>='Léeme'!$B$6,"barato",IF(X101<'Léeme'!$B$7,"caro","medio"))) | Z101: -0.11026171
A102: 2023-T1 | B102: 45016 | C102: 77.449999 | D102: 5.31 | E102: 4.268 | F102: 0.0348 | G102: 0.059578207 | H102: 0.0566 | I102: =IFERROR(C102/D102,"") | J102: =IFERROR(D102/C102,"") | K102: =IFERROR(E102/C102,"") | L102: =IFERROR(F102-G102,"") | M102: =IFERROR(J102-F102,"") | N102: =IFERROR(J102-L102,"") | O102: =IFERROR(J102-H102,"") | P102: =IFERROR(K102-F102,"") | Q102: 0.20909091 | R102: 0.067272727 | S102: 0.72545455 | T102: 0.074545455 | U102: 0.24418605 | V102: 0.18106312 | W102: 0.67991632 | X102: 0.31164702 | Y102: =IF(X102="","",IF(X102>='Léeme'!$B$6,"barato",IF(X102<'Léeme'!$B$7,"caro","medio"))) | Z102: -0.21716612
A103: 2023-T2 | B103: 45107 | C103: 67.559997 | D103: 5.27 | E103: 4.276 | F103: 0.0381 | G103: 0.041318512 | H103: 0.0577 | I103: =IFERROR(C103/D103,"") | J103: =IFERROR(D103/C103,"") | K103: =IFERROR(E103/C103,"") | L103: =IFERROR(F103-G103,"") | M103: =IFERROR(J103-F103,"") | N103: =IFERROR(J103-L103,"") | O103: =IFERROR(J103-H103,"") | P103: =IFERROR(K103-F103,"") | Q103: 0.33992806 | R103: 0.13129496 | S103: 0.52697842 | T103: 0.17086331 | U103: 0.56743421 | V103: 0.28125 | W103: 0.8946281 | X103: 0.41605387 | Y103: =IF(X103="","",IF(X103>='Léeme'!$B$6,"barato",IF(X103<'Léeme'!$B$7,"caro","medio"))) | Z103: -0.12468505
A104: 2023-T3 | B104: 45198 | C104: 54.079999 | D104: 5.32 | E104: 4.284 | F104: 0.0459 | G104: 0.037225048 | H104: 0.0639 | I104: =IFERROR(C104/D104,"") | J104: =IFERROR(D104/C104,"") | K104: =IFERROR(E104/C104,"") | L104: =IFERROR(F104-G104,"") | M104: =IFERROR(J104-F104,"") | N104: =IFERROR(J104-L104,"") | O104: =IFERROR(J104-H104,"") | P104: =IFERROR(K104-F104,"") | Q104: 0.66014235 | R104: 0.43950178 | S104: 0.68149466 | T104: 0.64590747 | U104: 0.84527687 | V104: 0.55863192 | W104: 0.98163265 | X104: 0.68751253 | Y104: =IF(X104="","",IF(X104>='Léeme'!$B$6,"barato",IF(X104<'Léeme'!$B$7,"caro","medio"))) | Z104: 0.22702147
A105: 2023-T4 | B105: 45289 | C105: 64.809998 | D105: 5.28 | E105: 3.44 | F105: 0.0388 | G105: 0.031333463 | H105: 0.0546 | I105: =IFERROR(C105/D105,"") | J105: =IFERROR(D105/C105,"") | K105: =IFERROR(E105/C105,"") | L105: =IFERROR(F105-G105,"") | M105: =IFERROR(J105-F105,"") | N105: =IFERROR(J105-L105,"") | O105: =IFERROR(J105-H105,"") | P105: =IFERROR(K105-F105,"") | Q105: 0.40316901 | R105: 0.18133803 | S105: 0.37852113 | T105: 0.37852113 | U105: 0.15 | V105: 0.075806452 | W105: 0.91733871 | X105: 0.35495635 | Y105: =IF(X105="","",IF(X105>='Léeme'!$B$6,"barato",IF(X105<'Léeme'!$B$7,"caro","medio"))) | Z105: -0.12807397
A106: 2024-T1 | B106: 45379 | C106: 56.439999 | D106: 5.18 | E106: 3.46 | F106: 0.042 | G106: 0.031570741 | H106: 0.0574 | I106: =IFERROR(C106/D106,"") | J106: =IFERROR(D106/C106,"") | K106: =IFERROR(E106/C106,"") | L106: =IFERROR(F106-G106,"") | M106: =IFERROR(J106-F106,"") | N106: =IFERROR(J106-L106,"") | O106: =IFERROR(J106-H106,"") | P106: =IFERROR(K106-F106,"") | Q106: 0.56271777 | R106: 0.36759582 | S106: 0.54181185 | T106: 0.64634146 | U106: 0.50638978 | V106: 0.16773163 | W106: 0.95418327 | X106: 0.53525308 | Y106: =IF(X106="","",IF(X106>='Léeme'!$B$6,"barato",IF(X106<'Léeme'!$B$7,"caro","medio"))) | Z106: 0.15229989
A107: 2024-T2 | B107: 45471 | C107: 55.049999 | D107: 5.01 | E107: 3.48 | F107: 0.0436 | G107: 0.032442786 | H107: 0.0584 | I107: =IFERROR(C107/D107,"") | J107: =IFERROR(D107/C107,"") | K107: =IFERROR(E107/C107,"") | L107: =IFERROR(F107-G107,"") | M107: =IFERROR(J107-F107,"") | N107: =IFERROR(J107-L107,"") | O107: =IFERROR(J107-H107,"") | P107: =IFERROR(K107-F107,"") | Q107: 0.55 | R107: 0.28793103 | S107: 0.51896552 | T107: 0.60862069 | U107: 0.5585443 | V107: 0.18512658 | W107: 0.93897638 | X107: 0.52116636 | Y107: =IF(X107="","",IF(X107>='Léeme'!$B$6,"barato",IF(X107<'Léeme'!$B$7,"caro","medio"))) | Z107: 0.183006
... A111: 2025-T2 | B111: 45838 | C111: 62.380001 | D111: 4.73 | E111: 3.6 | F111: 0.0424 | G111: 0.023772651 | H111: 0.0608 | I111: =IFERROR(C111/D111,"") | J111: =IFERROR(D111/C111,"") | K111: =IFERROR(E111/C111,"") | L111: =IFERROR(F111-G111,"") | M111: =IFERROR(J111-F111,"") | N111: =IFERROR(J111-L111,"") | O111: =IFERROR(J111-H111,"") | P111: =IFERROR(K111-F111,"") | Q111: 0.2897351 | R111: 0.071192053 | S111: 0.091059603 | T111: 0.10099338 | U111: 0.34908537 | V111: 0.10213415 | W111: 0.69360902 | X111: 0.2425441 | Y111: =IF(X111="","",IF(X111>='Léeme'!$B$6,"barato",IF(X111<'Léeme'!$B$7,"caro","medio"))) | Z111: 0.19708636
A112: 2025-T3 | B112: 45930 | C112: 67.57 | D112: 4.84 | E112: 3.64 | F112: 0.0416 | G112: 0.029385917 | H112: 0.0579 | I112: =IFERROR(C112/D112,"") | J112: =IFERROR(D112/C112,"") | K112: =IFERROR(E112/C112,"") | L112: =IFERROR(F112-G112,"") | M112: =IFERROR(J112-F112,"") | N112: =IFERROR(J112-L112,"") | O112: =IFERROR(J112-H112,"") | P112: =IFERROR(K112-F112,"") | Q112: 0.22786885 | R112: 0.024590164 | S112: 0.13278689 | T112: 0.083606557 | U112: 0.17069486 | V112: 0.049848943 | W112: 0.51486989 | X112: 0.17203802 | Y112: =IF(X112="","",IF(X112>='Léeme'!$B$6,"barato",IF(X112<'Léeme'!$B$7,"caro","medio")))
A113: 2025-T4 | B113: 46022 | C113: 64.360001 | D113: 4.91 | E113: 3.68 | F113: 0.0418 | G113: 0.026964439 | H113: 0.0589 | I113: =IFERROR(C113/D113,"") | J113: =IFERROR(D113/C113,"") | K113: =IFERROR(E113/C113,"") | L113: =IFERROR(F113-G113,"") | M113: =IFERROR(J113-F113,"") | N113: =IFERROR(J113-L113,"") | O113: =IFERROR(J113-H113,"") | P113: =IFERROR(K113-F113,"") | Q113: 0.31980519 | R113: 0.099025974 | S113: 0.16396104 | T113: 0.14123377 | U113: 0.34281437 | V113: 0.1242515 | W113: 0.68198529 | X113: 0.26758245 | Y113: =IF(X113="","",IF(X113>='Léeme'!$B$6,"barato",IF(X113<'Léeme'!$B$7,"caro","medio")))
A114: 2026-T1 | B114: 46112 | C114: 67.959999 | D114: 4.97 | E114: 3.72 | F114: 0.043 | G114: 0.024340041 | H114: 0.0614 | I114: =IFERROR(C114/D114,"") | J114: =IFERROR(D114/C114,"") | K114: =IFERROR(E114/C114,"") | L114: =IFERROR(F114-G114,"") | M114: =IFERROR(J114-F114,"") | N114: =IFERROR(J114-L114,"") | O114: =IFERROR(J114-H114,"") | P114: =IFERROR(K114-F114,"") | Q114: 0.25562701 | R114: 0.033762058 | S114: 0.069131833 | T114: 0.072347267 | U114: 0.21810089 | V114: 0.051928783 | W114: 0.57272727 | X114: 0.18194644 | Y114: =IF(X114="","",IF(X114>='Léeme'!$B$6,"barato",IF(X114<'Léeme'!$B$7,"caro","medio")))
A115: 2026-T2 | B115: 46203 | C115: 71.5 | D115: 5.1 | E115: 3.76 | F115: 0.0444 | G115: 0.041666147 | H115: 0.0593 | I115: =IFERROR(C115/D115,"") | J115: =IFERROR(D115/C115,"") | K115: =IFERROR(E115/C115,"") | L115: =IFERROR(F115-G115,"") | M115: =IFERROR(J115-F115,"") | N115: =IFERROR(J115-L115,"") | O115: =IFERROR(J115-H115,"") | P115: =IFERROR(K115-F115,"") | Q115: 0.23407643 | R115: 0.01433121 | S115: 0.30095541 | T115: 0.084394904 | U115: 0.12794118 | V115: 0.016176471 | W115: 0.48741007 | X115: 0.1807551 | Y115: =IF(X115="","",IF(X115>='Léeme'!$B$6,"barato",IF(X115<'Léeme'!$B$7,"caro","medio")))
A116: 2026-T3 | B116: 46293 | C116: 65.82 | D116: 5.16 | E116: 3.76 | F116: 0.0524 | G116: 0.033530163 | H116: 0.0663 | I116: =IFERROR(C116/D116,"") | J116: =IFERROR(D116/C116,"") | K116: =IFERROR(E116/C116,"") | L116: =IFERROR(F116-G116,"") | M116: =IFERROR(J116-F116,"") | N116: =IFERROR(J116-L116,"") | O116: =IFERROR(J116-H116,"") | P116: =IFERROR(K116-F116,"") | Q116: 0.36750789 | R116: 0.011041009 | S116: 0.14984227 | T116: 0.093059937 | U116: 0.35714286 | V116: 0.0043731778 | W116: 0.73843416 | X116: 0.24591447 | Y116: =IF(X116="","",IF(X116>='Léeme'!$B$6,"barato",IF(X116<'Léeme'!$B$7,"caro","medio")))

Sheet NNN valor
A1: Trimestre | B1: Fecha | C1: Precio | D1: Dividendo anualizado | E1: Flujo por acción, 12 meses | F1: Treasury 10 años | G1: Crecimiento del dividendo, 5 años | H1: Crecimiento del flujo, 5 años (sin acotar) | I1: NOI anualizado (USD) | J1: Deuda neta (USD) | K1: Preferentes (USD) | L1: Acciones | M1: Cap rate de compras | N1: Tasa de descuento r | O1: g del DDM | P1: Valor DDM | Q1: g de los 5 años del DCF | R1: g perpetuo del DCF | S1: Valor DCF | T1: g implícito en el precio | U1: Entregado − implícito | V1: NAV por acción | W1: DDM ÷ precio − 1 | X1: DCF ÷ precio − 1 | Y1: NAV ÷ precio − 1 | Z1: Señal DDM | AA1: Señal DCF | AB1: Señal crecimiento | AC1: Señal NAV | AD1: Percentil: DDM (Gordon sobre el dividendo) | AE1: Percentil: DCF del flujo en dos etapas | AF1: Percentil: Crecimiento entregado contra implícito | AG1: Percentil: NAV aproximado
A2: 1992-T1 | B2: 33694 | C2: 9.875 | D2: 1.08 | F2: 0.0754 | N2: =IF(F2="","",F2+'Léeme'!$B$10) | O2: =IF(OR(G2="",N2=""),"",MIN(MAX(G2,'Léeme'!$B$11),'Léeme'!$B$12,N2-'Léeme'!$B$16)) | P2: =IF(OR(D2="",O2=""),"",IFERROR(IF(D2<=0,"",D2*(1+O2)/(N2-O2)),"")) | Q2: =IF(H2="","",MIN(MAX(H2,'Léeme'!$B$13),'Léeme'!$B$14)) | R2: =IF(N2="","",MIN('Léeme'!$B$15,N2-'Léeme'!$B$16)) | S2: =IF(OR(E2="",Q2=""),"",IFERROR(IF(E2<=0,"",E2*(((1+Q2)/(1+N2))+((1+Q2)/(1+N2))^2+((1+Q2)/(1+N2))^3+((1+Q2)/(1+N2))^4+((1+Q2)/(1+N2))^5)+E2*(1+Q2)^5*(1+R2)/((N2-R2)*(1+N2)^5)),"")) | T2: =IF(OR(E2="",N2=""),"",IFERROR((C2*N2-E2)/(C2+E2),"")) | U2: =IF(OR(H2="",T2=""),"",IFERROR(MIN(MAX(H2,'Léeme'!$B$17),'Léeme'!$B$18)-T2,"")) | V2: =IF(OR(I2="",M2="",L2=""),"",IFERROR((I2/M2-J2-K2)/L2,"")) | W2: =IFERROR(P2/C2-1,"") | X2: =IFERROR(S2/C2-1,"") | Y2: =IFERROR(V2/C2-1,"") | Z2: =IF(OR(W2="",ISTEXT(W2)),"sin dato",IF(W2>='Léeme'!$B$19,"barato",IF(W2<=-'Léeme'!$B$19,"caro","medio"))) | AA2: =IF(OR(X2="",ISTEXT(X2)),"sin dato",IF(X2>='Léeme'!$B$19,"barato",IF(X2<=-'Léeme'!$B$19,"caro","medio"))) | AB2: =IF(OR(U2="",ISTEXT(U2)),"sin dato",IF(U2>='Léeme'!$B$20,"barato",IF(U2<=-'Léeme'!$B$20,"caro","medio"))) | AC2: =IF(OR(Y2="",ISTEXT(Y2)),"sin dato",IF(Y2>='Léeme'!$B$19,"barato",IF(Y2<=-'Léeme'!$B$19,"caro","medio")))
A3: 1992-T2 | B3: 33785 | C3: 10 | D3: 1.08 | F3: 0.0714 | N3: =IF(F3="","",F3+'Léeme'!$B$10) | O3: =IF(OR(G3="",N3=""),"",MIN(MAX(G3,'Léeme'!$B$11),'Léeme'!$B$12,N3-'Léeme'!$B$16)) | P3: =IF(OR(D3="",O3=""),"",IFERROR(IF(D3<=0,"",D3*(1+O3)/(N3-O3)),"")) | Q3: =IF(H3="","",MIN(MAX(H3,'Léeme'!$B$13),'Léeme'!$B$14)) | R3: =IF(N3="","",MIN('Léeme'!$B$15,N3-'Léeme'!$B$16)) | S3: =IF(OR(E3="",Q3=""),"",IFERROR(IF(E3<=0,"",E3*(((1+Q3)/(1+N3))+((1+Q3)/(1+N3))^2+((1+Q3)/(1+N3))^3+((1+Q3)/(1+N3))^4+((1+Q3)/(1+N3))^5)+E3*(1+Q3)^5*(1+R3)/((N3-R3)*(1+N3)^5)),"")) | T3: =IF(OR(E3="",N3=""),"",IFERROR((C3*N3-E3)/(C3+E3),"")) | U3: =IF(OR(H3="",T3=""),"",IFERROR(MIN(MAX(H3,'Léeme'!$B$17),'Léeme'!$B$18)-T3,"")) | V3: =IF(OR(I3="",M3="",L3=""),"",IFERROR((I3/M3-J3-K3)/L3,"")) | W3: =IFERROR(P3/C3-1,"") | X3: =IFERROR(S3/C3-1,"") | Y3: =IFERROR(V3/C3-1,"") | Z3: =IF(OR(W3="",ISTEXT(W3)),"sin dato",IF(W3>='Léeme'!$B$19,"barato",IF(W3<=-'Léeme'!$B$19,"caro","medio"))) | AA3: =IF(OR(X3="",ISTEXT(X3)),"sin dato",IF(X3>='Léeme'!$B$19,"barato",IF(X3<=-'Léeme'!$B$19,"caro","medio"))) | AB3: =IF(OR(U3="",ISTEXT(U3)),"sin dato",IF(U3>='Léeme'!$B$20,"barato",IF(U3<=-'Léeme'!$B$20,"caro","medio"))) | AC3: =IF(OR(Y3="",ISTEXT(Y3)),"sin dato",IF(Y3>='Léeme'!$B$19,"barato",IF(Y3<=-'Léeme'!$B$19,"caro","medio")))
A4: 1992-T3 | B4: 33877 | C4: 11.625 | D4: 1.08 | F4: 0.0637 | N4: =IF(F4="","",F4+'Léeme'!$B$10) | O4: =IF(OR(G4="",N4=""),"",MIN(MAX(G4,'Léeme'!$B$11),'Léeme'!$B$12,N4-'Léeme'!$B$16)) | P4: =IF(OR(D4="",O4=""),"",IFERROR(IF(D4<=0,"",D4*(1+O4)/(N4-O4)),"")) | Q4: =IF(H4="","",MIN(MAX(H4,'Léeme'!$B$13),'Léeme'!$B$14)) | R4: =IF(N4="","",MIN('Léeme'!$B$15,N4-'Léeme'!$B$16)) | S4: =IF(OR(E4="",Q4=""),"",IFERROR(IF(E4<=0,"",E4*(((1+Q4)/(1+N4))+((1+Q4)/(1+N4))^2+((1+Q4)/(1+N4))^3+((1+Q4)/(1+N4))^4+((1+Q4)/(1+N4))^5)+E4*(1+Q4)^5*(1+R4)/((N4-R4)*(1+N4)^5)),"")) | T4: =IF(OR(E4="",N4=""),"",IFERROR((C4*N4-E4)/(C4+E4),"")) | U4: =IF(OR(H4="",T4=""),"",IFERROR(MIN(MAX(H4,'Léeme'!$B$17),'Léeme'!$B$18)-T4,"")) | V4: =IF(OR(I4="",M4="",L4=""),"",IFERROR((I4/M4-J4-K4)/L4,"")) | W4: =IFERROR(P4/C4-1,"") | X4: =IFERROR(S4/C4-1,"") | Y4: =IFERROR(V4/C4-1,"") | Z4: =IF(OR(W4="",ISTEXT(W4)),"sin dato",IF(W4>='Léeme'!$B$19,"barato",IF(W4<=-'Léeme'!$B$19,"caro","medio"))) | AA4: =IF(OR(X4="",ISTEXT(X4)),"sin dato",IF(X4>='Léeme'!$B$19,"barato",IF(X4<=-'Léeme'!$B$19,"caro","medio"))) | AB4: =IF(OR(U4="",ISTEXT(U4)),"sin dato",IF(U4>='Léeme'!$B$20,"barato",IF(U4<=-'Léeme'!$B$20,"caro","medio"))) | AC4: =IF(OR(Y4="",ISTEXT(Y4)),"sin dato",IF(Y4>='Léeme'!$B$19,"barato",IF(Y4<=-'Léeme'!$B$19,"caro","medio")))
A5: 1992-T4 | B5: 33969 | C5: 12.125 | D5: 1.08 | F5: 0.067 | N5: =IF(F5="","",F5+'Léeme'!$B$10) | O5: =IF(OR(G5="",N5=""),"",MIN(MAX(G5,'Léeme'!$B$11),'Léeme'!$B$12,N5-'Léeme'!$B$16)) | P5: =IF(OR(D5="",O5=""),"",IFERROR(IF(D5<=0,"",D5*(1+O5)/(N5-O5)),"")) | Q5: =IF(H5="","",MIN(MAX(H5,'Léeme'!$B$13),'Léeme'!$B$14)) | R5: =IF(N5="","",MIN('Léeme'!$B$15,N5-'Léeme'!$B$16)) | S5: =IF(OR(E5="",Q5=""),"",IFERROR(IF(E5<=0,"",E5*(((1+Q5)/(1+N5))+((1+Q5)/(1+N5))^2+((1+Q5)/(1+N5))^3+((1+Q5)/(1+N5))^4+((1+Q5)/(1+N5))^5)+E5*(1+Q5)^5*(1+R5)/((N5-R5)*(1+N5)^5)),"")) | T5: =IF(OR(E5="",N5=""),"",IFERROR((C5*N5-E5)/(C5+E5),"")) | U5: =IF(OR(H5="",T5=""),"",IFERROR(MIN(MAX(H5,'Léeme'!$B$17),'Léeme'!$B$18)-T5,"")) | V5: =IF(OR(I5="",M5="",L5=""),"",IFERROR((I5/M5-J5-K5)/L5,"")) | W5: =IFERROR(P5/C5-1,"") | X5: =IFERROR(S5/C5-1,"") | Y5: =IFERROR(V5/C5-1,"") | Z5: =IF(OR(W5="",ISTEXT(W5)),"sin dato",IF(W5>='Léeme'!$B$19,"barato",IF(W5<=-'Léeme'!$B$19,"caro","medio"))) | AA5: =IF(OR(X5="",ISTEXT(X5)),"sin dato",IF(X5>='Léeme'!$B$19,"barato",IF(X5<=-'Léeme'!$B$19,"caro","medio"))) | AB5: =IF(OR(U5="",ISTEXT(U5)),"sin dato",IF(U5>='Léeme'!$B$20,"barato",IF(U5<=-'Léeme'!$B$20,"caro","medio"))) | AC5: =IF(OR(Y5="",ISTEXT(Y5)),"sin dato",IF(Y5>='Léeme'!$B$19,"barato",IF(Y5<=-'Léeme'!$B$19,"caro","medio")))
A6: 1993-T1 | B6: 34059 | C6: 13.875 | D6: 1.08 | E6: 1.15 | F6: 0.0603 | N6: =IF(F6="","",F6+'Léeme'!$B$10) | O6: =IF(OR(G6="",N6=""),"",MIN(MAX(G6,'Léeme'!$B$11),'Léeme'!$B$12,N6-'Léeme'!$B$16)) | P6: =IF(OR(D6="",O6=""),"",IFERROR(IF(D6<=0,"",D6*(1+O6)/(N6-O6)),"")) | Q6: =IF(H6="","",MIN(MAX(H6,'Léeme'!$B$13),'Léeme'!$B$14)) | R6: =IF(N6="","",MIN('Léeme'!$B$15,N6-'Léeme'!$B$16)) | S6: =IF(OR(E6="",Q6=""),"",IFERROR(IF(E6<=0,"",E6*(((1+Q6)/(1+N6))+((1+Q6)/(1+N6))^2+((1+Q6)/(1+N6))^3+((1+Q6)/(1+N6))^4+((1+Q6)/(1+N6))^5)+E6*(1+Q6)^5*(1+R6)/((N6-R6)*(1+N6)^5)),"")) | T6: =IF(OR(E6="",N6=""),"",IFERROR((C6*N6-E6)/(C6+E6),"")) | U6: =IF(OR(H6="",T6=""),"",IFERROR(MIN(MAX(H6,'Léeme'!$B$17),'Léeme'!$B$18)-T6,"")) | V6: =IF(OR(I6="",M6="",L6=""),"",IFERROR((I6/M6-J6-K6)/L6,"")) | W6: =IFERROR(P6/C6-1,"") | X6: =IFERROR(S6/C6-1,"") | Y6: =IFERROR(V6/C6-1,"") | Z6: =IF(OR(W6="",ISTEXT(W6)),"sin dato",IF(W6>='Léeme'!$B$19,"barato",IF(W6<=-'Léeme'!$B$19,"caro","medio"))) | AA6: =IF(OR(X6="",ISTEXT(X6)),"sin dato",IF(X6>='Léeme'!$B$19,"barato",IF(X6<=-'Léeme'!$B$19,"caro","medio"))) | AB6: =IF(OR(U6="",ISTEXT(U6)),"sin dato",IF(U6>='Léeme'!$B$20,"barato",IF(U6<=-'Léeme'!$B$20,"caro","medio"))) | AC6: =IF(OR(Y6="",ISTEXT(Y6)),"sin dato",IF(Y6>='Léeme'!$B$19,"barato",IF(Y6<=-'Léeme'!$B$19,"caro","medio")))
A7: 1993-T2 | B7: 34150 | C7: 13.5 | D7: 1.08 | E7: 1.15 | F7: 0.058 | N7: =IF(F7="","",F7+'Léeme'!$B$10) | O7: =IF(OR(G7="",N7=""),"",MIN(MAX(G7,'Léeme'!$B$11),'Léeme'!$B$12,N7-'Léeme'!$B$16)) | P7: =IF(OR(D7="",O7=""),"",IFERROR(IF(D7<=0,"",D7*(1+O7)/(N7-O7)),"")) | Q7: =IF(H7="","",MIN(MAX(H7,'Léeme'!$B$13),'Léeme'!$B$14)) | R7: =IF(N7="","",MIN('Léeme'!$B$15,N7-'Léeme'!$B$16)) | S7: =IF(OR(E7="",Q7=""),"",IFERROR(IF(E7<=0,"",E7*(((1+Q7)/(1+N7))+((1+Q7)/(1+N7))^2+((1+Q7)/(1+N7))^3+((1+Q7)/(1+N7))^4+((1+Q7)/(1+N7))^5)+E7*(1+Q7)^5*(1+R7)/((N7-R7)*(1+N7)^5)),"")) | T7: =IF(OR(E7="",N7=""),"",IFERROR((C7*N7-E7)/(C7+E7),"")) | U7: =IF(OR(H7="",T7=""),"",IFERROR(MIN(MAX(H7,'Léeme'!$B$17),'Léeme'!$B$18)-T7,"")) | V7: =IF(OR(I7="",M7="",L7=""),"",IFERROR((I7/M7-J7-K7)/L7,"")) | W7: =IFERROR(P7/C7-1,"") | X7: =IFERROR(S7/C7-1,"") | Y7: =IFERROR(V7/C7-1,"") | Z7: =IF(OR(W7="",ISTEXT(W7)),"sin dato",IF(W7>='Léeme'!$B$19,"barato",IF(W7<=-'Léeme'!$B$19,"caro","medio"))) | AA7: =IF(OR(X7="",ISTEXT(X7)),"sin dato",IF(X7>='Léeme'!$B$19,"barato",IF(X7<=-'Léeme'!$B$19,"caro","medio"))) | AB7: =IF(OR(U7="",ISTEXT(U7)),"sin dato",IF(U7>='Léeme'!$B$20,"barato",IF(U7<=-'Léeme'!$B$20,"caro","medio"))) | AC7: =IF(OR(Y7="",ISTEXT(Y7)),"sin dato",IF(Y7>='Léeme'!$B$19,"barato",IF(Y7<=-'Léeme'!$B$19,"caro","medio")))
A8: 1993-T3 | B8: 34242 | C8: 14 | D8: 1.12 | E8: 1.15 | F8: 0.054 | N8: =IF(F8="","",F8+'Léeme'!$B$10) | O8: =IF(OR(G8="",N8=""),"",MIN(MAX(G8,'Léeme'!$B$11),'Léeme'!$B$12,N8-'Léeme'!$B$16)) | P8: =IF(OR(D8="",O8=""),"",IFERROR(IF(D8<=0,"",D8*(1+O8)/(N8-O8)),"")) | Q8: =IF(H8="","",MIN(MAX(H8,'Léeme'!$B$13),'Léeme'!$B$14)) | R8: =IF(N8="","",MIN('Léeme'!$B$15,N8-'Léeme'!$B$16)) | S8: =IF(OR(E8="",Q8=""),"",IFERROR(IF(E8<=0,"",E8*(((1+Q8)/(1+N8))+((1+Q8)/(1+N8))^2+((1+Q8)/(1+N8))^3+((1+Q8)/(1+N8))^4+((1+Q8)/(1+N8))^5)+E8*(1+Q8)^5*(1+R8)/((N8-R8)*(1+N8)^5)),"")) | T8: =IF(OR(E8="",N8=""),"",IFERROR((C8*N8-E8)/(C8+E8),"")) | U8: =IF(OR(H8="",T8=""),"",IFERROR(MIN(MAX(H8,'Léeme'!$B$17),'Léeme'!$B$18)-T8,"")) | V8: =IF(OR(I8="",M8="",L8=""),"",IFERROR((I8/M8-J8-K8)/L8,"")) | W8: =IFERROR(P8/C8-1,"") | X8: =IFERROR(S8/C8-1,"") | Y8: =IFERROR(V8/C8-1,"") | Z8: =IF(OR(W8="",ISTEXT(W8)),"sin dato",IF(W8>='Léeme'!$B$19,"barato",IF(W8<=-'Léeme'!$B$19,"caro","medio"))) | AA8: =IF(OR(X8="",ISTEXT(X8)),"sin dato",IF(X8>='Léeme'!$B$19,"barato",IF(X8<=-'Léeme'!$B$19,"caro","medio"))) | AB8: =IF(OR(U8="",ISTEXT(U8)),"sin dato",IF(U8>='Léeme'!$B$20,"barato",IF(U8<=-'Léeme'!$B$20,"caro","medio"))) | AC8: =IF(OR(Y8="",ISTEXT(Y8)),"sin dato",IF(Y8>='Léeme'!$B$19,"barato",IF(Y8<=-'Léeme'!$B$19,"caro","medio")))
A9: 1993-T4 | B9: 34334 | C9: 13.75 | D9: 1.12 | E9: 1.15 | F9: 0.0583 | N9: =IF(F9="","",F9+'Léeme'!$B$10) | O9: =IF(OR(G9="",N9=""),"",MIN(MAX(G9,'Léeme'!$B$11),'Léeme'!$B$12,N9-'Léeme'!$B$16)) | P9: =IF(OR(D9="",O9=""),"",IFERROR(IF(D9<=0,"",D9*(1+O9)/(N9-O9)),"")) | Q9: =IF(H9="","",MIN(MAX(H9,'Léeme'!$B$13),'Léeme'!$B$14)) | R9: =IF(N9="","",MIN('Léeme'!$B$15,N9-'Léeme'!$B$16)) | S9: =IF(OR(E9="",Q9=""),"",IFERROR(IF(E9<=0,"",E9*(((1+Q9)/(1+N9))+((1+Q9)/(1+N9))^2+((1+Q9)/(1+N9))^3+((1+Q9)/(1+N9))^4+((1+Q9)/(1+N9))^5)+E9*(1+Q9)^5*(1+R9)/((N9-R9)*(1+N9)^5)),"")) | T9: =IF(OR(E9="",N9=""),"",IFERROR((C9*N9-E9)/(C9+E9),"")) | U9: =IF(OR(H9="",T9=""),"",IFERROR(MIN(MAX(H9,'Léeme'!$B$17),'Léeme'!$B$18)-T9,"")) | V9: =IF(OR(I9="",M9="",L9=""),"",IFERROR((I9/M9-J9-K9)/L9,"")) | W9: =IFERROR(P9/C9-1,"") | X9: =IFERROR(S9/C9-1,"") | Y9: =IFERROR(V9/C9-1,"") | Z9: =IF(OR(W9="",ISTEXT(W9)),"sin dato",IF(W9>='Léeme'!$B$19,"barato",IF(W9<=-'Léeme'!$B$19,"caro","medio"))) | AA9: =IF(OR(X9="",ISTEXT(X9)),"sin dato",IF(X9>='Léeme'!$B$19,"barato",IF(X9<=-'Léeme'!$B$19,"caro","medio"))) | AB9: =IF(OR(U9="",ISTEXT(U9)),"sin dato",IF(U9>='Léeme'!$B$20,"barato",IF(U9<=-'Léeme'!$B$20,"caro","medio"))) | AC9: =IF(OR(Y9="",ISTEXT(Y9)),"sin dato",IF(Y9>='Léeme'!$B$19,"barato",IF(Y9<=-'Léeme'!$B$19,"caro","medio")))
A10: 1994-T1 | B10: 34424 | C10: 13.875 | D10: 1.12 | E10: 1.05 | F10: 0.0677 | N10: =IF(F10="","",F10+'Léeme'!$B$10) | O10: =IF(OR(G10="",N10=""),"",MIN(MAX(G10,'Léeme'!$B$11),'Léeme'!$B$12,N10-'Léeme'!$B$16)) | P10: =IF(OR(D10="",O10=""),"",IFERROR(IF(D10<=0,"",D10*(1+O10)/(N10-O10)),"")) | Q10: =IF(H10="","",MIN(MAX(H10,'Léeme'!$B$13),'Léeme'!$B$14)) | R10: =IF(N10="","",MIN('Léeme'!$B$15,N10-'Léeme'!$B$16)) | S10: =IF(OR(E10="",Q10=""),"",IFERROR(IF(E10<=0,"",E10*(((1+Q10)/(1+N10))+((1+Q10)/(1+N10))^2+((1+Q10)/(1+N10))^3+((1+Q10)/(1+N10))^4+((1+Q10)/(1+N10))^5)+E10*(1+Q10)^5*(1+R10)/((N10-R10)*(1+N10)^5)),"")) | T10: =IF(OR(E10="",N10=""),"",IFERROR((C10*N10-E10)/(C10+E10),"")) | U10: =IF(OR(H10="",T10=""),"",IFERROR(MIN(MAX(H10,'Léeme'!$B$17),'Léeme'!$B$18)-T10,"")) | V10: =IF(OR(I10="",M10="",L10=""),"",IFERROR((I10/M10-J10-K10)/L10,"")) | W10: =IFERROR(P10/C10-1,"") | X10: =IFERROR(S10/C10-1,"") | Y10: =IFERROR(V10/C10-1,"") | Z10: =IF(OR(W10="",ISTEXT(W10)),"sin dato",IF(W10>='Léeme'!$B$19,"barato",IF(W10<=-'Léeme'!$B$19,"caro","medio"))) | AA10: =IF(OR(X10="",ISTEXT(X10)),"sin dato",IF(X10>='Léeme'!$B$19,"barato",IF(X10<=-'Léeme'!$B$19,"caro","medio"))) | AB10: =IF(OR(U10="",ISTEXT(U10)),"sin dato",IF(U10>='Léeme'!$B$20,"barato",IF(U10<=-'Léeme'!$B$20,"caro","medio"))) | AC10: =IF(OR(Y10="",ISTEXT(Y10)),"sin dato",IF(Y10>='Léeme'!$B$19,"barato",IF(Y10<=-'Léeme'!$B$19,"caro","medio")))
A11: 1994-T2 | B11: 34515 | C11: 13.625 | D11: 1.12 | E11: 1.05 | F11: 0.0734 | N11: =IF(F11="","",F11+'Léeme'!$B$10) | O11: =IF(OR(G11="",N11=""),"",MIN(MAX(G11,'Léeme'!$B$11),'Léeme'!$B$12,N11-'Léeme'!$B$16)) | P11: =IF(OR(D11="",O11=""),"",IFERROR(IF(D11<=0,"",D11*(1+O11)/(N11-O11)),"")) | Q11: =IF(H11="","",MIN(MAX(H11,'Léeme'!$B$13),'Léeme'!$B$14)) | R11: =IF(N11="","",MIN('Léeme'!$B$15,N11-'Léeme'!$B$16)) | S11: =IF(OR(E11="",Q11=""),"",IFERROR(IF(E11<=0,"",E11*(((1+Q11)/(1+N11))+((1+Q11)/(1+N11))^2+((1+Q11)/(1+N11))^3+((1+Q11)/(1+N11))^4+((1+Q11)/(1+N11))^5)+E11*(1+Q11)^5*(1+R11)/((N11-R11)*(1+N11)^5)),"")) | T11: =IF(OR(E11="",N11=""),"",IFERROR((C11*N11-E11)/(C11+E11),"")) | U11: =IF(OR(H11="",T11=""),"",IFERROR(MIN(MAX(H11,'Léeme'!$B$17),'Léeme'!$B$18)-T11,"")) | V11: =IF(OR(I11="",M11="",L11=""),"",IFERROR((I11/M11-J11-K11)/L11,"")) | W11: =IFERROR(P11/C11-1,"") | X11: =IFERROR(S11/C11-1,"") | Y11: =IFERROR(V11/C11-1,"") | Z11: =IF(OR(W11="",ISTEXT(W11)),"sin dato",IF(W11>='Léeme'!$B$19,"barato",IF(W11<=-'Léeme'!$B$19,"caro","medio"))) | AA11: =IF(OR(X11="",ISTEXT(X11)),"sin dato",IF(X11>='Léeme'!$B$19,"barato",IF(X11<=-'Léeme'!$B$19,"caro","medio"))) | AB11: =IF(OR(U11="",ISTEXT(U11)),"sin dato",IF(U11>='Léeme'!$B$20,"barato",IF(U11<=-'Léeme'!$B$20,"caro","medio"))) | AC11: =IF(OR(Y11="",ISTEXT(Y11)),"sin dato",IF(Y11>='Léeme'!$B$19,"barato",IF(Y11<=-'Léeme'!$B$19,"caro","medio")))
A12: 1994-T3 | B12: 34607 | C12: 12.25 | D12: 1.16 | E12: 1.05 | F12: 0.0762 | N12: =IF(F12="","",F12+'Léeme'!$B$10) | O12: =IF(OR(G12="",N12=""),"",MIN(MAX(G12,'Léeme'!$B$11),'Léeme'!$B$12,N12-'Léeme'!$B$16)) | P12: =IF(OR(D12="",O12=""),"",IFERROR(IF(D12<=0,"",D12*(1+O12)/(N12-O12)),"")) | Q12: =IF(H12="","",MIN(MAX(H12,'Léeme'!$B$13),'Léeme'!$B$14)) | R12: =IF(N12="","",MIN('Léeme'!$B$15,N12-'Léeme'!$B$16)) | S12: =IF(OR(E12="",Q12=""),"",IFERROR(IF(E12<=0,"",E12*(((1+Q12)/(1+N12))+((1+Q12)/(1+N12))^2+((1+Q12)/(1+N12))^3+((1+Q12)/(1+N12))^4+((1+Q12)/(1+N12))^5)+E12*(1+Q12)^5*(1+R12)/((N12-R12)*(1+N12)^5)),"")) | T12: =IF(OR(E12="",N12=""),"",IFERROR((C12*N12-E12)/(C12+E12),"")) | U12: =IF(OR(H12="",T12=""),"",IFERROR(MIN(MAX(H12,'Léeme'!$B$17),'Léeme'!$B$18)-T12,"")) | V12: =IF(OR(I12="",M12="",L12=""),"",IFERROR((I12/M12-J12-K12)/L12,"")) | W12: =IFERROR(P12/C12-1,"") | X12: =IFERROR(S12/C12-1,"") | Y12: =IFERROR(V12/C12-1,"") | Z12: =IF(OR(W12="",ISTEXT(W12)),"sin dato",IF(W12>='Léeme'!$B$19,"barato",IF(W12<=-'Léeme'!$B$19,"caro","medio"))) | AA12: =IF(OR(X12="",ISTEXT(X12)),"sin dato",IF(X12>='Léeme'!$B$19,"barato",IF(X12<=-'Léeme'!$B$19,"caro","medio"))) | AB12: =IF(OR(U12="",ISTEXT(U12)),"sin dato",IF(U12>='Léeme'!$B$20,"barato",IF(U12<=-'Léeme'!$B$20,"caro","medio"))) | AC12: =IF(OR(Y12="",ISTEXT(Y12)),"sin dato",IF(Y12>='Léeme'!$B$19,"barato",IF(Y12<=-'Léeme'!$B$19,"caro","medio")))
A13: 1994-T4 | B13: 34698 | C13: 12.25 | D13: 1.16 | E13: 1.05 | F13: 0.0784 | N13: =IF(F13="","",F13+'Léeme'!$B$10) | O13: =IF(OR(G13="",N13=""),"",MIN(MAX(G13,'Léeme'!$B$11),'Léeme'!$B$12,N13-'Léeme'!$B$16)) | P13: =IF(OR(D13="",O13=""),"",IFERROR(IF(D13<=0,"",D13*(1+O13)/(N13-O13)),"")) | Q13: =IF(H13="","",MIN(MAX(H13,'Léeme'!$B$13),'Léeme'!$B$14)) | R13: =IF(N13="","",MIN('Léeme'!$B$15,N13-'Léeme'!$B$16)) | S13: =IF(OR(E13="",Q13=""),"",IFERROR(IF(E13<=0,"",E13*(((1+Q13)/(1+N13))+((1+Q13)/(1+N13))^2+((1+Q13)/(1+N13))^3+((1+Q13)/(1+N13))^4+((1+Q13)/(1+N13))^5)+E13*(1+Q13)^5*(1+R13)/((N13-R13)*(1+N13)^5)),"")) | T13: =IF(OR(E13="",N13=""),"",IFERROR((C13*N13-E13)/(C13+E13),"")) | U13: =IF(OR(H13="",T13=""),"",IFERROR(MIN(MAX(H13,'Léeme'!$B$17),'Léeme'!$B$18)-T13,"")) | V13: =IF(OR(I13="",M13="",L13=""),"",IFERROR((I13/M13-J13-K13)/L13,"")) | W13: =IFERROR(P13/C13-1,"") | X13: =IFERROR(S13/C13-1,"") | Y13: =IFERROR(V13/C13-1,"") | Z13: =IF(OR(W13="",ISTEXT(W13)),"sin dato",IF(W13>='Léeme'!$B$19,"barato",IF(W13<=-'Léeme'!$B$19,"caro","medio"))) | AA13: =IF(OR(X13="",ISTEXT(X13)),"sin dato",IF(X13>='Léeme'!$B$19,"barato",IF(X13<=-'Léeme'!$B$19,"caro","medio"))) | AB13: =IF(OR(U13="",ISTEXT(U13)),"sin dato",IF(U13>='Léeme'!$B$20,"barato",IF(U13<=-'Léeme'!$B$20,"caro","medio"))) | AC13: =IF(OR(Y13="",ISTEXT(Y13)),"sin dato",IF(Y13>='Léeme'!$B$19,"barato",IF(Y13<=-'Léeme'!$B$19,"caro","medio")))
A14: 1995-T1 | B14: 34789 | C14: 12.125 | D14: 1.16 | E14: 1.16 | F14: 0.072 | N14: =IF(F14="","",F14+'Léeme'!$B$10) | O14: =IF(OR(G14="",N14=""),"",MIN(MAX(G14,'Léeme'!$B$11),'Léeme'!$B$12,N14-'Léeme'!$B$16)) | P14: =IF(OR(D14="",O14=""),"",IFERROR(IF(D14<=0,"",D14*(1+O14)/(N14-O14)),"")) | Q14: =IF(H14="","",MIN(MAX(H14,'Léeme'!$B$13),'Léeme'!$B$14)) | R14: =IF(N14="","",MIN('Léeme'!$B$15,N14-'Léeme'!$B$16)) | S14: =IF(OR(E14="",Q14=""),"",IFERROR(IF(E14<=0,"",E14*(((1+Q14)/(1+N14))+((1+Q14)/(1+N14))^2+((1+Q14)/(1+N14))^3+((1+Q14)/(1+N14))^4+((1+Q14)/(1+N14))^5)+E14*(1+Q14)^5*(1+R14)/((N14-R14)*(1+N14)^5)),"")) | T14: =IF(OR(E14="",N14=""),"",IFERROR((C14*N14-E14)/(C14+E14),"")) | U14: =IF(OR(H14="",T14=""),"",IFERROR(MIN(MAX(H14,'Léeme'!$B$17),'Léeme'!$B$18)-T14,"")) | V14: =IF(OR(I14="",M14="",L14=""),"",IFERROR((I14/M14-J14-K14)/L14,"")) | W14: =IFERROR(P14/C14-1,"") | X14: =IFERROR(S14/C14-1,"") | Y14: =IFERROR(V14/C14-1,"") | Z14: =IF(OR(W14="",ISTEXT(W14)),"sin dato",IF(W14>='Léeme'!$B$19,"barato",IF(W14<=-'Léeme'!$B$19,"caro","medio"))) | AA14: =IF(OR(X14="",ISTEXT(X14)),"sin dato",IF(X14>='Léeme'!$B$19,"barato",IF(X14<=-'Léeme'!$B$19,"caro","medio"))) | AB14: =IF(OR(U14="",ISTEXT(U14)),"sin dato",IF(U14>='Léeme'!$B$20,"barato",IF(U14<=-'Léeme'!$B$20,"caro","medio"))) | AC14: =IF(OR(Y14="",ISTEXT(Y14)),"sin dato",IF(Y14>='Léeme'!$B$19,"barato",IF(Y14<=-'Léeme'!$B$19,"caro","medio")))
A15: 1995-T2 | B15: 34880 | C15: 13.125 | D15: 1.16 | E15: 1.16 | F15: 0.0621 | N15: =IF(F15="","",F15+'Léeme'!$B$10) | O15: =IF(OR(G15="",N15=""),"",MIN(MAX(G15,'Léeme'!$B$11),'Léeme'!$B$12,N15-'Léeme'!$B$16)) | P15: =IF(OR(D15="",O15=""),"",IFERROR(IF(D15<=0,"",D15*(1+O15)/(N15-O15)),"")) | Q15: =IF(H15="","",MIN(MAX(H15,'Léeme'!$B$13),'Léeme'!$B$14)) | R15: =IF(N15="","",MIN('Léeme'!$B$15,N15-'Léeme'!$B$16)) | S15: =IF(OR(E15="",Q15=""),"",IFERROR(IF(E15<=0,"",E15*(((1+Q15)/(1+N15))+((1+Q15)/(1+N15))^2+((1+Q15)/(1+N15))^3+((1+Q15)/(1+N15))^4+((1+Q15)/(1+N15))^5)+E15*(1+Q15)^5*(1+R15)/((N15-R15)*(1+N15)^5)),"")) | T15: =IF(OR(E15="",N15=""),"",IFERROR((C15*N15-E15)/(C15+E15),"")) | U15: =IF(OR(H15="",T15=""),"",IFERROR(MIN(MAX(H15,'Léeme'!$B$17),'Léeme'!$B$18)-T15,"")) | V15: =IF(OR(I15="",M15="",L15=""),"",IFERROR((I15/M15-J15-K15)/L15,"")) | W15: =IFERROR(P15/C15-1,"") | X15: =IFERROR(S15/C15-1,"") | Y15: =IFERROR(V15/C15-1,"") | Z15: =IF(OR(W15="",ISTEXT(W15)),"sin dato",IF(W15>='Léeme'!$B$19,"barato",IF(W15<=-'Léeme'!$B$19,"caro","medio"))) | AA15: =IF(OR(X15="",ISTEXT(X15)),"sin dato",IF(X15>='Léeme'!$B$19,"barato",IF(X15<=-'Léeme'!$B$19,"caro","medio"))) | AB15: =IF(OR(U15="",ISTEXT(U15)),"sin dato",IF(U15>='Léeme'!$B$20,"barato",IF(U15<=-'Léeme'!$B$20,"caro","medio"))) | AC15: =IF(OR(Y15="",ISTEXT(Y15)),"sin dato",IF(Y15>='Léeme'!$B$19,"barato",IF(Y15<=-'Léeme'!$B$19,"caro","medio")))
A16: 1995-T3 | B16: 34971 | C16: 13.25 | D16: 1.16 | E16: 1.16 | F16: 0.0617 | N16: =IF(F16="","",F16+'Léeme'!$B$10) | O16: =IF(OR(G16="",N16=""),"",MIN(MAX(G16,'Léeme'!$B$11),'Léeme'!$B$12,N16-'Léeme'!$B$16)) | P16: =IF(OR(D16="",O16=""),"",IFERROR(IF(D16<=0,"",D16*(1+O16)/(N16-O16)),"")) | Q16: =IF(H16="","",MIN(MAX(H16,'Léeme'!$B$13),'Léeme'!$B$14)) | R16: =IF(N16="","",MIN('Léeme'!$B$15,N16-'Léeme'!$B$16)) | S16: =IF(OR(E16="",Q16=""),"",IFERROR(IF(E16<=0,"",E16*(((1+Q16)/(1+N16))+((1+Q16)/(1+N16))^2+((1+Q16)/(1+N16))^3+((1+Q16)/(1+N16))^4+((1+Q16)/(1+N16))^5)+E16*(1+Q16)^5*(1+R16)/((N16-R16)*(1+N16)^5)),"")) | T16: =IF(OR(E16="",N16=""),"",IFERROR((C16*N16-E16)/(C16+E16),"")) | U16: =IF(OR(H16="",T16=""),"",IFERROR(MIN(MAX(H16,'Léeme'!$B$17),'Léeme'!$B$18)-T16,"")) | V16: =IF(OR(I16="",M16="",L16=""),"",IFERROR((I16/M16-J16-K16)/L16,"")) | W16: =IFERROR(P16/C16-1,"") | X16: =IFERROR(S16/C16-1,"") | Y16: =IFERROR(V16/C16-1,"") | Z16: =IF(OR(W16="",ISTEXT(W16)),"sin dato",IF(W16>='Léeme'!$B$19,"barato",IF(W16<=-'Léeme'!$B$19,"caro","medio"))) | AA16: =IF(OR(X16="",ISTEXT(X16)),"sin dato",IF(X16>='Léeme'!$B$19,"barato",IF(X16<=-'Léeme'!$B$19,"caro","medio"))) | AB16: =IF(OR(U16="",ISTEXT(U16)),"sin dato",IF(U16>='Léeme'!$B$20,"barato",IF(U16<=-'Léeme'!$B$20,"caro","medio"))) | AC16: =IF(OR(Y16="",ISTEXT(Y16)),"sin dato",IF(Y16>='Léeme'!$B$19,"barato",IF(Y16<=-'Léeme'!$B$19,"caro","medio")))
A17: 1995-T4 | B17: 35062 | C17: 12.75 | D17: 1.16 | E17: 1.16 | F17: 0.0558 | N17: =IF(F17="","",F17+'Léeme'!$B$10) | O17: =IF(OR(G17="",N17=""),"",MIN(MAX(G17,'Léeme'!$B$11),'Léeme'!$B$12,N17-'Léeme'!$B$16)) | P17: =IF(OR(D17="",O17=""),"",IFERROR(IF(D17<=0,"",D17*(1+O17)/(N17-O17)),"")) | Q17: =IF(H17="","",MIN(MAX(H17,'Léeme'!$B$13),'Léeme'!$B$14)) | R17: =IF(N17="","",MIN('Léeme'!$B$15,N17-'Léeme'!$B$16)) | S17: =IF(OR(E17="",Q17=""),"",IFERROR(IF(E17<=0,"",E17*(((1+Q17)/(1+N17))+((1+Q17)/(1+N17))^2+((1+Q17)/(1+N17))^3+((1+Q17)/(1+N17))^4+((1+Q17)/(1+N17))^5)+E17*(1+Q17)^5*(1+R17)/((N17-R17)*(1+N17)^5)),"")) | T17: =IF(OR(E17="",N17=""),"",IFERROR((C17*N17-E17)/(C17+E17),"")) | U17: =IF(OR(H17="",T17=""),"",IFERROR(MIN(MAX(H17,'Léeme'!$B$17),'Léeme'!$B$18)-T17,"")) | V17: =IF(OR(I17="",M17="",L17=""),"",IFERROR((I17/M17-J17-K17)/L17,"")) | W17: =IFERROR(P17/C17-1,"") | X17: =IFERROR(S17/C17-1,"") | Y17: =IFERROR(V17/C17-1,"") | Z17: =IF(OR(W17="",ISTEXT(W17)),"sin dato",IF(W17>='Léeme'!$B$19,"barato",IF(W17<=-'Léeme'!$B$19,"caro","medio"))) | AA17: =IF(OR(X17="",ISTEXT(X17)),"sin dato",IF(X17>='Léeme'!$B$19,"barato",IF(X17<=-'Léeme'!$B$19,"caro","medio"))) | AB17: =IF(OR(U17="",ISTEXT(U17)),"sin dato",IF(U17>='Léeme'!$B$20,"barato",IF(U17<=-'Léeme'!$B$20,"caro","medio"))) | AC17: =IF(OR(Y17="",ISTEXT(Y17)),"sin dato",IF(Y17>='Léeme'!$B$19,"barato",IF(Y17<=-'Léeme'!$B$19,"caro","medio")))
... A21: 1996-T4 | B21: 35430 | C21: 15.875 | D21: 1.2 | E21: 1.24 | F21: 0.0643 | N21: =IF(F21="","",F21+'Léeme'!$B$10) | O21: =IF(OR(G21="",N21=""),"",MIN(MAX(G21,'Léeme'!$B$11),'Léeme'!$B$12,N21-'Léeme'!$B$16)) | P21: =IF(OR(D21="",O21=""),"",IFERROR(IF(D21<=0,"",D21*(1+O21)/(N21-O21)),"")) | Q21: =IF(H21="","",MIN(MAX(H21,'Léeme'!$B$13),'Léeme'!$B$14)) | R21: =IF(N21="","",MIN('Léeme'!$B$15,N21-'Léeme'!$B$16)) | S21: =IF(OR(E21="",Q21=""),"",IFERROR(IF(E21<=0,"",E21*(((1+Q21)/(1+N21))+((1+Q21)/(1+N21))^2+((1+Q21)/(1+N21))^3+((1+Q21)/(1+N21))^4+((1+Q21)/(1+N21))^5)+E21*(1+Q21)^5*(1+R21)/((N21-R21)*(1+N21)^5)),"")) | T21: =IF(OR(E21="",N21=""),"",IFERROR((C21*N21-E21)/(C21+E21),"")) | U21: =IF(OR(H21="",T21=""),"",IFERROR(MIN(MAX(H21,'Léeme'!$B$17),'Léeme'!$B$18)-T21,"")) | V21: =IF(OR(I21="",M21="",L21=""),"",IFERROR((I21/M21-J21-K21)/L21,"")) | W21: =IFERROR(P21/C21-1,"") | X21: =IFERROR(S21/C21-1,"") | Y21: =IFERROR(V21/C21-1,"") | Z21: =IF(OR(W21="",ISTEXT(W21)),"sin dato",IF(W21>='Léeme'!$B$19,"barato",IF(W21<=-'Léeme'!$B$19,"caro","medio"))) | AA21: =IF(OR(X21="",ISTEXT(X21)),"sin dato",IF(X21>='Léeme'!$B$19,"barato",IF(X21<=-'Léeme'!$B$19,"caro","medio"))) | AB21: =IF(OR(U21="",ISTEXT(U21)),"sin dato",IF(U21>='Léeme'!$B$20,"barato",IF(U21<=-'Léeme'!$B$20,"caro","medio"))) | AC21: =IF(OR(Y21="",ISTEXT(Y21)),"sin dato",IF(Y21>='Léeme'!$B$19,"barato",IF(Y21<=-'Léeme'!$B$19,"caro","medio")))
A22: 1997-T1 | B22: 35520 | C22: 14.75 | D22: 1.2 | E22: 1.34 | F22: 0.0692 | G22: 0.021295688 | N22: =IF(F22="","",F22+'Léeme'!$B$10) | O22: =IF(OR(G22="",N22=""),"",MIN(MAX(G22,'Léeme'!$B$11),'Léeme'!$B$12,N22-'Léeme'!$B$16)) | P22: =IF(OR(D22="",O22=""),"",IFERROR(IF(D22<=0,"",D22*(1+O22)/(N22-O22)),"")) | Q22: =IF(H22="","",MIN(MAX(H22,'Léeme'!$B$13),'Léeme'!$B$14)) | R22: =IF(N22="","",MIN('Léeme'!$B$15,N22-'Léeme'!$B$16)) | S22: =IF(OR(E22="",Q22=""),"",IFERROR(IF(E22<=0,"",E22*(((1+Q22)/(1+N22))+((1+Q22)/(1+N22))^2+((1+Q22)/(1+N22))^3+((1+Q22)/(1+N22))^4+((1+Q22)/(1+N22))^5)+E22*(1+Q22)^5*(1+R22)/((N22-R22)*(1+N22)^5)),"")) | T22: =IF(OR(E22="",N22=""),"",IFERROR((C22*N22-E22)/(C22+E22),"")) | U22: =IF(OR(H22="",T22=""),"",IFERROR(MIN(MAX(H22,'Léeme'!$B$17),'Léeme'!$B$18)-T22,"")) | V22: =IF(OR(I22="",M22="",L22=""),"",IFERROR((I22/M22-J22-K22)/L22,"")) | W22: =IFERROR(P22/C22-1,"") | X22: =IFERROR(S22/C22-1,"") | Y22: =IFERROR(V22/C22-1,"") | Z22: =IF(OR(W22="",ISTEXT(W22)),"sin dato",IF(W22>='Léeme'!$B$19,"barato",IF(W22<=-'Léeme'!$B$19,"caro","medio"))) | AA22: =IF(OR(X22="",ISTEXT(X22)),"sin dato",IF(X22>='Léeme'!$B$19,"barato",IF(X22<=-'Léeme'!$B$19,"caro","medio"))) | AB22: =IF(OR(U22="",ISTEXT(U22)),"sin dato",IF(U22>='Léeme'!$B$20,"barato",IF(U22<=-'Léeme'!$B$20,"caro","medio"))) | AC22: =IF(OR(Y22="",ISTEXT(Y22)),"sin dato",IF(Y22>='Léeme'!$B$19,"barato",IF(Y22<=-'Léeme'!$B$19,"caro","medio")))
A23: 1997-T2 | B23: 35611 | C23: 15.3125 | D23: 1.2 | E23: 1.34 | F23: 0.0651 | G23: 0.021295688 | N23: =IF(F23="","",F23+'Léeme'!$B$10) | O23: =IF(OR(G23="",N23=""),"",MIN(MAX(G23,'Léeme'!$B$11),'Léeme'!$B$12,N23-'Léeme'!$B$16)) | P23: =IF(OR(D23="",O23=""),"",IFERROR(IF(D23<=0,"",D23*(1+O23)/(N23-O23)),"")) | Q23: =IF(H23="","",MIN(MAX(H23,'Léeme'!$B$13),'Léeme'!$B$14)) | R23: =IF(N23="","",MIN('Léeme'!$B$15,N23-'Léeme'!$B$16)) | S23: =IF(OR(E23="",Q23=""),"",IFERROR(IF(E23<=0,"",E23*(((1+Q23)/(1+N23))+((1+Q23)/(1+N23))^2+((1+Q23)/(1+N23))^3+((1+Q23)/(1+N23))^4+((1+Q23)/(1+N23))^5)+E23*(1+Q23)^5*(1+R23)/((N23-R23)*(1+N23)^5)),"")) | T23: =IF(OR(E23="",N23=""),"",IFERROR((C23*N23-E23)/(C23+E23),"")) | U23: =IF(OR(H23="",T23=""),"",IFERROR(MIN(MAX(H23,'Léeme'!$B$17),'Léeme'!$B$18)-T23,"")) | V23: =IF(OR(I23="",M23="",L23=""),"",IFERROR((I23/M23-J23-K23)/L23,"")) | W23: =IFERROR(P23/C23-1,"") | X23: =IFERROR(S23/C23-1,"") | Y23: =IFERROR(V23/C23-1,"") | Z23: =IF(OR(W23="",ISTEXT(W23)),"sin dato",IF(W23>='Léeme'!$B$19,"barato",IF(W23<=-'Léeme'!$B$19,"caro","medio"))) | AA23: =IF(OR(X23="",ISTEXT(X23)),"sin dato",IF(X23>='Léeme'!$B$19,"barato",IF(X23<=-'Léeme'!$B$19,"caro","medio"))) | AB23: =IF(OR(U23="",ISTEXT(U23)),"sin dato",IF(U23>='Léeme'!$B$20,"barato",IF(U23<=-'Léeme'!$B$20,"caro","medio"))) | AC23: =IF(OR(Y23="",ISTEXT(Y23)),"sin dato",IF(Y23>='Léeme'!$B$19,"barato",IF(Y23<=-'Léeme'!$B$19,"caro","medio")))
A24: 1997-T3 | B24: 35703 | C24: 15.9375 | D24: 1.2 | E24: 1.34 | F24: 0.0612 | G24: 0.021295688 | N24: =IF(F24="","",F24+'Léeme'!$B$10) | O24: =IF(OR(G24="",N24=""),"",MIN(MAX(G24,'Léeme'!$B$11),'Léeme'!$B$12,N24-'Léeme'!$B$16)) | P24: =IF(OR(D24="",O24=""),"",IFERROR(IF(D24<=0,"",D24*(1+O24)/(N24-O24)),"")) | Q24: =IF(H24="","",MIN(MAX(H24,'Léeme'!$B$13),'Léeme'!$B$14)) | R24: =IF(N24="","",MIN('Léeme'!$B$15,N24-'Léeme'!$B$16)) | S24: =IF(OR(E24="",Q24=""),"",IFERROR(IF(E24<=0,"",E24*(((1+Q24)/(1+N24))+((1+Q24)/(1+N24))^2+((1+Q24)/(1+N24))^3+((1+Q24)/(1+N24))^4+((1+Q24)/(1+N24))^5)+E24*(1+Q24)^5*(1+R24)/((N24-R24)*(1+N24)^5)),"")) | T24: =IF(OR(E24="",N24=""),"",IFERROR((C24*N24-E24)/(C24+E24),"")) | U24: =IF(OR(H24="",T24=""),"",IFERROR(MIN(MAX(H24,'Léeme'!$B$17),'Léeme'!$B$18)-T24,"")) | V24: =IF(OR(I24="",M24="",L24=""),"",IFERROR((I24/M24-J24-K24)/L24,"")) | W24: =IFERROR(P24/C24-1,"") | X24: =IFERROR(S24/C24-1,"") | Y24: =IFERROR(V24/C24-1,"") | Z24: =IF(OR(W24="",ISTEXT(W24)),"sin dato",IF(W24>='Léeme'!$B$19,"barato",IF(W24<=-'Léeme'!$B$19,"caro","medio"))) | AA24: =IF(OR(X24="",ISTEXT(X24)),"sin dato",IF(X24>='Léeme'!$B$19,"barato",IF(X24<=-'Léeme'!$B$19,"caro","medio"))) | AB24: =IF(OR(U24="",ISTEXT(U24)),"sin dato",IF(U24>='Léeme'!$B$20,"barato",IF(U24<=-'Léeme'!$B$20,"caro","medio"))) | AC24: =IF(OR(Y24="",ISTEXT(Y24)),"sin dato",IF(Y24>='Léeme'!$B$19,"barato",IF(Y24<=-'Léeme'!$B$19,"caro","medio")))
A25: 1997-T4 | B25: 35795 | C25: 17.875 | D25: 1.2 | E25: 1.34 | F25: 0.0575 | G25: 0.021295688 | N25: =IF(F25="","",F25+'Léeme'!$B$10) | O25: =IF(OR(G25="",N25=""),"",MIN(MAX(G25,'Léeme'!$B$11),'Léeme'!$B$12,N25-'Léeme'!$B$16)) | P25: =IF(OR(D25="",O25=""),"",IFERROR(IF(D25<=0,"",D25*(1+O25)/(N25-O25)),"")) | Q25: =IF(H25="","",MIN(MAX(H25,'Léeme'!$B$13),'Léeme'!$B$14)) | R25: =IF(N25="","",MIN('Léeme'!$B$15,N25-'Léeme'!$B$16)) | S25: =IF(OR(E25="",Q25=""),"",IFERROR(IF(E25<=0,"",E25*(((1+Q25)/(1+N25))+((1+Q25)/(1+N25))^2+((1+Q25)/(1+N25))^3+((1+Q25)/(1+N25))^4+((1+Q25)/(1+N25))^5)+E25*(1+Q25)^5*(1+R25)/((N25-R25)*(1+N25)^5)),"")) | T25: =IF(OR(E25="",N25=""),"",IFERROR((C25*N25-E25)/(C25+E25),"")) | U25: =IF(OR(H25="",T25=""),"",IFERROR(MIN(MAX(H25,'Léeme'!$B$17),'Léeme'!$B$18)-T25,"")) | V25: =IF(OR(I25="",M25="",L25=""),"",IFERROR((I25/M25-J25-K25)/L25,"")) | W25: =IFERROR(P25/C25-1,"") | X25: =IFERROR(S25/C25-1,"") | Y25: =IFERROR(V25/C25-1,"") | Z25: =IF(OR(W25="",ISTEXT(W25)),"sin dato",IF(W25>='Léeme'!$B$19,"barato",IF(W25<=-'Léeme'!$B$19,"caro","medio"))) | AA25: =IF(OR(X25="",ISTEXT(X25)),"sin dato",IF(X25>='Léeme'!$B$19,"barato",IF(X25<=-'Léeme'!$B$19,"caro","medio"))) | AB25: =IF(OR(U25="",ISTEXT(U25)),"sin dato",IF(U25>='Léeme'!$B$20,"barato",IF(U25<=-'Léeme'!$B$20,"caro","medio"))) | AC25: =IF(OR(Y25="",ISTEXT(Y25)),"sin dato",IF(Y25>='Léeme'!$B$19,"barato",IF(Y25<=-'Léeme'!$B$19,"caro","medio")))
A26: 1998-T1 | B26: 35885 | C26: 17.625 | D26: 1.2 | E26: 1.4132 | F26: 0.0567 | G26: 0.021295688 | H26: 0.042080232 | N26: =IF(F26="","",F26+'Léeme'!$B$10) | O26: =IF(OR(G26="",N26=""),"",MIN(MAX(G26,'Léeme'!$B$11),'Léeme'!$B$12,N26-'Léeme'!$B$16)) | P26: =IF(OR(D26="",O26=""),"",IFERROR(IF(D26<=0,"",D26*(1+O26)/(N26-O26)),"")) | Q26: =IF(H26="","",MIN(MAX(H26,'Léeme'!$B$13),'Léeme'!$B$14)) | R26: =IF(N26="","",MIN('Léeme'!$B$15,N26-'Léeme'!$B$16)) | S26: =IF(OR(E26="",Q26=""),"",IFERROR(IF(E26<=0,"",E26*(((1+Q26)/(1+N26))+((1+Q26)/(1+N26))^2+((1+Q26)/(1+N26))^3+((1+Q26)/(1+N26))^4+((1+Q26)/(1+N26))^5)+E26*(1+Q26)^5*(1+R26)/((N26-R26)*(1+N26)^5)),"")) | T26: =IF(OR(E26="",N26=""),"",IFERROR((C26*N26-E26)/(C26+E26),"")) | U26: =IF(OR(H26="",T26=""),"",IFERROR(MIN(MAX(H26,'Léeme'!$B$17),'Léeme'!$B$18)-T26,"")) | V26: =IF(OR(I26="",M26="",L26=""),"",IFERROR((I26/M26-J26-K26)/L26,"")) | W26: =IFERROR(P26/C26-1,"") | X26: =IFERROR(S26/C26-1,"") | Y26: =IFERROR(V26/C26-1,"") | Z26: =IF(OR(W26="",ISTEXT(W26)),"sin dato",IF(W26>='Léeme'!$B$19,"barato",IF(W26<=-'Léeme'!$B$19,"caro","medio"))) | AA26: =IF(OR(X26="",ISTEXT(X26)),"sin dato",IF(X26>='Léeme'!$B$19,"barato",IF(X26<=-'Léeme'!$B$19,"caro","medio"))) | AB26: =IF(OR(U26="",ISTEXT(U26)),"sin dato",IF(U26>='Léeme'!$B$20,"barato",IF(U26<=-'Léeme'!$B$20,"caro","medio"))) | AC26: =IF(OR(Y26="",ISTEXT(Y26)),"sin dato",IF(Y26>='Léeme'!$B$19,"barato",IF(Y26<=-'Léeme'!$B$19,"caro","medio")))
A27: 1998-T2 | B27: 35976 | C27: 16.1875 | D27: 1.24 | E27: 1.4132 | F27: 0.0544 | G27: 0.028015318 | H27: 0.042080232 | N27: =IF(F27="","",F27+'Léeme'!$B$10) | O27: =IF(OR(G27="",N27=""),"",MIN(MAX(G27,'Léeme'!$B$11),'Léeme'!$B$12,N27-'Léeme'!$B$16)) | P27: =IF(OR(D27="",O27=""),"",IFERROR(IF(D27<=0,"",D27*(1+O27)/(N27-O27)),"")) | Q27: =IF(H27="","",MIN(MAX(H27,'Léeme'!$B$13),'Léeme'!$B$14)) | R27: =IF(N27="","",MIN('Léeme'!$B$15,N27-'Léeme'!$B$16)) | S27: =IF(OR(E27="",Q27=""),"",IFERROR(IF(E27<=0,"",E27*(((1+Q27)/(1+N27))+((1+Q27)/(1+N27))^2+((1+Q27)/(1+N27))^3+((1+Q27)/(1+N27))^4+((1+Q27)/(1+N27))^5)+E27*(1+Q27)^5*(1+R27)/((N27-R27)*(1+N27)^5)),"")) | T27: =IF(OR(E27="",N27=""),"",IFERROR((C27*N27-E27)/(C27+E27),"")) | U27: =IF(OR(H27="",T27=""),"",IFERROR(MIN(MAX(H27,'Léeme'!$B$17),'Léeme'!$B$18)-T27,"")) | V27: =IF(OR(I27="",M27="",L27=""),"",IFERROR((I27/M27-J27-K27)/L27,"")) | W27: =IFERROR(P27/C27-1,"") | X27: =IFERROR(S27/C27-1,"") | Y27: =IFERROR(V27/C27-1,"") | Z27: =IF(OR(W27="",ISTEXT(W27)),"sin dato",IF(W27>='Léeme'!$B$19,"barato",IF(W27<=-'Léeme'!$B$19,"caro","medio"))) | AA27: =IF(OR(X27="",ISTEXT(X27)),"sin dato",IF(X27>='Léeme'!$B$19,"barato",IF(X27<=-'Léeme'!$B$19,"caro","medio"))) | AB27: =IF(OR(U27="",ISTEXT(U27)),"sin dato",IF(U27>='Léeme'!$B$20,"barato",IF(U27<=-'Léeme'!$B$20,"caro","medio"))) | AC27: =IF(OR(Y27="",ISTEXT(Y27)),"sin dato",IF(Y27>='Léeme'!$B$19,"barato",IF(Y27<=-'Léeme'!$B$19,"caro","medio")))
A28: 1998-T3 | B28: 36068 | C28: 14.625 | D28: 1.24 | E28: 1.4132 | F28: 0.0444 | G28: 0.020565146 | H28: 0.042080232 | N28: =IF(F28="","",F28+'Léeme'!$B$10) | O28: =IF(OR(G28="",N28=""),"",MIN(MAX(G28,'Léeme'!$B$11),'Léeme'!$B$12,N28-'Léeme'!$B$16)) | P28: =IF(OR(D28="",O28=""),"",IFERROR(IF(D28<=0,"",D28*(1+O28)/(N28-O28)),"")) | Q28: =IF(H28="","",MIN(MAX(H28,'Léeme'!$B$13),'Léeme'!$B$14)) | R28: =IF(N28="","",MIN('Léeme'!$B$15,N28-'Léeme'!$B$16)) | S28: =IF(OR(E28="",Q28=""),"",IFERROR(IF(E28<=0,"",E28*(((1+Q28)/(1+N28))+((1+Q28)/(1+N28))^2+((1+Q28)/(1+N28))^3+((1+Q28)/(1+N28))^4+((1+Q28)/(1+N28))^5)+E28*(1+Q28)^5*(1+R28)/((N28-R28)*(1+N28)^5)),"")) | T28: =IF(OR(E28="",N28=""),"",IFERROR((C28*N28-E28)/(C28+E28),"")) | U28: =IF(OR(H28="",T28=""),"",IFERROR(MIN(MAX(H28,'Léeme'!$B$17),'Léeme'!$B$18)-T28,"")) | V28: =IF(OR(I28="",M28="",L28=""),"",IFERROR((I28/M28-J28-K28)/L28,"")) | W28: =IFERROR(P28/C28-1,"") | X28: =IFERROR(S28/C28-1,"") | Y28: =IFERROR(V28/C28-1,"") | Z28: =IF(OR(W28="",ISTEXT(W28)),"sin dato",IF(W28>='Léeme'!$B$19,"barato",IF(W28<=-'Léeme'!$B$19,"caro","medio"))) | AA28: =IF(OR(X28="",ISTEXT(X28)),"sin dato",IF(X28>='Léeme'!$B$19,"barato",IF(X28<=-'Léeme'!$B$19,"caro","medio"))) | AB28: =IF(OR(U28="",ISTEXT(U28)),"sin dato",IF(U28>='Léeme'!$B$20,"barato",IF(U28<=-'Léeme'!$B$20,"caro","medio"))) | AC28: =IF(OR(Y28="",ISTEXT(Y28)),"sin dato",IF(Y28>='Léeme'!$B$19,"barato",IF(Y28<=-'Léeme'!$B$19,"caro","medio")))
A29: 1998-T4 | B29: 36160 | C29: 13.25 | D29: 1.24 | E29: 1.4132 | F29: 0.0465 | G29: 0.020565146 | H29: 0.042080232 | N29: =IF(F29="","",F29+'Léeme'!$B$10) | O29: =IF(OR(G29="",N29=""),"",MIN(MAX(G29,'Léeme'!$B$11),'Léeme'!$B$12,N29-'Léeme'!$B$16)) | P29: =IF(OR(D29="",O29=""),"",IFERROR(IF(D29<=0,"",D29*(1+O29)/(N29-O29)),"")) | Q29: =IF(H29="","",MIN(MAX(H29,'Léeme'!$B$13),'Léeme'!$B$14)) | R29: =IF(N29="","",MIN('Léeme'!$B$15,N29-'Léeme'!$B$16)) | S29: =IF(OR(E29="",Q29=""),"",IFERROR(IF(E29<=0,"",E29*(((1+Q29)/(1+N29))+((1+Q29)/(1+N29))^2+((1+Q29)/(1+N29))^3+((1+Q29)/(1+N29))^4+((1+Q29)/(1+N29))^5)+E29*(1+Q29)^5*(1+R29)/((N29-R29)*(1+N29)^5)),"")) | T29: =IF(OR(E29="",N29=""),"",IFERROR((C29*N29-E29)/(C29+E29),"")) | U29: =IF(OR(H29="",T29=""),"",IFERROR(MIN(MAX(H29,'Léeme'!$B$17),'Léeme'!$B$18)-T29,"")) | V29: =IF(OR(I29="",M29="",L29=""),"",IFERROR((I29/M29-J29-K29)/L29,"")) | W29: =IFERROR(P29/C29-1,"") | X29: =IFERROR(S29/C29-1,"") | Y29: =IFERROR(V29/C29-1,"") | Z29: =IF(OR(W29="",ISTEXT(W29)),"sin dato",IF(W29>='Léeme'!$B$19,"barato",IF(W29<=-'Léeme'!$B$19,"caro","medio"))) | AA29: =IF(OR(X29="",ISTEXT(X29)),"sin dato",IF(X29>='Léeme'!$B$19,"barato",IF(X29<=-'Léeme'!$B$19,"caro","medio"))) | AB29: =IF(OR(U29="",ISTEXT(U29)),"sin dato",IF(U29>='Léeme'!$B$20,"barato",IF(U29<=-'Léeme'!$B$20,"caro","medio"))) | AC29: =IF(OR(Y29="",ISTEXT(Y29)),"sin dato",IF(Y29>='Léeme'!$B$19,"barato",IF(Y29<=-'Léeme'!$B$19,"caro","medio")))
A30: 1999-T1 | B30: 36250 | C30: 11.1875 | D30: 1.24 | E30: 1.4463 | F30: 0.0525 | G30: 0.020565146 | H30: 0.066138968 | N30: =IF(F30="","",F30+'Léeme'!$B$10) | O30: =IF(OR(G30="",N30=""),"",MIN(MAX(G30,'Léeme'!$B$11),'Léeme'!$B$12,N30-'Léeme'!$B$16)) | P30: =IF(OR(D30="",O30=""),"",IFERROR(IF(D30<=0,"",D30*(1+O30)/(N30-O30)),"")) | Q30: =IF(H30="","",MIN(MAX(H30,'Léeme'!$B$13),'Léeme'!$B$14)) | R30: =IF(N30="","",MIN('Léeme'!$B$15,N30-'Léeme'!$B$16)) | S30: =IF(OR(E30="",Q30=""),"",IFERROR(IF(E30<=0,"",E30*(((1+Q30)/(1+N30))+((1+Q30)/(1+N30))^2+((1+Q30)/(1+N30))^3+((1+Q30)/(1+N30))^4+((1+Q30)/(1+N30))^5)+E30*(1+Q30)^5*(1+R30)/((N30-R30)*(1+N30)^5)),"")) | T30: =IF(OR(E30="",N30=""),"",IFERROR((C30*N30-E30)/(C30+E30),"")) | U30: =IF(OR(H30="",T30=""),"",IFERROR(MIN(MAX(H30,'Léeme'!$B$17),'Léeme'!$B$18)-T30,"")) | V30: =IF(OR(I30="",M30="",L30=""),"",IFERROR((I30/M30-J30-K30)/L30,"")) | W30: =IFERROR(P30/C30-1,"") | X30: =IFERROR(S30/C30-1,"") | Y30: =IFERROR(V30/C30-1,"") | Z30: =IF(OR(W30="",ISTEXT(W30)),"sin dato",IF(W30>='Léeme'!$B$19,"barato",IF(W30<=-'Léeme'!$B$19,"caro","medio"))) | AA30: =IF(OR(X30="",ISTEXT(X30)),"sin dato",IF(X30>='Léeme'!$B$19,"barato",IF(X30<=-'Léeme'!$B$19,"caro","medio"))) | AB30: =IF(OR(U30="",ISTEXT(U30)),"sin dato",IF(U30>='Léeme'!$B$20,"barato",IF(U30<=-'Léeme'!$B$20,"caro","medio"))) | AC30: =IF(OR(Y30="",ISTEXT(Y30)),"sin dato",IF(Y30>='Léeme'!$B$19,"barato",IF(Y30<=-'Léeme'!$B$19,"caro","medio")))
A31: 1999-T2 | B31: 36341 | C31: 12.875 | D31: 1.24 | E31: 1.4463 | F31: 0.0581 | G31: 0.020565146 | H31: 0.066138968 | N31: =IF(F31="","",F31+'Léeme'!$B$10) | O31: =IF(OR(G31="",N31=""),"",MIN(MAX(G31,'Léeme'!$B$11),'Léeme'!$B$12,N31-'Léeme'!$B$16)) | P31: =IF(OR(D31="",O31=""),"",IFERROR(IF(D31<=0,"",D31*(1+O31)/(N31-O31)),"")) | Q31: =IF(H31="","",MIN(MAX(H31,'Léeme'!$B$13),'Léeme'!$B$14)) | R31: =IF(N31="","",MIN('Léeme'!$B$15,N31-'Léeme'!$B$16)) | S31: =IF(OR(E31="",Q31=""),"",IFERROR(IF(E31<=0,"",E31*(((1+Q31)/(1+N31))+((1+Q31)/(1+N31))^2+((1+Q31)/(1+N31))^3+((1+Q31)/(1+N31))^4+((1+Q31)/(1+N31))^5)+E31*(1+Q31)^5*(1+R31)/((N31-R31)*(1+N31)^5)),"")) | T31: =IF(OR(E31="",N31=""),"",IFERROR((C31*N31-E31)/(C31+E31),"")) | U31: =IF(OR(H31="",T31=""),"",IFERROR(MIN(MAX(H31,'Léeme'!$B$17),'Léeme'!$B$18)-T31,"")) | V31: =IF(OR(I31="",M31="",L31=""),"",IFERROR((I31/M31-J31-K31)/L31,"")) | W31: =IFERROR(P31/C31-1,"") | X31: =IFERROR(S31/C31-1,"") | Y31: =IFERROR(V31/C31-1,"") | Z31: =IF(OR(W31="",ISTEXT(W31)),"sin dato",IF(W31>='Léeme'!$B$19,"barato",IF(W31<=-'Léeme'!$B$19,"caro","medio"))) | AA31: =IF(OR(X31="",ISTEXT(X31)),"sin dato",IF(X31>='Léeme'!$B$19,"barato",IF(X31<=-'Léeme'!$B$19,"caro","medio"))) | AB31: =IF(OR(U31="",ISTEXT(U31)),"sin dato",IF(U31>='Léeme'!$B$20,"barato",IF(U31<=-'Léeme'!$B$20,"caro","medio"))) | AC31: =IF(OR(Y31="",ISTEXT(Y31)),"sin dato",IF(Y31>='Léeme'!$B$19,"barato",IF(Y31<=-'Léeme'!$B$19,"caro","medio")))
A32: 1999-T3 | B32: 36433 | C32: 10.625 | D32: 1.24 | E32: 1.4463 | F32: 0.059 | G32: 0.013427627 | H32: 0.066138968 | N32: =IF(F32="","",F32+'Léeme'!$B$10) | O32: =IF(OR(G32="",N32=""),"",MIN(MAX(G32,'Léeme'!$B$11),'Léeme'!$B$12,N32-'Léeme'!$B$16)) | P32: =IF(OR(D32="",O32=""),"",IFERROR(IF(D32<=0,"",D32*(1+O32)/(N32-O32)),"")) | Q32: =IF(H32="","",MIN(MAX(H32,'Léeme'!$B$13),'Léeme'!$B$14)) | R32: =IF(N32="","",MIN('Léeme'!$B$15,N32-'Léeme'!$B$16)) | S32: =IF(OR(E32="",Q32=""),"",IFERROR(IF(E32<=0,"",E32*(((1+Q32)/(1+N32))+((1+Q32)/(1+N32))^2+((1+Q32)/(1+N32))^3+((1+Q32)/(1+N32))^4+((1+Q32)/(1+N32))^5)+E32*(1+Q32)^5*(1+R32)/((N32-R32)*(1+N32)^5)),"")) | T32: =IF(OR(E32="",N32=""),"",IFERROR((C32*N32-E32)/(C32+E32),"")) | U32: =IF(OR(H32="",T32=""),"",IFERROR(MIN(MAX(H32,'Léeme'!$B$17),'Léeme'!$B$18)-T32,"")) | V32: =IF(OR(I32="",M32="",L32=""),"",IFERROR((I32/M32-J32-K32)/L32,"")) | W32: =IFERROR(P32/C32-1,"") | X32: =IFERROR(S32/C32-1,"") | Y32: =IFERROR(V32/C32-1,"") | Z32: =IF(OR(W32="",ISTEXT(W32)),"sin dato",IF(W32>='Léeme'!$B$19,"barato",IF(W32<=-'Léeme'!$B$19,"caro","medio"))) | AA32: =IF(OR(X32="",ISTEXT(X32)),"sin dato",IF(X32>='Léeme'!$B$19,"barato",IF(X32<=-'Léeme'!$B$19,"caro","medio"))) | AB32: =IF(OR(U32="",ISTEXT(U32)),"sin dato",IF(U32>='Léeme'!$B$20,"barato",IF(U32<=-'Léeme'!$B$20,"caro","medio"))) | AC32: =IF(OR(Y32="",ISTEXT(Y32)),"sin dato",IF(Y32>='Léeme'!$B$19,"barato",IF(Y32<=-'Léeme'!$B$19,"caro","medio")))
A33: 1999-T4 | B33: 36525 | C33: 9.9375 | D33: 1.24 | E33: 1.4463 | F33: 0.0645 | G33: 0.013427627 | H33: 0.066138968 | N33: =IF(F33="","",F33+'Léeme'!$B$10) | O33: =IF(OR(G33="",N33=""),"",MIN(MAX(G33,'Léeme'!$B$11),'Léeme'!$B$12,N33-'Léeme'!$B$16)) | P33: =IF(OR(D33="",O33=""),"",IFERROR(IF(D33<=0,"",D33*(1+O33)/(N33-O33)),"")) | Q33: =IF(H33="","",MIN(MAX(H33,'Léeme'!$B$13),'Léeme'!$B$14)) | R33: =IF(N33="","",MIN('Léeme'!$B$15,N33-'Léeme'!$B$16)) | S33: =IF(OR(E33="",Q33=""),"",IFERROR(IF(E33<=0,"",E33*(((1+Q33)/(1+N33))+((1+Q33)/(1+N33))^2+((1+Q33)/(1+N33))^3+((1+Q33)/(1+N33))^4+((1+Q33)/(1+N33))^5)+E33*(1+Q33)^5*(1+R33)/((N33-R33)*(1+N33)^5)),"")) | T33: =IF(OR(E33="",N33=""),"",IFERROR((C33*N33-E33)/(C33+E33),"")) | U33: =IF(OR(H33="",T33=""),"",IFERROR(MIN(MAX(H33,'Léeme'!$B$17),'Léeme'!$B$18)-T33,"")) | V33: =IF(OR(I33="",M33="",L33=""),"",IFERROR((I33/M33-J33-K33)/L33,"")) | W33: =IFERROR(P33/C33-1,"") | X33: =IFERROR(S33/C33-1,"") | Y33: =IFERROR(V33/C33-1,"") | Z33: =IF(OR(W33="",ISTEXT(W33)),"sin dato",IF(W33>='Léeme'!$B$19,"barato",IF(W33<=-'Léeme'!$B$19,"caro","medio"))) | AA33: =IF(OR(X33="",ISTEXT(X33)),"sin dato",IF(X33>='Léeme'!$B$19,"barato",IF(X33<=-'Léeme'!$B$19,"caro","medio"))) | AB33: =IF(OR(U33="",ISTEXT(U33)),"sin dato",IF(U33>='Léeme'!$B$20,"barato",IF(U33<=-'Léeme'!$B$20,"caro","medio"))) | AC33: =IF(OR(Y33="",ISTEXT(Y33)),"sin dato",IF(Y33>='Léeme'!$B$19,"barato",IF(Y33<=-'Léeme'!$B$19,"caro","medio"))) | AD33: 0.73611111
A34: 2000-T1 | B34: 36616 | C34: 10.4375 | D34: 1.24 | E34: 1.5142 | F34: 0.0603 | G34: 0.013427627 | H34: 0.054739111 | N34: =IF(F34="","",F34+'Léeme'!$B$10) | O34: =IF(OR(G34="",N34=""),"",MIN(MAX(G34,'Léeme'!$B$11),'Léeme'!$B$12,N34-'Léeme'!$B$16)) | P34: =IF(OR(D34="",O34=""),"",IFERROR(IF(D34<=0,"",D34*(1+O34)/(N34-O34)),"")) | Q34: =IF(H34="","",MIN(MAX(H34,'Léeme'!$B$13),'Léeme'!$B$14)) | R34: =IF(N34="","",MIN('Léeme'!$B$15,N34-'Léeme'!$B$16)) | S34: =IF(OR(E34="",Q34=""),"",IFERROR(IF(E34<=0,"",E34*(((1+Q34)/(1+N34))+((1+Q34)/(1+N34))^2+((1+Q34)/(1+N34))^3+((1+Q34)/(1+N34))^4+((1+Q34)/(1+N34))^5)+E34*(1+Q34)^5*(1+R34)/((N34-R34)*(1+N34)^5)),"")) | T34: =IF(OR(E34="",N34=""),"",IFERROR((C34*N34-E34)/(C34+E34),"")) | U34: =IF(OR(H34="",T34=""),"",IFERROR(MIN(MAX(H34,'Léeme'!$B$17),'Léeme'!$B$18)-T34,"")) | V34: =IF(OR(I34="",M34="",L34=""),"",IFERROR((I34/M34-J34-K34)/L34,"")) | W34: =IFERROR(P34/C34-1,"") | X34: =IFERROR(S34/C34-1,"") | Y34: =IFERROR(V34/C34-1,"") | Z34: =IF(OR(W34="",ISTEXT(W34)),"sin dato",IF(W34>='Léeme'!$B$19,"barato",IF(W34<=-'Léeme'!$B$19,"caro","medio"))) | AA34: =IF(OR(X34="",ISTEXT(X34)),"sin dato",IF(X34>='Léeme'!$B$19,"barato",IF(X34<=-'Léeme'!$B$19,"caro","medio"))) | AB34: =IF(OR(U34="",ISTEXT(U34)),"sin dato",IF(U34>='Léeme'!$B$20,"barato",IF(U34<=-'Léeme'!$B$20,"caro","medio"))) | AC34: =IF(OR(Y34="",ISTEXT(Y34)),"sin dato",IF(Y34>='Léeme'!$B$19,"barato",IF(Y34<=-'Léeme'!$B$19,"caro","medio"))) | AD34: 0.80769231
A35: 2000-T2 | B35: 36707 | C35: 10.515625 | D35: 1.24 | E35: 1.5142 | F35: 0.0603 | G35: 0.013427627 | H35: 0.054739111 | N35: =IF(F35="","",F35+'Léeme'!$B$10) | O35: =IF(OR(G35="",N35=""),"",MIN(MAX(G35,'Léeme'!$B$11),'Léeme'!$B$12,N35-'Léeme'!$B$16)) | P35: =IF(OR(D35="",O35=""),"",IFERROR(IF(D35<=0,"",D35*(1+O35)/(N35-O35)),"")) | Q35: =IF(H35="","",MIN(MAX(H35,'Léeme'!$B$13),'Léeme'!$B$14)) | R35: =IF(N35="","",MIN('Léeme'!$B$15,N35-'Léeme'!$B$16)) | S35: =IF(OR(E35="",Q35=""),"",IFERROR(IF(E35<=0,"",E35*(((1+Q35)/(1+N35))+((1+Q35)/(1+N35))^2+((1+Q35)/(1+N35))^3+((1+Q35)/(1+N35))^4+((1+Q35)/(1+N35))^5)+E35*(1+Q35)^5*(1+R35)/((N35-R35)*(1+N35)^5)),"")) | T35: =IF(OR(E35="",N35=""),"",IFERROR((C35*N35-E35)/(C35+E35),"")) | U35: =IF(OR(H35="",T35=""),"",IFERROR(MIN(MAX(H35,'Léeme'!$B$17),'Léeme'!$B$18)-T35,"")) | V35: =IF(OR(I35="",M35="",L35=""),"",IFERROR((I35/M35-J35-K35)/L35,"")) | W35: =IFERROR(P35/C35-1,"") | X35: =IFERROR(S35/C35-1,"") | Y35: =IFERROR(V35/C35-1,"") | Z35: =IF(OR(W35="",ISTEXT(W35)),"sin dato",IF(W35>='Léeme'!$B$19,"barato",IF(W35<=-'Léeme'!$B$19,"caro","medio"))) | AA35: =IF(OR(X35="",ISTEXT(X35)),"sin dato",IF(X35>='Léeme'!$B$19,"barato",IF(X35<=-'Léeme'!$B$19,"caro","medio"))) | AB35: =IF(OR(U35="",ISTEXT(U35)),"sin dato",IF(U35>='Léeme'!$B$20,"barato",IF(U35<=-'Léeme'!$B$20,"caro","medio"))) | AC35: =IF(OR(Y35="",ISTEXT(Y35)),"sin dato",IF(Y35>='Léeme'!$B$19,"barato",IF(Y35<=-'Léeme'!$B$19,"caro","medio"))) | AD35: 0.72619048
A36: 2000-T3 | B36: 36798 | C36: 10.375 | D36: 1.24 | E36: 1.5142 | F36: 0.058 | G36: 0.013427627 | H36: 0.054739111 | N36: =IF(F36="","",F36+'Léeme'!$B$10) | O36: =IF(OR(G36="",N36=""),"",MIN(MAX(G36,'Léeme'!$B$11),'Léeme'!$B$12,N36-'Léeme'!$B$16)) | P36: =IF(OR(D36="",O36=""),"",IFERROR(IF(D36<=0,"",D36*(1+O36)/(N36-O36)),"")) | Q36: =IF(H36="","",MIN(MAX(H36,'Léeme'!$B$13),'Léeme'!$B$14)) | R36: =IF(N36="","",MIN('Léeme'!$B$15,N36-'Léeme'!$B$16)) | S36: =IF(OR(E36="",Q36=""),"",IFERROR(IF(E36<=0,"",E36*(((1+Q36)/(1+N36))+((1+Q36)/(1+N36))^2+((1+Q36)/(1+N36))^3+((1+Q36)/(1+N36))^4+((1+Q36)/(1+N36))^5)+E36*(1+Q36)^5*(1+R36)/((N36-R36)*(1+N36)^5)),"")) | T36: =IF(OR(E36="",N36=""),"",IFERROR((C36*N36-E36)/(C36+E36),"")) | U36: =IF(OR(H36="",T36=""),"",IFERROR(MIN(MAX(H36,'Léeme'!$B$17),'Léeme'!$B$18)-T36,"")) | V36: =IF(OR(I36="",M36="",L36=""),"",IFERROR((I36/M36-J36-K36)/L36,"")) | W36: =IFERROR(P36/C36-1,"") | X36: =IFERROR(S36/C36-1,"") | Y36: =IFERROR(V36/C36-1,"") | Z36: =IF(OR(W36="",ISTEXT(W36)),"sin dato",IF(W36>='Léeme'!$B$19,"barato",IF(W36<=-'Léeme'!$B$19,"caro","medio"))) | AA36: =IF(OR(X36="",ISTEXT(X36)),"sin dato",IF(X36>='Léeme'!$B$19,"barato",IF(X36<=-'Léeme'!$B$19,"caro","medio"))) | AB36: =IF(OR(U36="",ISTEXT(U36)),"sin dato",IF(U36>='Léeme'!$B$20,"barato",IF(U36<=-'Léeme'!$B$20,"caro","medio"))) | AC36: =IF(OR(Y36="",ISTEXT(Y36)),"sin dato",IF(Y36>='Léeme'!$B$19,"barato",IF(Y36<=-'Léeme'!$B$19,"caro","medio"))) | AD36: 0.87777778
A37: 2000-T4 | B37: 36889 | C37: 10.1875 | D37: 1.26 | E37: 1.5142 | F37: 0.0512 | G37: 0.016675859 | H37: 0.054739111 | N37: =IF(F37="","",F37+'Léeme'!$B$10) | O37: =IF(OR(G37="",N37=""),"",MIN(MAX(G37,'Léeme'!$B$11),'Léeme'!$B$12,N37-'Léeme'!$B$16)) | P37: =IF(OR(D37="",O37=""),"",IFERROR(IF(D37<=0,"",D37*(1+O37)/(N37-O37)),"")) | Q37: =IF(H37="","",MIN(MAX(H37,'Léeme'!$B$13),'Léeme'!$B$14)) | R37: =IF(N37="","",MIN('Léeme'!$B$15,N37-'Léeme'!$B$16)) | S37: =IF(OR(E37="",Q37=""),"",IFERROR(IF(E37<=0,"",E37*(((1+Q37)/(1+N37))+((1+Q37)/(1+N37))^2+((1+Q37)/(1+N37))^3+((1+Q37)/(1+N37))^4+((1+Q37)/(1+N37))^5)+E37*(1+Q37)^5*(1+R37)/((N37-R37)*(1+N37)^5)),"")) | T37: =IF(OR(E37="",N37=""),"",IFERROR((C37*N37-E37)/(C37+E37),"")) | U37: =IF(OR(H37="",T37=""),"",IFERROR(MIN(MAX(H37,'Léeme'!$B$17),'Léeme'!$B$18)-T37,"")) | V37: =IF(OR(I37="",M37="",L37=""),"",IFERROR((I37/M37-J37-K37)/L37,"")) | W37: =IFERROR(P37/C37-1,"") | X37: =IFERROR(S37/C37-1,"") | Y37: =IFERROR(V37/C37-1,"") | Z37: =IF(OR(W37="",ISTEXT(W37)),"sin dato",IF(W37>='Léeme'!$B$19,"barato",IF(W37<=-'Léeme'!$B$19,"caro","medio"))) | AA37: =IF(OR(X37="",ISTEXT(X37)),"sin dato",IF(X37>='Léeme'!$B$19,"barato",IF(X37<=-'Léeme'!$B$19,"caro","medio"))) | AB37: =IF(OR(U37="",ISTEXT(U37)),"sin dato",IF(U37>='Léeme'!$B$20,"barato",IF(U37<=-'Léeme'!$B$20,"caro","medio"))) | AC37: =IF(OR(Y37="",ISTEXT(Y37)),"sin dato",IF(Y37>='Léeme'!$B$19,"barato",IF(Y37<=-'Léeme'!$B$19,"caro","medio"))) | AD37: 0.98958333
A38: 2001-T1 | B38: 36980 | C38: 11.8 | D38: 1.26 | E38: 1.4453 | F38: 0.0493 | G38: 0.016675859 | H38: 0.031115377 | N38: =IF(F38="","",F38+'Léeme'!$B$10) | O38: =IF(OR(G38="",N38=""),"",MIN(MAX(G38,'Léeme'!$B$11),'Léeme'!$B$12,N38-'Léeme'!$B$16)) | P38: =IF(OR(D38="",O38=""),"",IFERROR(IF(D38<=0,"",D38*(1+O38)/(N38-O38)),"")) | Q38: =IF(H38="","",MIN(MAX(H38,'Léeme'!$B$13),'Léeme'!$B$14)) | R38: =IF(N38="","",MIN('Léeme'!$B$15,N38-'Léeme'!$B$16)) | S38: =IF(OR(E38="",Q38=""),"",IFERROR(IF(E38<=0,"",E38*(((1+Q38)/(1+N38))+((1+Q38)/(1+N38))^2+((1+Q38)/(1+N38))^3+((1+Q38)/(1+N38))^4+((1+Q38)/(1+N38))^5)+E38*(1+Q38)^5*(1+R38)/((N38-R38)*(1+N38)^5)),"")) | T38: =IF(OR(E38="",N38=""),"",IFERROR((C38*N38-E38)/(C38+E38),"")) | U38: =IF(OR(H38="",T38=""),"",IFERROR(MIN(MAX(H38,'Léeme'!$B$17),'Léeme'!$B$18)-T38,"")) | V38: =IF(OR(I38="",M38="",L38=""),"",IFERROR((I38/M38-J38-K38)/L38,"")) | W38: =IFERROR(P38/C38-1,"") | X38: =IFERROR(S38/C38-1,"") | Y38: =IFERROR(V38/C38-1,"") | Z38: =IF(OR(W38="",ISTEXT(W38)),"sin dato",IF(W38>='Léeme'!$B$19,"barato",IF(W38<=-'Léeme'!$B$19,"caro","medio"))) | AA38: =IF(OR(X38="",ISTEXT(X38)),"sin dato",IF(X38>='Léeme'!$B$19,"barato",IF(X38<=-'Léeme'!$B$19,"caro","medio"))) | AB38: =IF(OR(U38="",ISTEXT(U38)),"sin dato",IF(U38>='Léeme'!$B$20,"barato",IF(U38<=-'Léeme'!$B$20,"caro","medio"))) | AC38: =IF(OR(Y38="",ISTEXT(Y38)),"sin dato",IF(Y38>='Léeme'!$B$19,"barato",IF(Y38<=-'Léeme'!$B$19,"caro","medio"))) | AD38: 0.89215686 | AE38: 0.41891892 | AF38: 0.28378378
A39: 2001-T2 | B39: 37071 | C39: 14.25 | D39: 1.26 | E39: 1.4453 | F39: 0.0542 | G39: 0.016675859 | H39: 0.031115377 | N39: =IF(F39="","",F39+'Léeme'!$B$10) | O39: =IF(OR(G39="",N39=""),"",MIN(MAX(G39,'Léeme'!$B$11),'Léeme'!$B$12,N39-'Léeme'!$B$16)) | P39: =IF(OR(D39="",O39=""),"",IFERROR(IF(D39<=0,"",D39*(1+O39)/(N39-O39)),"")) | Q39: =IF(H39="","",MIN(MAX(H39,'Léeme'!$B$13),'Léeme'!$B$14)) | R39: =IF(N39="","",MIN('Léeme'!$B$15,N39-'Léeme'!$B$16)) | S39: =IF(OR(E39="",Q39=""),"",IFERROR(IF(E39<=0,"",E39*(((1+Q39)/(1+N39))+((1+Q39)/(1+N39))^2+((1+Q39)/(1+N39))^3+((1+Q39)/(1+N39))^4+((1+Q39)/(1+N39))^5)+E39*(1+Q39)^5*(1+R39)/((N39-R39)*(1+N39)^5)),"")) | T39: =IF(OR(E39="",N39=""),"",IFERROR((C39*N39-E39)/(C39+E39),"")) | U39: =IF(OR(H39="",T39=""),"",IFERROR(MIN(MAX(H39,'Léeme'!$B$17),'Léeme'!$B$18)-T39,"")) | V39: =IF(OR(I39="",M39="",L39=""),"",IFERROR((I39/M39-J39-K39)/L39,"")) | W39: =IFERROR(P39/C39-1,"") | X39: =IFERROR(S39/C39-1,"") | Y39: =IFERROR(V39/C39-1,"") | Z39: =IF(OR(W39="",ISTEXT(W39)),"sin dato",IF(W39>='Léeme'!$B$19,"barato",IF(W39<=-'Léeme'!$B$19,"caro","medio"))) | AA39: =IF(OR(X39="",ISTEXT(X39)),"sin dato",IF(X39>='Léeme'!$B$19,"barato",IF(X39<=-'Léeme'!$B$19,"caro","medio"))) | AB39: =IF(OR(U39="",ISTEXT(U39)),"sin dato",IF(U39>='Léeme'!$B$20,"barato",IF(U39<=-'Léeme'!$B$20,"caro","medio"))) | AC39: =IF(OR(Y39="",ISTEXT(Y39)),"sin dato",IF(Y39>='Léeme'!$B$19,"barato",IF(Y39<=-'Léeme'!$B$19,"caro","medio"))) | AD39: 0.32407407 | AE39: 0.1375 | AF39: 0.1375
A40: 2001-T3 | B40: 37162 | C40: 13.25 | D40: 1.26 | E40: 1.4453 | F40: 0.046 | G40: 0.0098057977 | H40: 0.031115377 | N40: =IF(F40="","",F40+'Léeme'!$B$10) | O40: =IF(OR(G40="",N40=""),"",MIN(MAX(G40,'Léeme'!$B$11),'Léeme'!$B$12,N40-'Léeme'!$B$16)) | P40: =IF(OR(D40="",O40=""),"",IFERROR(IF(D40<=0,"",D40*(1+O40)/(N40-O40)),"")) | Q40: =IF(H40="","",MIN(MAX(H40,'Léeme'!$B$13),'Léeme'!$B$14)) | R40: =IF(N40="","",MIN('Léeme'!$B$15,N40-'Léeme'!$B$16)) | S40: =IF(OR(E40="",Q40=""),"",IFERROR(IF(E40<=0,"",E40*(((1+Q40)/(1+N40))+((1+Q40)/(1+N40))^2+((1+Q40)/(1+N40))^3+((1+Q40)/(1+N40))^4+((1+Q40)/(1+N40))^5)+E40*(1+Q40)^5*(1+R40)/((N40-R40)*(1+N40)^5)),"")) | T40: =IF(OR(E40="",N40=""),"",IFERROR((C40*N40-E40)/(C40+E40),"")) | U40: =IF(OR(H40="",T40=""),"",IFERROR(MIN(MAX(H40,'Léeme'!$B$17),'Léeme'!$B$18)-T40,"")) | V40: =IF(OR(I40="",M40="",L40=""),"",IFERROR((I40/M40-J40-K40)/L40,"")) | W40: =IFERROR(P40/C40-1,"") | X40: =IFERROR(S40/C40-1,"") | Y40: =IFERROR(V40/C40-1,"") | Z40: =IF(OR(W40="",ISTEXT(W40)),"sin dato",IF(W40>='Léeme'!$B$19,"barato",IF(W40<=-'Léeme'!$B$19,"caro","medio"))) | AA40: =IF(OR(X40="",ISTEXT(X40)),"sin dato",IF(X40>='Léeme'!$B$19,"barato",IF(X40<=-'Léeme'!$B$19,"caro","medio"))) | AB40: =IF(OR(U40="",ISTEXT(U40)),"sin dato",IF(U40>='Léeme'!$B$20,"barato",IF(U40<=-'Léeme'!$B$20,"caro","medio"))) | AC40: =IF(OR(Y40="",ISTEXT(Y40)),"sin dato",IF(Y40>='Léeme'!$B$19,"barato",IF(Y40<=-'Léeme'!$B$19,"caro","medio"))) | AD40: 0.46491228 | AE40: 0.40697674 | AF40: 0.24418605
A41: 2001-T4 | B41: 37256 | C41: 13 | D41: 1.26 | E41: 1.4453 | F41: 0.0507 | G41: 0.0098057977 | H41: 0.031115377 | N41: =IF(F41="","",F41+'Léeme'!$B$10) | O41: =IF(OR(G41="",N41=""),"",MIN(MAX(G41,'Léeme'!$B$11),'Léeme'!$B$12,N41-'Léeme'!$B$16)) | P41: =IF(OR(D41="",O41=""),"",IFERROR(IF(D41<=0,"",D41*(1+O41)/(N41-O41)),"")) | Q41: =IF(H41="","",MIN(MAX(H41,'Léeme'!$B$13),'Léeme'!$B$14)) | R41: =IF(N41="","",MIN('Léeme'!$B$15,N41-'Léeme'!$B$16)) | S41: =IF(OR(E41="",Q41=""),"",IFERROR(IF(E41<=0,"",E41*(((1+Q41)/(1+N41))+((1+Q41)/(1+N41))^2+((1+Q41)/(1+N41))^3+((1+Q41)/(1+N41))^4+((1+Q41)/(1+N41))^5)+E41*(1+Q41)^5*(1+R41)/((N41-R41)*(1+N41)^5)),"")) | T41: =IF(OR(E41="",N41=""),"",IFERROR((C41*N41-E41)/(C41+E41),"")) | U41: =IF(OR(H41="",T41=""),"",IFERROR(MIN(MAX(H41,'Léeme'!$B$17),'Léeme'!$B$18)-T41,"")) | V41: =IF(OR(I41="",M41="",L41=""),"",IFERROR((I41/M41-J41-K41)/L41,"")) | W41: =IFERROR(P41/C41-1,"") | X41: =IFERROR(S41/C41-1,"") | Y41: =IFERROR(V41/C41-1,"") | Z41: =IF(OR(W41="",ISTEXT(W41)),"sin dato",IF(W41>='Léeme'!$B$19,"barato",IF(W41<=-'Léeme'!$B$19,"caro","medio"))) | AA41: =IF(OR(X41="",ISTEXT(X41)),"sin dato",IF(X41>='Léeme'!$B$19,"barato",IF(X41<=-'Léeme'!$B$19,"caro","medio"))) | AB41: =IF(OR(U41="",ISTEXT(U41)),"sin dato",IF(U41>='Léeme'!$B$20,"barato",IF(U41<=-'Léeme'!$B$20,"caro","medio"))) | AC41: =IF(OR(Y41="",ISTEXT(Y41)),"sin dato",IF(Y41>='Léeme'!$B$19,"barato",IF(Y41<=-'Léeme'!$B$19,"caro","medio"))) | AD41: 0.34166667 | AE41: 0.22826087 | AF41: 0.20652174
A42: 2002-T1 | B42: 37343 | C42: 13.96 | D42: 1.26 | E42: 1.4067 | F42: 0.0542 | G42: 0.0098057977 | H42: 0.0097627319 | N42: =IF(F42="","",F42+'Léeme'!$B$10) | O42: =IF(OR(G42="",N42=""),"",MIN(MAX(G42,'Léeme'!$B$11),'Léeme'!$B$12,N42-'Léeme'!$B$16)) | P42: =IF(OR(D42="",O42=""),"",IFERROR(IF(D42<=0,"",D42*(1+O42)/(N42-O42)),"")) | Q42: =IF(H42="","",MIN(MAX(H42,'Léeme'!$B$13),'Léeme'!$B$14)) | R42: =IF(N42="","",MIN('Léeme'!$B$15,N42-'Léeme'!$B$16)) | S42: =IF(OR(E42="",Q42=""),"",IFERROR(IF(E42<=0,"",E42*(((1+Q42)/(1+N42))+((1+Q42)/(1+N42))^2+((1+Q42)/(1+N42))^3+((1+Q42)/(1+N42))^4+((1+Q42)/(1+N42))^5)+E42*(1+Q42)^5*(1+R42)/((N42-R42)*(1+N42)^5)),"")) | T42: =IF(OR(E42="",N42=""),"",IFERROR((C42*N42-E42)/(C42+E42),"")) | U42: =IF(OR(H42="",T42=""),"",IFERROR(MIN(MAX(H42,'Léeme'!$B$17),'Léeme'!$B$18)-T42,"")) | V42: =IF(OR(I42="",M42="",L42=""),"",IFERROR((I42/M42-J42-K42)/L42,"")) | W42: =IFERROR(P42/C42-1,"") | X42: =IFERROR(S42/C42-1,"") | Y42: =IFERROR(V42/C42-1,"") | Z42: =IF(OR(W42="",ISTEXT(W42)),"sin dato",IF(W42>='Léeme'!$B$19,"barato",IF(W42<=-'Léeme'!$B$19,"caro","medio"))) | AA42: =IF(OR(X42="",ISTEXT(X42)),"sin dato",IF(X42>='Léeme'!$B$19,"barato",IF(X42<=-'Léeme'!$B$19,"caro","medio"))) | AB42: =IF(OR(U42="",ISTEXT(U42)),"sin dato",IF(U42>='Léeme'!$B$20,"barato",IF(U42<=-'Léeme'!$B$20,"caro","medio"))) | AC42: =IF(OR(Y42="",ISTEXT(Y42)),"sin dato",IF(Y42>='Léeme'!$B$19,"barato",IF(Y42<=-'Léeme'!$B$19,"caro","medio"))) | AD42: 0.24603175 | AE42: 0.091836735 | AF42: 0.010204082
A43: 2002-T2 | B43: 37435 | C43: 16 | D43: 1.26 | E43: 1.4067 | F43: 0.0486 | G43: 0.0098057977 | H43: 0.0097627319 | N43: =IF(F43="","",F43+'Léeme'!$B$10) | O43: =IF(OR(G43="",N43=""),"",MIN(MAX(G43,'Léeme'!$B$11),'Léeme'!$B$12,N43-'Léeme'!$B$16)) | P43: =IF(OR(D43="",O43=""),"",IFERROR(IF(D43<=0,"",D43*(1+O43)/(N43-O43)),"")) | Q43: =IF(H43="","",MIN(MAX(H43,'Léeme'!$B$13),'Léeme'!$B$14)) | R43: =IF(N43="","",MIN('Léeme'!$B$15,N43-'Léeme'!$B$16)) | S43: =IF(OR(E43="",Q43=""),"",IFERROR(IF(E43<=0,"",E43*(((1+Q43)/(1+N43))+((1+Q43)/(1+N43))^2+((1+Q43)/(1+N43))^3+((1+Q43)/(1+N43))^4+((1+Q43)/(1+N43))^5)+E43*(1+Q43)^5*(1+R43)/((N43-R43)*(1+N43)^5)),"")) | T43: =IF(OR(E43="",N43=""),"",IFERROR((C43*N43-E43)/(C43+E43),"")) | U43: =IF(OR(H43="",T43=""),"",IFERROR(MIN(MAX(H43,'Léeme'!$B$17),'Léeme'!$B$18)-T43,"")) | V43: =IF(OR(I43="",M43="",L43=""),"",IFERROR((I43/M43-J43-K43)/L43,"")) | W43: =IFERROR(P43/C43-1,"") | X43: =IFERROR(S43/C43-1,"") | Y43: =IFERROR(V43/C43-1,"") | Z43: =IF(OR(W43="",ISTEXT(W43)),"sin dato",IF(W43>='Léeme'!$B$19,"barato",IF(W43<=-'Léeme'!$B$19,"caro","medio"))) | AA43: =IF(OR(X43="",ISTEXT(X43)),"sin dato",IF(X43>='Léeme'!$B$19,"barato",IF(X43<=-'Léeme'!$B$19,"caro","medio"))) | AB43: =IF(OR(U43="",ISTEXT(U43)),"sin dato",IF(U43>='Léeme'!$B$20,"barato",IF(U43<=-'Léeme'!$B$20,"caro","medio"))) | AC43: =IF(OR(Y43="",ISTEXT(Y43)),"sin dato",IF(Y43>='Léeme'!$B$19,"barato",IF(Y43<=-'Léeme'!$B$19,"caro","medio"))) | AD43: 0.23484848 | AE43: 0.048076923 | AF43: 0.0096153846
A44: 2002-T3 | B44: 37529 | C44: 16.120001 | D44: 1.28 | E44: 1.4067 | F44: 0.0363 | G44: 0.012991368 | H44: 0.0097627319 | N44: =IF(F44="","",F44+'Léeme'!$B$10) | O44: =IF(OR(G44="",N44=""),"",MIN(MAX(G44,'Léeme'!$B$11),'Léeme'!$B$12,N44-'Léeme'!$B$16)) | P44: =IF(OR(D44="",O44=""),"",IFERROR(IF(D44<=0,"",D44*(1+O44)/(N44-O44)),"")) | Q44: =IF(H44="","",MIN(MAX(H44,'Léeme'!$B$13),'Léeme'!$B$14)) | R44: =IF(N44="","",MIN('Léeme'!$B$15,N44-'Léeme'!$B$16)) | S44: =IF(OR(E44="",Q44=""),"",IFERROR(IF(E44<=0,"",E44*(((1+Q44)/(1+N44))+((1+Q44)/(1+N44))^2+((1+Q44)/(1+N44))^3+((1+Q44)/(1+N44))^4+((1+Q44)/(1+N44))^5)+E44*(1+Q44)^5*(1+R44)/((N44-R44)*(1+N44)^5)),"")) | T44: =IF(OR(E44="",N44=""),"",IFERROR((C44*N44-E44)/(C44+E44),"")) | U44: =IF(OR(H44="",T44=""),"",IFERROR(MIN(MAX(H44,'Léeme'!$B$17),'Léeme'!$B$18)-T44,"")) | V44: =IF(OR(I44="",M44="",L44=""),"",IFERROR((I44/M44-J44-K44)/L44,"")) | W44: =IFERROR(P44/C44-1,"") | X44: =IFERROR(S44/C44-1,"") | Y44: =IFERROR(V44/C44-1,"") | Z44: =IF(OR(W44="",ISTEXT(W44)),"sin dato",IF(W44>='Léeme'!$B$19,"barato",IF(W44<=-'Léeme'!$B$19,"caro","medio"))) | AA44: =IF(OR(X44="",ISTEXT(X44)),"sin dato",IF(X44>='Léeme'!$B$19,"barato",IF(X44<=-'Léeme'!$B$19,"caro","medio"))) | AB44: =IF(OR(U44="",ISTEXT(U44)),"sin dato",IF(U44>='Léeme'!$B$20,"barato",IF(U44<=-'Léeme'!$B$20,"caro","medio"))) | AC44: =IF(OR(Y44="",ISTEXT(Y44)),"sin dato",IF(Y44>='Léeme'!$B$19,"barato",IF(Y44<=-'Léeme'!$B$19,"caro","medio"))) | AD44: 0.63043478 | AE44: 0.22727273 | AF44: 0.11818182
A45: 2002-T4 | B45: 37621 | C45: 15.33 | D45: 1.28 | E45: 1.4067 | F45: 0.0383 | G45: 0.012991368 | H45: 0.0097627319 | N45: =IF(F45="","",F45+'Léeme'!$B$10) | O45: =IF(OR(G45="",N45=""),"",MIN(MAX(G45,'Léeme'!$B$11),'Léeme'!$B$12,N45-'Léeme'!$B$16)) | P45: =IF(OR(D45="",O45=""),"",IFERROR(IF(D45<=0,"",D45*(1+O45)/(N45-O45)),"")) | Q45: =IF(H45="","",MIN(MAX(H45,'Léeme'!$B$13),'Léeme'!$B$14)) | R45: =IF(N45="","",MIN('Léeme'!$B$15,N45-'Léeme'!$B$16)) | S45: =IF(OR(E45="",Q45=""),"",IFERROR(IF(E45<=0,"",E45*(((1+Q45)/(1+N45))+((1+Q45)/(1+N45))^2+((1+Q45)/(1+N45))^3+((1+Q45)/(1+N45))^4+((1+Q45)/(1+N45))^5)+E45*(1+Q45)^5*(1+R45)/((N45-R45)*(1+N45)^5)),"")) | T45: =IF(OR(E45="",N45=""),"",IFERROR((C45*N45-E45)/(C45+E45),"")) | U45: =IF(OR(H45="",T45=""),"",IFERROR(MIN(MAX(H45,'Léeme'!$B$17),'Léeme'!$B$18)-T45,"")) | V45: =IF(OR(I45="",M45="",L45=""),"",IFERROR((I45/M45-J45-K45)/L45,"")) | W45: =IFERROR(P45/C45-1,"") | X45: =IFERROR(S45/C45-1,"") | Y45: =IFERROR(V45/C45-1,"") | Z45: =IF(OR(W45="",ISTEXT(W45)),"sin dato",IF(W45>='Léeme'!$B$19,"barato",IF(W45<=-'Léeme'!$B$19,"caro","medio"))) | AA45: =IF(OR(X45="",ISTEXT(X45)),"sin dato",IF(X45>='Léeme'!$B$19,"barato",IF(X45<=-'Léeme'!$B$19,"caro","medio"))) | AB45: =IF(OR(U45="",ISTEXT(U45)),"sin dato",IF(U45>='Léeme'!$B$20,"barato",IF(U45<=-'Léeme'!$B$20,"caro","medio"))) | AC45: =IF(OR(Y45="",ISTEXT(Y45)),"sin dato",IF(Y45>='Léeme'!$B$19,"barato",IF(Y45<=-'Léeme'!$B$19,"caro","medio"))) | AD45: 0.67361111 | AE45: 0.26724138 | AF45: 0.1637931
A46: 2003-T1 | B46: 37711 | C46: 15.1 | D46: 1.28 | E46: 1.43 | F46: 0.0383 | G46: 0.012991368 | H46: 0.002366357 | N46: =IF(F46="","",F46+'Léeme'!$B$10) | O46: =IF(OR(G46="",N46=""),"",MIN(MAX(G46,'Léeme'!$B$11),'Léeme'!$B$12,N46-'Léeme'!$B$16)) | P46: =IF(OR(D46="",O46=""),"",IFERROR(IF(D46<=0,"",D46*(1+O46)/(N46-O46)),"")) | Q46: =IF(H46="","",MIN(MAX(H46,'Léeme'!$B$13),'Léeme'!$B$14)) | R46: =IF(N46="","",MIN('Léeme'!$B$15,N46-'Léeme'!$B$16)) | S46: =IF(OR(E46="",Q46=""),"",IFERROR(IF(E46<=0,"",E46*(((1+Q46)/(1+N46))+((1+Q46)/(1+N46))^2+((1+Q46)/(1+N46))^3+((1+Q46)/(1+N46))^4+((1+Q46)/(1+N46))^5)+E46*(1+Q46)^5*(1+R46)/((N46-R46)*(1+N46)^5)),"")) | T46: =IF(OR(E46="",N46=""),"",IFERROR((C46*N46-E46)/(C46+E46),"")) | U46: =IF(OR(H46="",T46=""),"",IFERROR(MIN(MAX(H46,'Léeme'!$B$17),'Léeme'!$B$18)-T46,"")) | V46: =IF(OR(I46="",M46="",L46=""),"",IFERROR((I46/M46-J46-K46)/L46,"")) | W46: =IFERROR(P46/C46-1,"") | X46: =IFERROR(S46/C46-1,"") | Y46: =IFERROR(V46/C46-1,"") | Z46: =IF(OR(W46="",ISTEXT(W46)),"sin dato",IF(W46>='Léeme'!$B$19,"barato",IF(W46<=-'Léeme'!$B$19,"caro","medio"))) | AA46: =IF(OR(X46="",ISTEXT(X46)),"sin dato",IF(X46>='Léeme'!$B$19,"barato",IF(X46<=-'Léeme'!$B$19,"caro","medio"))) | AB46: =IF(OR(U46="",ISTEXT(U46)),"sin dato",IF(U46>='Léeme'!$B$20,"barato",IF(U46<=-'Léeme'!$B$20,"caro","medio"))) | AC46: =IF(OR(Y46="",ISTEXT(Y46)),"sin dato",IF(Y46>='Léeme'!$B$19,"barato",IF(Y46<=-'Léeme'!$B$19,"caro","medio"))) | AD46: 0.71333333 | AE46: 0.2704918 | AF46: 0.10655738
A47: 2003-T2 | B47: 37802 | C47: 17.24 | D47: 1.28 | E47: 1.43 | F47: 0.0354 | G47: 0.006369942 | H47: 0.002366357 | N47: =IF(F47="","",F47+'Léeme'!$B$10) | O47: =IF(OR(G47="",N47=""),"",MIN(MAX(G47,'Léeme'!$B$11),'Léeme'!$B$12,N47-'Léeme'!$B$16)) | P47: =IF(OR(D47="",O47=""),"",IFERROR(IF(D47<=0,"",D47*(1+O47)/(N47-O47)),"")) | Q47: =IF(H47="","",MIN(MAX(H47,'Léeme'!$B$13),'Léeme'!$B$14)) | R47: =IF(N47="","",MIN('Léeme'!$B$15,N47-'Léeme'!$B$16)) | S47: =IF(OR(E47="",Q47=""),"",IFERROR(IF(E47<=0,"",E47*(((1+Q47)/(1+N47))+((1+Q47)/(1+N47))^2+((1+Q47)/(1+N47))^3+((1+Q47)/(1+N47))^4+((1+Q47)/(1+N47))^5)+E47*(1+Q47)^5*(1+R47)/((N47-R47)*(1+N47)^5)),"")) | T47: =IF(OR(E47="",N47=""),"",IFERROR((C47*N47-E47)/(C47+E47),"")) | U47: =IF(OR(H47="",T47=""),"",IFERROR(MIN(MAX(H47,'Léeme'!$B$17),'Léeme'!$B$18)-T47,"")) | V47: =IF(OR(I47="",M47="",L47=""),"",IFERROR((I47/M47-J47-K47)/L47,"")) | W47: =IFERROR(P47/C47-1,"") | X47: =IFERROR(S47/C47-1,"") | Y47: =IFERROR(V47/C47-1,"") | Z47: =IF(OR(W47="",ISTEXT(W47)),"sin dato",IF(W47>='Léeme'!$B$19,"barato",IF(W47<=-'Léeme'!$B$19,"caro","medio"))) | AA47: =IF(OR(X47="",ISTEXT(X47)),"sin dato",IF(X47>='Léeme'!$B$19,"barato",IF(X47<=-'Léeme'!$B$19,"caro","medio"))) | AB47: =IF(OR(U47="",ISTEXT(U47)),"sin dato",IF(U47>='Léeme'!$B$20,"barato",IF(U47<=-'Léeme'!$B$20,"caro","medio"))) | AC47: =IF(OR(Y47="",ISTEXT(Y47)),"sin dato",IF(Y47>='Léeme'!$B$19,"barato",IF(Y47<=-'Léeme'!$B$19,"caro","medio"))) | AD47: 0.26282051 | AE47: 0.2265625 | AF47: 0.0234375
A48: 2003-T3 | B48: 37894 | C48: 17.030001 | D48: 1.28 | E48: 1.43 | F48: 0.0396 | G48: 0.006369942 | H48: 0.002366357 | N48: =IF(F48="","",F48+'Léeme'!$B$10) | O48: =IF(OR(G48="",N48=""),"",MIN(MAX(G48,'Léeme'!$B$11),'Léeme'!$B$12,N48-'Léeme'!$B$16)) | P48: =IF(OR(D48="",O48=""),"",IFERROR(IF(D48<=0,"",D48*(1+O48)/(N48-O48)),"")) | Q48: =IF(H48="","",MIN(MAX(H48,'Léeme'!$B$13),'Léeme'!$B$14)) | R48: =IF(N48="","",MIN('Léeme'!$B$15,N48-'Léeme'!$B$16)) | S48: =IF(OR(E48="",Q48=""),"",IFERROR(IF(E48<=0,"",E48*(((1+Q48)/(1+N48))+((1+Q48)/(1+N48))^2+((1+Q48)/(1+N48))^3+((1+Q48)/(1+N48))^4+((1+Q48)/(1+N48))^5)+E48*(1+Q48)^5*(1+R48)/((N48-R48)*(1+N48)^5)),"")) | T48: =IF(OR(E48="",N48=""),"",IFERROR((C48*N48-E48)/(C48+E48),"")) | U48: =IF(OR(H48="",T48=""),"",IFERROR(MIN(MAX(H48,'Léeme'!$B$17),'Léeme'!$B$18)-T48,"")) | V48: =IF(OR(I48="",M48="",L48=""),"",IFERROR((I48/M48-J48-K48)/L48,"")) | W48: =IFERROR(P48/C48-1,"") | X48: =IFERROR(S48/C48-1,"") | Y48: =IFERROR(V48/C48-1,"") | Z48: =IF(OR(W48="",ISTEXT(W48)),"sin dato",IF(W48>='Léeme'!$B$19,"barato",IF(W48<=-'Léeme'!$B$19,"caro","medio"))) | AA48: =IF(OR(X48="",ISTEXT(X48)),"sin dato",IF(X48>='Léeme'!$B$19,"barato",IF(X48<=-'Léeme'!$B$19,"caro","medio"))) | AB48: =IF(OR(U48="",ISTEXT(U48)),"sin dato",IF(U48>='Léeme'!$B$20,"barato",IF(U48<=-'Léeme'!$B$20,"caro","medio"))) | AC48: =IF(OR(Y48="",ISTEXT(Y48)),"sin dato",IF(Y48>='Léeme'!$B$19,"barato",IF(Y48<=-'Léeme'!$B$19,"caro","medio"))) | AD48: 0.25308642 | AE48: 0.18656716 | AF48: 0.037313433
A49: 2003-T4 | B49: 37986 | C49: 17.799999 | D49: 1.28 | E49: 1.43 | F49: 0.0427 | G49: 0.006369942 | H49: 0.002366357 | N49: =IF(F49="","",F49+'Léeme'!$B$10) | O49: =IF(OR(G49="",N49=""),"",MIN(MAX(G49,'Léeme'!$B$11),'Léeme'!$B$12,N49-'Léeme'!$B$16)) | P49: =IF(OR(D49="",O49=""),"",IFERROR(IF(D49<=0,"",D49*(1+O49)/(N49-O49)),"")) | Q49: =IF(H49="","",MIN(MAX(H49,'Léeme'!$B$13),'Léeme'!$B$14)) | R49: =IF(N49="","",MIN('Léeme'!$B$15,N49-'Léeme'!$B$16)) | S49: =IF(OR(E49="",Q49=""),"",IFERROR(IF(E49<=0,"",E49*(((1+Q49)/(1+N49))+((1+Q49)/(1+N49))^2+((1+Q49)/(1+N49))^3+((1+Q49)/(1+N49))^4+((1+Q49)/(1+N49))^5)+E49*(1+Q49)^5*(1+R49)/((N49-R49)*(1+N49)^5)),"")) | T49: =IF(OR(E49="",N49=""),"",IFERROR((C49*N49-E49)/(C49+E49),"")) | U49: =IF(OR(H49="",T49=""),"",IFERROR(MIN(MAX(H49,'Léeme'!$B$17),'Léeme'!$B$18)-T49,"")) | V49: =IF(OR(I49="",M49="",L49=""),"",IFERROR((I49/M49-J49-K49)/L49,"")) | W49: =IFERROR(P49/C49-1,"") | X49: =IFERROR(S49/C49-1,"") | Y49: =IFERROR(V49/C49-1,"") | Z49: =IF(OR(W49="",ISTEXT(W49)),"sin dato",IF(W49>='Léeme'!$B$19,"barato",IF(W49<=-'Léeme'!$B$19,"caro","medio"))) | AA49: =IF(OR(X49="",ISTEXT(X49)),"sin dato",IF(X49>='Léeme'!$B$19,"barato",IF(X49<=-'Léeme'!$B$19,"caro","medio"))) | AB49: =IF(OR(U49="",ISTEXT(U49)),"sin dato",IF(U49>='Léeme'!$B$20,"barato",IF(U49<=-'Léeme'!$B$20,"caro","medio"))) | AC49: =IF(OR(Y49="",ISTEXT(Y49)),"sin dato",IF(Y49>='Léeme'!$B$19,"barato",IF(Y49<=-'Léeme'!$B$19,"caro","medio"))) | AD49: 0.13690476 | AE49: 0.05 | AF49: 0.035714286
... A89: 2013-T4 | B89: 41639 | C89: 30.33 | D89: 1.62 | E89: 1.77 | F89: 0.0304 | G89: 0.015511278 | H89: -0.010931588 | N89: =IF(F89="","",F89+'Léeme'!$B$10) | O89: =IF(OR(G89="",N89=""),"",MIN(MAX(G89,'Léeme'!$B$11),'Léeme'!$B$12,N89-'Léeme'!$B$16)) | P89: =IF(OR(D89="",O89=""),"",IFERROR(IF(D89<=0,"",D89*(1+O89)/(N89-O89)),"")) | Q89: =IF(H89="","",MIN(MAX(H89,'Léeme'!$B$13),'Léeme'!$B$14)) | R89: =IF(N89="","",MIN('Léeme'!$B$15,N89-'Léeme'!$B$16)) | S89: =IF(OR(E89="",Q89=""),"",IFERROR(IF(E89<=0,"",E89*(((1+Q89)/(1+N89))+((1+Q89)/(1+N89))^2+((1+Q89)/(1+N89))^3+((1+Q89)/(1+N89))^4+((1+Q89)/(1+N89))^5)+E89*(1+Q89)^5*(1+R89)/((N89-R89)*(1+N89)^5)),"")) | T89: =IF(OR(E89="",N89=""),"",IFERROR((C89*N89-E89)/(C89+E89),"")) | U89: =IF(OR(H89="",T89=""),"",IFERROR(MIN(MAX(H89,'Léeme'!$B$17),'Léeme'!$B$18)-T89,"")) | V89: =IF(OR(I89="",M89="",L89=""),"",IFERROR((I89/M89-J89-K89)/L89,"")) | W89: =IFERROR(P89/C89-1,"") | X89: =IFERROR(S89/C89-1,"") | Y89: =IFERROR(V89/C89-1,"") | Z89: =IF(OR(W89="",ISTEXT(W89)),"sin dato",IF(W89>='Léeme'!$B$19,"barato",IF(W89<=-'Léeme'!$B$19,"caro","medio"))) | AA89: =IF(OR(X89="",ISTEXT(X89)),"sin dato",IF(X89>='Léeme'!$B$19,"barato",IF(X89<=-'Léeme'!$B$19,"caro","medio"))) | AB89: =IF(OR(U89="",ISTEXT(U89)),"sin dato",IF(U89>='Léeme'!$B$20,"barato",IF(U89<=-'Léeme'!$B$20,"caro","medio"))) | AC89: =IF(OR(Y89="",ISTEXT(Y89)),"sin dato",IF(Y89>='Léeme'!$B$19,"barato",IF(Y89<=-'Léeme'!$B$19,"caro","medio"))) | AD89: 0.37009804 | AE89: 0.19736842 | AF89: 0.097368421
A90: 2014-T1 | B90: 41729 | C90: 34.32 | D90: 1.62 | E90: 1.91 | F90: 0.0273 | G90: 0.015511278 | H90: -0.0081726997 | I90: 387836000 | J90: 1568574000 | K90: 0 | L90: 111554997 | M90: 0.078 | N90: =IF(F90="","",F90+'Léeme'!$B$10) | O90: =IF(OR(G90="",N90=""),"",MIN(MAX(G90,'Léeme'!$B$11),'Léeme'!$B$12,N90-'Léeme'!$B$16)) | P90: =IF(OR(D90="",O90=""),"",IFERROR(IF(D90<=0,"",D90*(1+O90)/(N90-O90)),"")) | Q90: =IF(H90="","",MIN(MAX(H90,'Léeme'!$B$13),'Léeme'!$B$14)) | R90: =IF(N90="","",MIN('Léeme'!$B$15,N90-'Léeme'!$B$16)) | S90: =IF(OR(E90="",Q90=""),"",IFERROR(IF(E90<=0,"",E90*(((1+Q90)/(1+N90))+((1+Q90)/(1+N90))^2+((1+Q90)/(1+N90))^3+((1+Q90)/(1+N90))^4+((1+Q90)/(1+N90))^5)+E90*(1+Q90)^5*(1+R90)/((N90-R90)*(1+N90)^5)),"")) | T90: =IF(OR(E90="",N90=""),"",IFERROR((C90*N90-E90)/(C90+E90),"")) | U90: =IF(OR(H90="",T90=""),"",IFERROR(MIN(MAX(H90,'Léeme'!$B$17),'Léeme'!$B$18)-T90,"")) | V90: =IF(OR(I90="",M90="",L90=""),"",IFERROR((I90/M90-J90-K90)/L90,"")) | W90: =IFERROR(P90/C90-1,"") | X90: =IFERROR(S90/C90-1,"") | Y90: =IFERROR(V90/C90-1,"") | Z90: =IF(OR(W90="",ISTEXT(W90)),"sin dato",IF(W90>='Léeme'!$B$19,"barato",IF(W90<=-'Léeme'!$B$19,"caro","medio"))) | AA90: =IF(OR(X90="",ISTEXT(X90)),"sin dato",IF(X90>='Léeme'!$B$19,"barato",IF(X90<=-'Léeme'!$B$19,"caro","medio"))) | AB90: =IF(OR(U90="",ISTEXT(U90)),"sin dato",IF(U90>='Léeme'!$B$20,"barato",IF(U90<=-'Léeme'!$B$20,"caro","medio"))) | AC90: =IF(OR(Y90="",ISTEXT(Y90)),"sin dato",IF(Y90>='Léeme'!$B$19,"barato",IF(Y90<=-'Léeme'!$B$19,"caro","medio"))) | AD90: 0.30676329 | AE90: 0.24093264 | AF90: 0.16839378
A91: 2014-T2 | B91: 41820 | C91: 37.189999 | D91: 1.62 | E91: 1.91 | F91: 0.0253 | G91: 0.015511278 | H91: -0.0081726997 | I91: 396680000 | J91: 1609241000 | K91: 0 | L91: 122971965 | M91: 0.078 | N91: =IF(F91="","",F91+'Léeme'!$B$10) | O91: =IF(OR(G91="",N91=""),"",MIN(MAX(G91,'Léeme'!$B$11),'Léeme'!$B$12,N91-'Léeme'!$B$16)) | P91: =IF(OR(D91="",O91=""),"",IFERROR(IF(D91<=0,"",D91*(1+O91)/(N91-O91)),"")) | Q91: =IF(H91="","",MIN(MAX(H91,'Léeme'!$B$13),'Léeme'!$B$14)) | R91: =IF(N91="","",MIN('Léeme'!$B$15,N91-'Léeme'!$B$16)) | S91: =IF(OR(E91="",Q91=""),"",IFERROR(IF(E91<=0,"",E91*(((1+Q91)/(1+N91))+((1+Q91)/(1+N91))^2+((1+Q91)/(1+N91))^3+((1+Q91)/(1+N91))^4+((1+Q91)/(1+N91))^5)+E91*(1+Q91)^5*(1+R91)/((N91-R91)*(1+N91)^5)),"")) | T91: =IF(OR(E91="",N91=""),"",IFERROR((C91*N91-E91)/(C91+E91),"")) | U91: =IF(OR(H91="",T91=""),"",IFERROR(MIN(MAX(H91,'Léeme'!$B$17),'Léeme'!$B$18)-T91,"")) | V91: =IF(OR(I91="",M91="",L91=""),"",IFERROR((I91/M91-J91-K91)/L91,"")) | W91: =IFERROR(P91/C91-1,"") | X91: =IFERROR(S91/C91-1,"") | Y91: =IFERROR(V91/C91-1,"") | Z91: =IF(OR(W91="",ISTEXT(W91)),"sin dato",IF(W91>='Léeme'!$B$19,"barato",IF(W91<=-'Léeme'!$B$19,"caro","medio"))) | AA91: =IF(OR(X91="",ISTEXT(X91)),"sin dato",IF(X91>='Léeme'!$B$19,"barato",IF(X91<=-'Léeme'!$B$19,"caro","medio"))) | AB91: =IF(OR(U91="",ISTEXT(U91)),"sin dato",IF(U91>='Léeme'!$B$20,"barato",IF(U91<=-'Léeme'!$B$20,"caro","medio"))) | AC91: =IF(OR(Y91="",ISTEXT(Y91)),"sin dato",IF(Y91>='Léeme'!$B$19,"barato",IF(Y91<=-'Léeme'!$B$19,"caro","medio"))) | AD91: 0.2547619 | AE91: 0.21683673 | AF91: 0.11989796
